Workbook

Sheet Sheet1
A1: s
A2: id | B2: Country | C2: City | D2: Line | E2: Phase | F2: Start year | G2: End year | H2: RR? | I2: Length | J2: TunnelPer | K2: Tunnel | L2: Elevated | M2: Atgrade | N2: Stations | O2: Platform Length (Meters) | P2: Source1 | Q2: Cost | R2: Currency | S2: Year | T2: PPP rate | U2: Real cost | V2: Cost/km (Millions) | W2: Cheap? | X2: Clength | Y2: Ctunnel | Z2: Anglo? | AA2: Inflation Index | AB2: Real cost (2025 dollars) | AC2: Cost/km (2025 dollars) | AD2: Source2 | AE2: Reference
A3: 8200 | B3: AE | C3: Dubai | D3: Phase 1 | E3: Phase 1 - Red Line | F3: 2005 | G3: 2010 | H3: 0 | I3: 35 | J3: =K3/I3 -> 0.13428571 | K3: 4.7 | L3: 0 | M3: 0 | N3: 29 | P3: Trade | Q3: 4200 | R3: USD | S3: 2005 | T3: 1.8 | U3: =Q3*T3 -> 7560 | V3: =U3/I3 -> 216 | W3: =IF(OR(B3 = "BG",B3 = "GR",B3 = "IT",B3 = "ES",B3 = "PT",B3 = "TR", B3 = "KR",B3 = "SE",B3 = "CH",B3 = "NO",B3 = "DK",B3 = "FI"), 1, 0) -> 0 | X3: =W3*I3 -> 0 | Y3: =W3*K3 -> 0 | Z3: =IF(OR(B3 = "US",B3 = "CA",B3 = "UK",B3 = "NZ",B3 = "AU",B3 = "SG"), 1, 0) -> 0 | AA3: =VLOOKUP(S3,CPI!$A$2:$F$71,6,0) -> 1.6493318 | AB3: =U3*AA3 -> 12468.948 | AC3: =V3*AA3 -> 356.25567
A4: 8201 | B4: AE | C4: Dubai | D4: Phase 2 | E4: Phase 2 - Green Line | F4: 2006 | G4: 2010 | H4: 0 | I4: 22.5 | J4: =K4/I4 -> 0.35111111 | K4: 7.9 | L4: 0 | M4: 0 | N4: 20 | Q4: 3600 | R4: USD | S4: 2006 | T4: 1.9 | U4: =Q4*T4 -> 6840 | V4: =U4/I4 -> 304 | W4: =IF(OR(B4 = "BG",B4 = "GR",B4 = "IT",B4 = "ES",B4 = "PT",B4 = "TR", B4 = "KR",B4 = "SE",B4 = "CH",B4 = "NO",B4 = "DK",B4 = "FI"), 1, 0) -> 0 | X4: =W4*I4 -> 0 | Y4: =W4*K4 -> 0 | Z4: =IF(OR(B4 = "US",B4 = "CA",B4 = "UK",B4 = "NZ",B4 = "AU",B4 = "SG"), 1, 0) -> 0 | AA4: =VLOOKUP(S4,CPI!$A$2:$F$71,6,0) -> 1.5977902 | AB4: =U4*AA4 -> 10928.885 | AC4: =V4*AA4 -> 485.72821
A5: 8202 | B5: AE | C5: Dubai | D5: Red Line | E5: Phase 3 (Red Line Extension/Route 2020) | F5: 2016 | G5: 2020 | H5: 0 | I5: 15 | J5: =K5/I5 -> 0.21333333 | K5: 3.2 | L5: 0 | M5: 0 | N5: 7 | P5: Trade | Q5: 2900 | R5: USD | S5: 2016 | T5: 1.9 | U5: =Q5*T5 -> 5510 | V5: =U5/I5 -> 367.33333 | W5: =IF(OR(B5 = "BG",B5 = "GR",B5 = "IT",B5 = "ES",B5 = "PT",B5 = "TR", B5 = "KR",B5 = "SE",B5 = "CH",B5 = "NO",B5 = "DK",B5 = "FI"), 1, 0) -> 0 | X5: =W5*I5 -> 0 | Y5: =W5*K5 -> 0 | Z5: =IF(OR(B5 = "US",B5 = "CA",B5 = "UK",B5 = "NZ",B5 = "AU",B5 = "SG"), 1, 0) -> 0 | AA5: =VLOOKUP(S5,CPI!$A$2:$F$71,6,0) -> 1.3421046 | AB5: =U5*AA5 -> 7394.9964 | AC5: =V5*AA5 -> 492.99976 | AD5: Media | AE5: https://www.railway-technology.com/projects/route-2020-dubai/
A6: 7593 | B6: AR | C6: Buenos Aires | D6: RER | E6: RER | F6: 2020 | G6: 2026 | H6: 1 | I6: 20 | J6: 1 | K6: 20 | L6: 0 | M6: 0 | N6: 4 | P6: Media | Q6: 2300 | R6: USD | S6: 2023 | T6: 2.02 | U6: =Q6*T6 -> 4646 | V6: =U6/I6 -> 232.3 | W6: =IF(OR(B6 = "BG",B6 = "GR",B6 = "IT",B6 = "ES",B6 = "PT",B6 = "TR", B6 = "KR",B6 = "SE",B6 = "CH",B6 = "NO",B6 = "DK",B6 = "FI"), 1, 0) -> 0 | X6: =W6*I6 -> 0 | Y6: =W6*K6 -> 0 | Z6: =IF(OR(B6 = "US",B6 = "CA",B6 = "UK",B6 = "NZ",B6 = "AU",B6 = "SG"), 1, 0) -> 0 | AA6: =VLOOKUP(S6,CPI!$A$2:$F$71,6,0) -> 1.057146 | AB6: =U6*AA6 -> 4911.5003 | AC6: =V6*AA6 -> 245.57502 | AD6: Media | AE6: https://tn.com.ar/economia/el-gobierno-relanzo-el-rer-el-proyecto-para-conectar-los-trenes-del-area-metropolitana_856411
A7: 9753 | B7: AT | C7: Vienna | D7: va | E7: Lainz Tunnel | F7: 1999 | G7: 2012 | H7: 1 | I7: 12.8 | J7: 1 | K7: 12.8 | L7: 0 | M7: 0 | N7: 0 | P7: Media | Q7: 1300 | R7: EUR | S7: 2005 | T7: 1.25 | U7: =Q7*T7 -> 1625 | V7: =U7/I7 -> 126.95312 | W7: =IF(OR(B7 = "BG",B7 = "GR",B7 = "IT",B7 = "ES",B7 = "PT",B7 = "TR", B7 = "KR",B7 = "SE",B7 = "CH",B7 = "NO",B7 = "DK",B7 = "FI"), 1, 0) -> 0 | X7: =W7*I7 -> 0 | Y7: =W7*K7 -> 0 | Z7: =IF(OR(B7 = "US",B7 = "CA",B7 = "UK",B7 = "NZ",B7 = "AU",B7 = "SG"), 1, 0) -> 0 | AA7: =VLOOKUP(S7,CPI!$A$2:$F$71,6,0) -> 1.6493318 | AB7: =U7*AA7 -> 2680.1642 | AC7: =V7*AA7 -> 209.38783 | AD7: Media | AE7: https://wien.orf.at/v2/news/stories/2537074/
A8: 7360 | B8: AT | C8: Vienna | D8: Line 2 | E8: Line 2 extension | F8: 2010 | G8: 2013 | H8: 0 | I8: 4.2 | J8: 0 | K8: 0 | L8: 2.63 | M8: 1.57 | N8: 3 | P8: Media | Q8: 320 | R8: EUR | S8: 2012 | T8: 1.3 | U8: =Q8*T8 -> 416 | V8: =U8/I8 -> 99.047619 | W8: =IF(OR(B8 = "BG",B8 = "GR",B8 = "IT",B8 = "ES",B8 = "PT",B8 = "TR", B8 = "KR",B8 = "SE",B8 = "CH",B8 = "NO",B8 = "DK",B8 = "FI"), 1, 0) -> 0 | X8: =W8*I8 -> 0 | Y8: =W8*K8 -> 0 | Z8: =IF(OR(B8 = "US",B8 = "CA",B8 = "UK",B8 = "NZ",B8 = "AU",B8 = "SG"), 1, 0) -> 0 | AA8: =VLOOKUP(S8,CPI!$A$2:$F$71,6,0) -> 1.4029744 | AB8: =U8*AA8 -> 583.63734 | AC8: =V8*AA8 -> 138.96127 | AD8: Media | AE8: https://wien.orf.at/news/stories/2607445/
A9: 7361 | B9: AT | C9: Vienna | D9: Line 1 | E9: Line 1 extension | F9: 2012 | G9: 2017 | H9: 0 | I9: 4.7 | J9: 0.57 | K9: 2.7 | L9: 0.06 | M9: 2.008 | N9: 5 | P9: Measured | Q9: 600 | R9: EUR | S9: 2015 | T9: 1.3 | U9: =Q9*T9 -> 780 | V9: =U9/I9 -> 165.95745 | W9: =IF(OR(B9 = "BG",B9 = "GR",B9 = "IT",B9 = "ES",B9 = "PT",B9 = "TR", B9 = "KR",B9 = "SE",B9 = "CH",B9 = "NO",B9 = "DK",B9 = "FI"), 1, 0) -> 0 | X9: =W9*I9 -> 0 | Y9: =W9*K9 -> 0 | Z9: =IF(OR(B9 = "US",B9 = "CA",B9 = "UK",B9 = "NZ",B9 = "AU",B9 = "SG"), 1, 0) -> 0 | AA9: =VLOOKUP(S9,CPI!$A$2:$F$71,6,0) -> 1.3590354 | AB9: =U9*AA9 -> 1060.0476 | AC9: =V9*AA9 -> 225.54205 | AD9: Plan | AE9: https://www.wien.gv.at/stadtentwicklung/projekte/verkehrsplanung/u-bahn/u1-oberlaa.html
A10: 7362 | B10: AT | C10: Vienna | D10: U2/U5 cross | E10: U2/U5 cross | F10: 2019 | G10: 2029 | H10: 0 | I10: 9 | J10: 1 | K10: 9 | L10: 0 | M10: 0 | N10: 11 | P10: Plan | Q10: 2200 | R10: EUR | S10: 2023 | T10: 1.3 | U10: =Q10*T10 -> 2860 | V10: =U10/I10 -> 317.77778 | W10: =IF(OR(B10 = "BG",B10 = "GR",B10 = "IT",B10 = "ES",B10 = "PT",B10 = "TR", B10 = "KR",B10 = "SE",B10 = "CH",B10 = "NO",B10 = "DK",B10 = "FI"), 1, 0) -> 0 | X10: =W10*I10 -> 0 | Y10: =W10*K10 -> 0 | Z10: =IF(OR(B10 = "US",B10 = "CA",B10 = "UK",B10 = "NZ",B10 = "AU",B10 = "SG"), 1, 0) -> 0 | AA10: =VLOOKUP(S10,CPI!$A$2:$F$71,6,0) -> 1.057146 | AB10: =U10*AA10 -> 3023.4376 | AC10: =V10*AA10 -> 335.93751 | AD10: Media | AE10: https://wien.orf.at/news/stories/2940360/
A11: 7280 | B11: AU | C11: Melbourne | D11: Metro Tunnel | E11: Metro Tunnel | F11: 2018 | G11: 2025 | H11: 0 | I11: 9 | J11: 1 | K11: 9 | L11: 0 | M11: 0 | N11: 5 | P11: Plan | Q11: 12584.4 | R11: AUD | S11: 2021 | T11: 0.69 | U11: =Q11*T11 -> 8683.236 | V11: =U11/I11 -> 964.804 | W11: =IF(OR(B11 = "BG",B11 = "GR",B11 = "IT",B11 = "ES",B11 = "PT",B11 = "TR", B11 = "KR",B11 = "SE",B11 = "CH",B11 = "NO",B11 = "DK",B11 = "FI"), 1, 0) -> 0 | X11: =W11*I11 -> 0 | Y11: =W11*K11 -> 0 | Z11: =IF(OR(B11 = "US",B11 = "CA",B11 = "UK",B11 = "NZ",B11 = "AU",B11 = "SG"), 1, 0) -> 1 | AA11: =VLOOKUP(S11,CPI!$A$2:$F$71,6,0) -> 1.188746 | AB11: =U11*AA11 -> 10322.162 | AC11: =V11*AA11 -> 1146.9069 | AD11: Plan | AE11: https://www.audit.vic.gov.au/report/melbourne-metro-tunnel-project-phase-2-main-works?section=
A12: 7587 | B12: AU | C12: Perth | D12: Forrestfield-Airport Link | E12: Forrestfield-Airport Link | F12: 2016 | G12: 2021 | H12: 1 | I12: 8.5 | J12: 1 | K12: 8.5 | L12: 0 | M12: 0 | N12: 3 | P12: Plan | Q12: 1860 | R12: AUD | S12: 2018 | T12: 0.69 | U12: =Q12*T12 -> 1283.4 | V12: =U12/I12 -> 150.98824 | W12: =IF(OR(B12 = "BG",B12 = "GR",B12 = "IT",B12 = "ES",B12 = "PT",B12 = "TR", B12 = "KR",B12 = "SE",B12 = "CH",B12 = "NO",B12 = "DK",B12 = "FI"), 1, 0) -> 0 | X12: =W12*I12 -> 0 | Y12: =W12*K12 -> 0 | Z12: =IF(OR(B12 = "US",B12 = "CA",B12 = "UK",B12 = "NZ",B12 = "AU",B12 = "SG"), 1, 0) -> 1 | AA12: =VLOOKUP(S12,CPI!$A$2:$F$71,6,0) -> 1.2827779 | AB12: =U12*AA12 -> 1646.3171 | AC12: =V12*AA12 -> 193.68437 | AD12: Plan | AE12: https://www.forrestfieldairportlink.wa.gov.au/Portals/14/Project%20Overview%20Fact%20Sheet%20-%20Dec18%20WEB.pdf
A13: 7275 | B13: AU | C13: Sydney | D13: Metro NW | E13: Metro NW | F13: 2013 | G13: 2019 | H13: 0 | I13: 36 | J13: 0.42 | K13: 15.1 | L13: 0 | M13: 0 | N13: 13 | P13: Wiki | Q13: 7800 | R13: AUD | S13: 2016 | T13: 0.69 | U13: =Q13*T13 -> 5382 | V13: =U13/I13 -> 149.5 | W13: =IF(OR(B13 = "BG",B13 = "GR",B13 = "IT",B13 = "ES",B13 = "PT",B13 = "TR", B13 = "KR",B13 = "SE",B13 = "CH",B13 = "NO",B13 = "DK",B13 = "FI"), 1, 0) -> 0 | X13: =W13*I13 -> 0 | Y13: =W13*K13 -> 0 | Z13: =IF(OR(B13 = "US",B13 = "CA",B13 = "UK",B13 = "NZ",B13 = "AU",B13 = "SG"), 1, 0) -> 1 | AA13: =VLOOKUP(S13,CPI!$A$2:$F$71,6,0) -> 1.3421046 | AB13: =U13*AA13 -> 7223.207 | AC13: =V13*AA13 -> 200.64464 | AD13: Plan | AE13: https://www.transport.nsw.gov.au/news-and-events/media-releases/sydney-metro-northwest-under-budget
A14: 7274 | B14: AU | C14: Sydney | D14: Metro City & SW | E14: Metro City & SW | F14: 2017 | G14: 2024 | H14: 0 | I14: 30 | J14: 0.51 | K14: 15.3 | L14: 0 | M14: 0 | N14: 7 | P14: Wiki | Q14: 15500 | R14: AUD | S14: 2021 | T14: 0.69 | U14: =Q14*T14 -> 10695 | V14: =U14/I14 -> 356.5 | W14: =IF(OR(B14 = "BG",B14 = "GR",B14 = "IT",B14 = "ES",B14 = "PT",B14 = "TR", B14 = "KR",B14 = "SE",B14 = "CH",B14 = "NO",B14 = "DK",B14 = "FI"), 1, 0) -> 0 | X14: =W14*I14 -> 0 | Y14: =W14*K14 -> 0 | Z14: =IF(OR(B14 = "US",B14 = "CA",B14 = "UK",B14 = "NZ",B14 = "AU",B14 = "SG"), 1, 0) -> 1 | AA14: =VLOOKUP(S14,CPI!$A$2:$F$71,6,0) -> 1.188746 | AB14: =U14*AA14 -> 12713.638 | AC14: =V14*AA14 -> 423.78794 | AD14: Media | AE14: https://www.abc.net.au/news/2020-02-21/nsw-government-confirms-three-billion-metro-budget-blowout/11986968
A15: 7464 | B15: BD | C15: Dhaka | D15: Line 6 | E15: Line 6 | F15: 2015 | G15: 2022 | H15: 0 | I15: 21.3 | J15: 0 | K15: 0 | L15: 0 | M15: 0 | N15: 16 | P15: Media | Q15: 334720 | R15: BDT | S15: 2019 | T15: 0.032 | U15: =Q15*T15 -> 10711.04 | V15: =U15/I15 -> 502.86573 | W15: =IF(OR(B15 = "BG",B15 = "GR",B15 = "IT",B15 = "ES",B15 = "PT",B15 = "TR", B15 = "KR",B15 = "SE",B15 = "CH",B15 = "NO",B15 = "DK",B15 = "FI"), 1, 0) -> 0 | X15: =W15*I15 -> 0 | Y15: =W15*K15 -> 0 | Z15: =IF(OR(B15 = "US",B15 = "CA",B15 = "UK",B15 = "NZ",B15 = "AU",B15 = "SG"), 1, 0) -> 0 | AA15: =VLOOKUP(S15,CPI!$A$2:$F$71,6,0) -> 1.2599479 | AB15: =U15*AA15 -> 13495.352 | AC15: =V15*AA15 -> 633.58462 | AD15: Media | AE15: https://www.thedailystar.net/news/bangladesh/transport/news/metro-now-set-cost-50pc-more-3072816
A16: 7465 | B16: BD | C16: Dhaka | D16: Line 1 | E16: Line 1 | F16: 2020 | G16: 2026 | H16: 0 | I16: 31.2 | J16: 0.64 | K16: 19.9 | L16: 0 | M16: 0 | N16: 19 | P16: Media | Q16: 525610 | R16: BDT | S16: 2023 | T16: 0.032 | U16: =Q16*T16 -> 16819.52 | V16: =U16/I16 -> 539.08718 | W16: =IF(OR(B16 = "BG",B16 = "GR",B16 = "IT",B16 = "ES",B16 = "PT",B16 = "TR", B16 = "KR",B16 = "SE",B16 = "CH",B16 = "NO",B16 = "DK",B16 = "FI"), 1, 0) -> 0 | X16: =W16*I16 -> 0 | Y16: =W16*K16 -> 0 | Z16: =IF(OR(B16 = "US",B16 = "CA",B16 = "UK",B16 = "NZ",B16 = "AU",B16 = "SG"), 1, 0) -> 0 | AA16: =VLOOKUP(S16,CPI!$A$2:$F$71,6,0) -> 1.057146 | AB16: =U16*AA16 -> 17780.688 | AC16: =V16*AA16 -> 569.89385 | AD16: Media | AE16: https://bdnews24.com/economy/2019/10/15/govt-approves-two-more-metro-rail-projects-worth-tk-938bn
A17: 7466 | B17: BD | C17: Dhaka | D17: Line 5 | E17: Line 5 | F17: 2020 | G17: 2028 | H17: 0 | I17: 19.6 | J17: 0.7 | K17: 14 | L17: 0 | M17: 0 | N17: 14 | P17: Media | Q17: 412380 | R17: BDT | S17: 2024 | T17: 0.032 | U17: =Q17*T17 -> 13196.16 | V17: =U17/I17 -> 673.27347 | W17: =IF(OR(B17 = "BG",B17 = "GR",B17 = "IT",B17 = "ES",B17 = "PT",B17 = "TR", B17 = "KR",B17 = "SE",B17 = "CH",B17 = "NO",B17 = "DK",B17 = "FI"), 1, 0) -> 0 | X17: =W17*I17 -> 0 | Y17: =W17*K17 -> 0 | Z17: =IF(OR(B17 = "US",B17 = "CA",B17 = "UK",B17 = "NZ",B17 = "AU",B17 = "SG"), 1, 0) -> 0 | AA17: =VLOOKUP(S17,CPI!$A$2:$F$71,6,0) -> 1 | AB17: =U17*AA17 -> 13196.16 | AC17: =V17*AA17 -> 673.27347 | AD17: Media | AE17: https://bdnews24.com/economy/2019/10/15/govt-approves-two-more-metro-rail-projects-worth-tk-938bn
... A23: 7177 | B23: BG | C23: Sofia | D23: Line 3 | E23: Line 3 extension (Third Stage) | F23: 2021 | G23: 2026 | H23: 0 | I23: 3.1 | J23: 1 | K23: 3.1 | L23: 0 | M23: 0 | N23: 4 | P23: Plan | Q23: 112.5 | R23: EUR | S23: 2021 | T23: 3.32 | U23: =Q23*T23 -> 373.5 | V23: =U23/I23 -> 120.48387 | W23: =IF(OR(B23 = "BG",B23 = "GR",B23 = "IT",B23 = "ES",B23 = "PT",B23 = "TR", B23 = "KR",B23 = "SE",B23 = "CH",B23 = "NO",B23 = "DK",B23 = "FI"), 1, 0) -> 1 | X23: =W23*I23 -> 3.1 | Y23: =W23*K23 -> 3.1 | Z23: =IF(OR(B23 = "US",B23 = "CA",B23 = "UK",B23 = "NZ",B23 = "AU",B23 = "SG"), 1, 0) -> 0 | AA23: =VLOOKUP(S23,CPI!$A$2:$F$71,6,0) -> 1.188746 | AB23: =U23*AA23 -> 443.99663 | AC23: =V23*AA23 -> 143.22472 | AD23: Trade | AE23: https://seenews.com/news/sofia-opens-1125-mln-euro-tender-for-subway-expansion-681553
A24: 7168 | B24: BG | C24: Sofia | D24: Line 1 | E24: Line 1 northern | F24: 2009 | G24: cond | H24: 0 | I24: 5.1 | J24: 0.6 | K24: 3.1 | L24: 0 | M24: 0 | N24: 4 | P24: Measured | Q24: 407 | R24: BGN | S24: 2010 | T24: 1.69 | U24: =Q24*T24 -> 687.83 | V24: =U24/I24 -> 134.86863 | W24: =IF(OR(B24 = "BG",B24 = "GR",B24 = "IT",B24 = "ES",B24 = "PT",B24 = "TR", B24 = "KR",B24 = "SE",B24 = "CH",B24 = "NO",B24 = "DK",B24 = "FI"), 1, 0) -> 1 | X24: =W24*I24 -> 5.1 | Y24: =W24*K24 -> 3.1 | Z24: =IF(OR(B24 = "US",B24 = "CA",B24 = "UK",B24 = "NZ",B24 = "AU",B24 = "SG"), 1, 0) -> 0 | AA24: =VLOOKUP(S24,CPI!$A$2:$F$71,6,0) -> 1.47721 | AB24: =U24*AA24 -> 1016.0693 | AC24: =V24*AA24 -> 199.22928 | AD24: Media | AE24: https://www.novinite.com/articles/167648/Subway+Trains+to+Sofia+Airport+Start+Running+at+1+pm+on+April+2
A25: 8194 | B25: BH | C25: Bahrain | D25: Phase 1 | E25: Phase 1 (Red & Blue) | F25: 2018 | G25: 2023 | H25: 1 | I25: 28.6 | J25: =K25/I25 -> 0 | K25: 0 | L25: 0 | M25: 0 | N25: 20 | Q25: 453 | R25: BD | S25: 2019 | T25: =1/0.2 -> 5 | U25: =Q25*T25 -> 2265 | V25: =U25/I25 -> 79.195804 | W25: =IF(OR(B25 = "BG",B25 = "GR",B25 = "IT",B25 = "ES",B25 = "PT",B25 = "TR", B25 = "KR",B25 = "SE",B25 = "CH",B25 = "NO",B25 = "DK",B25 = "FI"), 1, 0) -> 0 | X25: =W25*I25 -> 0 | Y25: =W25*K25 -> 0 | Z25: =IF(OR(B25 = "US",B25 = "CA",B25 = "UK",B25 = "NZ",B25 = "AU",B25 = "SG"), 1, 0) -> 0 | AA25: =VLOOKUP(S25,CPI!$A$2:$F$71,6,0) -> 1.2599479 | AB25: =U25*AA25 -> 2853.782 | AC25: =V25*AA25 -> 99.782587 | AD25: Media | AE25: https://www.urbantransportnews.com/bahrain-to-finalise-109-km-light-metro-rail-bids-in-march-2020/
A26: 8195 | B26: BH | C26: Bahrain | D26: Phase 2 | E26: Phase 2 | F26: 2020 | G26: X | H26: 1 | I26: 72.7 | J26: =K26/I26 -> 0 | K26: 0 | L26: 0 | M26: 0 | Q26: 1500 | R26: BD | S26: 2010 | T26: =1/0.2 -> 5 | U26: =Q26*T26 -> 7500 | V26: =U26/I26 -> 103.16369 | W26: =IF(OR(B26 = "BG",B26 = "GR",B26 = "IT",B26 = "ES",B26 = "PT",B26 = "TR", B26 = "KR",B26 = "SE",B26 = "CH",B26 = "NO",B26 = "DK",B26 = "FI"), 1, 0) -> 0 | X26: =W26*I26 -> 0 | Y26: =W26*K26 -> 0 | Z26: =IF(OR(B26 = "US",B26 = "CA",B26 = "UK",B26 = "NZ",B26 = "AU",B26 = "SG"), 1, 0) -> 0 | AA26: =VLOOKUP(S26,CPI!$A$2:$F$71,6,0) -> 1.47721 | AB26: =U26*AA26 -> 11079.075 | AC26: =V26*AA26 -> 152.39443 | AD26: Media | AE26: http://www.tradearabia.com/news/stn_178416.html
A27: 9754 | B27: BR | C27: Rio de Janeiro | D27: Line 4 | E27: Line 4 | F27: 2010 | G27: 2016 | H27: 0 | I27: 16 | J27: 0.96 | K27: 15.4 | L27: 0 | M27: 0 | N27: 7 | P27: Measured | Q27: 10300 | R27: BRL | S27: 2013 | T27: 0.59 | U27: =Q27*T27 -> 6077 | V27: =U27/I27 -> 379.8125 | W27: =IF(OR(B27 = "BG",B27 = "GR",B27 = "IT",B27 = "ES",B27 = "PT",B27 = "TR", B27 = "KR",B27 = "SE",B27 = "CH",B27 = "NO",B27 = "DK",B27 = "FI"), 1, 0) -> 0 | X27: =W27*I27 -> 0 | Y27: =W27*K27 -> 0 | Z27: =IF(OR(B27 = "US",B27 = "CA",B27 = "UK",B27 = "NZ",B27 = "AU",B27 = "SG"), 1, 0) -> 0 | AA27: =VLOOKUP(S27,CPI!$A$2:$F$71,6,0) -> 1.3827208 | AB27: =U27*AA27 -> 8402.7946 | AC27: =V27*AA27 -> 525.17466 | AD27: Trade | AE27: http://itdpbrasil.org.br/wp-content/uploads/2018/05/ITDP_PP_Linha_4_Maio_2018.pdf
A28: 7344 | B28: BR | C28: Salvador | D28: Lines 1-2 | E28: Lines 1-2 | F28: 2000 | G28: 2017 | H28: 0 | I28: 33 | J28: 0.04 | K28: 1.4 | L28: 10.935 | M28: 20.745 | N28: 20 | P28: Wiki | Q28: 4800 | R28: BRL | S28: 2012 | T28: 0.62 | U28: =Q28*T28 -> 2976 | V28: =U28/I28 -> 90.181818 | W28: =IF(OR(B28 = "BG",B28 = "GR",B28 = "IT",B28 = "ES",B28 = "PT",B28 = "TR", B28 = "KR",B28 = "SE",B28 = "CH",B28 = "NO",B28 = "DK",B28 = "FI"), 1, 0) -> 0 | X28: =W28*I28 -> 0 | Y28: =W28*K28 -> 0 | Z28: =IF(OR(B28 = "US",B28 = "CA",B28 = "UK",B28 = "NZ",B28 = "AU",B28 = "SG"), 1, 0) -> 0 | AA28: =VLOOKUP(S28,CPI!$A$2:$F$71,6,0) -> 1.4029744 | AB28: =U28*AA28 -> 4175.2518 | AC28: =V28*AA28 -> 126.52278 | AD28: Media | AE28: http://patrocinados.estadao.com.br/ccr/salvadors-subway-becomes-a-model-of-success/
A29: 9755 | B29: BR | C29: Salvador | D29: SkyRail Bahia | E29: SkyRail Bahia | F29: 2020 | G29: 2022 | H29: 0 | I29: 23.3 | J29: 0 | K29: 0 | L29: 0 | M29: 0 | N29: 26 | P29: Trade | Q29: 689 | R29: USD | S29: 2021 | T29: 2.3 | U29: =Q29*T29 -> 1584.7 | V29: =U29/I29 -> 68.012876 | W29: =IF(OR(B29 = "BG",B29 = "GR",B29 = "IT",B29 = "ES",B29 = "PT",B29 = "TR", B29 = "KR",B29 = "SE",B29 = "CH",B29 = "NO",B29 = "DK",B29 = "FI"), 1, 0) -> 0 | X29: =W29*I29 -> 0 | Y29: =W29*K29 -> 0 | Z29: =IF(OR(B29 = "US",B29 = "CA",B29 = "UK",B29 = "NZ",B29 = "AU",B29 = "SG"), 1, 0) -> 0 | AA29: =VLOOKUP(S29,CPI!$A$2:$F$71,6,0) -> 1.188746 | AB29: =U29*AA29 -> 1883.8058 | AC29: =V29*AA29 -> 80.850033 | AD29: Trade | AE29: https://www.yicaiglobal.com/news/byd-design-for-usd689-million-brazil-monorail-gets-green-light
A30: 7339 | B30: BR | C30: Sao Paulo | D30: Line 5 | E30: Line 5 extension | F30: 2010 | G30: 2019 | H30: 0 | I30: 12 | J30: 1 | K30: 12 | L30: 0 | M30: 0 | N30: 11 | P30: Wiki | Q30: 6900 | R30: BRL | S30: 2014 | T30: 0.55 | U30: =Q30*T30 -> 3795 | V30: =U30/I30 -> 316.25 | W30: =IF(OR(B30 = "BG",B30 = "GR",B30 = "IT",B30 = "ES",B30 = "PT",B30 = "TR", B30 = "KR",B30 = "SE",B30 = "CH",B30 = "NO",B30 = "DK",B30 = "FI"), 1, 0) -> 0 | X30: =W30*I30 -> 0 | Y30: =W30*K30 -> 0 | Z30: =IF(OR(B30 = "US",B30 = "CA",B30 = "UK",B30 = "NZ",B30 = "AU",B30 = "SG"), 1, 0) -> 0 | AA30: =VLOOKUP(S30,CPI!$A$2:$F$71,6,0) -> 1.3606486 | AB30: =U30*AA30 -> 5163.6613 | AC30: =V30*AA30 -> 430.30511 | AD30: Trade | AE30: https://www.bnamericas.com/en/news/brazil-metro-cost-overruns-top-us9bn1
A31: 9756 | B31: BR | C31: Sao Paulo | D31: Line 17 | E31: Line 17 | F31: 2012 | G31: 2021 | H31: 0 | I31: 7.7 | J31: 0 | K31: 0 | L31: 0 | M31: 0 | N31: 8 | P31: Trade | Q31: 1300 | R31: USD | S31: 2016 | T31: 2.3 | U31: =Q31*T31 -> 2990 | V31: =U31/I31 -> 388.31169 | W31: =IF(OR(B31 = "BG",B31 = "GR",B31 = "IT",B31 = "ES",B31 = "PT",B31 = "TR", B31 = "KR",B31 = "SE",B31 = "CH",B31 = "NO",B31 = "DK",B31 = "FI"), 1, 0) -> 0 | X31: =W31*I31 -> 0 | Y31: =W31*K31 -> 0 | Z31: =IF(OR(B31 = "US",B31 = "CA",B31 = "UK",B31 = "NZ",B31 = "AU",B31 = "SG"), 1, 0) -> 0 | AA31: =VLOOKUP(S31,CPI!$A$2:$F$71,6,0) -> 1.3421046 | AB31: =U31*AA31 -> 4012.8928 | AC31: =V31*AA31 -> 521.15491 | AD31: Trade | AE31: https://www.railjournal.com/in_depth/21-rail-projects-to-watch-in-2021
A32: 7528 | B32: BR | C32: Sao Paulo | D32: Line 6 | E32: Line 6 phase 1 | F32: 2015 | G32: 2023 | H32: 0 | I32: 15.9 | J32: 0.84 | K32: 13.4 | L32: 0 | M32: 0 | N32: 15 | P32: Trade | Q32: 9600 | R32: BRL | S32: 2020 | T32: 0.44 | U32: =Q32*T32 -> 4224 | V32: =U32/I32 -> 265.66038 | W32: =IF(OR(B32 = "BG",B32 = "GR",B32 = "IT",B32 = "ES",B32 = "PT",B32 = "TR", B32 = "KR",B32 = "SE",B32 = "CH",B32 = "NO",B32 = "DK",B32 = "FI"), 1, 0) -> 0 | X32: =W32*I32 -> 0 | Y32: =W32*K32 -> 0 | Z32: =IF(OR(B32 = "US",B32 = "CA",B32 = "UK",B32 = "NZ",B32 = "AU",B32 = "SG"), 1, 0) -> 0 | AA32: =VLOOKUP(S32,CPI!$A$2:$F$71,6,0) -> 1.2445935 | AB32: =U32*AA32 -> 5257.1631 | AC32: =V32*AA32 -> 330.63919 | AD32: Trade | AE32: https://www.railjournal.com/passenger/metros/revival-of-sao-paulo-metro-line-6-orange-project-a-step-closer/
A33: 9761 | B33: CA | C33: Calgary | D33: Green Line | E33: Green Line stage 1 | F33: 2021 | G33: 2027 | H33: 0 | I33: 20 | J33: 0.2 | K33: 4 | L33: 0 | M33: 0 | N33: 15 | P33: Wiki | Q33: 5500 | R33: CAD | S33: 2024 | T33: 0.84 | U33: =Q33*T33 -> 4620 | V33: =U33/I33 -> 231 | W33: =IF(OR(B33 = "BG",B33 = "GR",B33 = "IT",B33 = "ES",B33 = "PT",B33 = "TR", B33 = "KR",B33 = "SE",B33 = "CH",B33 = "NO",B33 = "DK",B33 = "FI"), 1, 0) -> 0 | X33: =W33*I33 -> 0 | Y33: =W33*K33 -> 0 | Z33: =IF(OR(B33 = "US",B33 = "CA",B33 = "UK",B33 = "NZ",B33 = "AU",B33 = "SG"), 1, 0) -> 1 | AA33: =VLOOKUP(S33,CPI!$A$2:$F$71,6,0) -> 1 | AB33: =U33*AA33 -> 4620 | AC33: =V33*AA33 -> 231 | AD33: Media | AE33: https://globalnews.ca/news/7527443/green-line-lrt-calgary-alberta-government/
A34: 7106 | B34: CA | C34: Calgary | D34: Blue Line Extension | E34: Northeast | F34: 2027 | G34: ~ | H34: 0 | I34: 1 | J34: 0 | K34: 0 | L34: 0 | M34: 1 | N34: 1 | O34: 40 | P34: Plan | Q34: 160.6 | R34: CAD | S34: 2027 | T34: 1 | U34: =Q34*T34 -> 160.6 | V34: =U34/I34 -> 160.6 | W34: =IF(OR(B34 = "BG",B34 = "GR",B34 = "IT",B34 = "ES",B34 = "PT",B34 = "TR", B34 = "KR",B34 = "SE",B34 = "CH",B34 = "NO",B34 = "DK",B34 = "FI"), 1, 0) -> 0 | X34: =W34*I34 -> 0 | Y34: =W34*K34 -> 0 | Z34: 1 | AA34: =VLOOKUP(S34,CPI!$A$2:$F$71,6,0) -> 1 | AB34: =U34*AA34 -> 160.6 | AC34: =V34*AA34 -> 160.6
B35: CA | C35: Edmonton | D35: Valley Line Southeast | E35: Southeast | F35: 2016 | G35: 2023 | H35: 0 | I35: 13.1 | J35: 0.03 | K35: 0.4 | N35: 12 | O35: 125 | P35: Wiki | Q35: 1800 | R35: CAD | S35: 2019 | T35: 0.802 | U35: =Q35*T35 -> 1443.6 | V35: =U35/I35 -> 110.19847 | W35: =IF(OR(B35 = "BG",B35 = "GR",B35 = "IT",B35 = "ES",B35 = "PT",B35 = "TR", B35 = "KR",B35 = "SE",B35 = "CH",B35 = "NO",B35 = "DK",B35 = "FI"), 1, 0) -> 0 | X35: =W35*I35 -> 0 | Y35: =W35*K35 -> 0 | Z35: =IF(OR(B35 = "US",B35 = "CA",B35 = "UK",B35 = "NZ",B35 = "AU",B35 = "SG"), 1, 0) -> 1 | AA35: =VLOOKUP(S35,CPI!$A$2:$F$71,6,0) -> 1.2599479 | AB35: =U35*AA35 -> 1818.8608 | AC35: =V35*AA35 -> 138.84433 | AD35: Media | AE35: https://edmontonjournal.com/news/local-news/long-delayed-1-8-billion-valley-line-lrt-stymied-yet-again
A36: 7104 | B36: CA | C36: Edmonton | D36: Metro Line Extension | E36: Northwest Phase 1 | F36: 2020 | G36: 2024 | H36: 0 | I36: 1.6 | J36: 0 | K36: 0 | L36: 0 | M36: 1.6 | N36: 2 | O36: 125 | P36: Plan | Q36: 291 | R36: CAD | S36: 2020 | T36: 0.81 | U36: =Q36*T36 -> 235.71 | V36: =U36/I36 -> 147.31875 | Z36: 1 | AA36: =VLOOKUP(S36,CPI!$A$2:$F$71,6,0) -> 1.2445935 | AB36: =U36*AA36 -> 293.36314 | AC36: =V36*AA36 -> 183.35197 | AE36: https://www.edmonton.ca/projects_plans/transit/nw-lrt https://tam-america.com/article/edmonton-metro-northwest-lrt-extension-phase-completed-on-budget-before-time#:~:text=Phase%201%20construction%20was%20originally,million%20(US%24215%20million).
A37: 7103 | B37: CA | C37: Edmonton | D37: Valley Line Extension | E37: West | F37: 2022 | G37: 2028 | H37: 0 | I37: 14 | J37: 0 | K37: 0 | L37: 2.1 | M37: =14-2.1 -> 11.9 | N37: 14 | O37: 125 | P37: Plan | Q37: 2700 | R37: CAD | S37: 2022 | T37: 0.88 | U37: =Q37*T37 -> 2376 | V37: =U37/I37 -> 169.71429 | W37: 0 | Z37: 1 | AA37: =VLOOKUP(S37,CPI!$A$2:$F$71,6,0) -> 1.1006629 | AB37: =U37*AA37 -> 2615.175 | AC37: =V37*AA37 -> 186.79822 | AD37: Media | AE37: https://majorprojects.alberta.ca/details/Valley-Line-West-LRT/3692 https://www.operis.com/case-study/edmonton-valley-line-west/
A38: 7116 | B38: CA | C38: Hamilton | D38: Hamilton LRT | E38: Phase 1 | F38: 2025 | G38: 2029 | H38: 0 | I38: 14 | J38: 0 | K38: 0 | L38: 0 | M38: 14 | N38: 17 | O38: 50 | P38: Plan | Q38: 3400 | R38: CAD | S38: 2025 | T38: 1 | U38: =Q38*T38 -> 3400 | V38: =U38/I38 -> 242.85714 | AA38: =VLOOKUP(S38,CPI!$A$2:$F$71,6,0) -> 1 | AB38: =U38*AA38 -> 3400 | AC38: =V38*AA38 -> 242.85714 | AD38: Media | AE38: https://www.metrolinx.com/en/projects-and-programs/hamilton-lrt https://canada.constructconnect.com/dcn/news/infrastructure/2024/11/request-for-qualifications-issued-for-hamilton-lrt-project
A39: 7114 | B39: CA | C39: Mississauga | D39: Hazel McCallion LRT | E39: Phase 1 | F39: 2020 | G39: 2027 | H39: 0 | I39: 18 | J39: =(1/19)% -> 0.00052631579 | K39: 1 | M39: 18 | N39: 19 | O39: 50 | P39: Plan | Q39: 4700 | R39: CAD | S39: 2020 | T39: 0.84 | U39: =Q39*T39 -> 3948 | V39: =U39/I39 -> 219.33333 | AA39: =VLOOKUP(S39,CPI!$A$2:$F$71,6,0) -> 1.2445935 | AB39: =U39*AA39 -> 4913.6553 | AC39: =V39*AA39 -> 272.98085 | AD39: Media | AE39: https://www.metrolinx.com/en/projects-and-programs/hazel-mccallion-lrt/faqs
A40: 7401 | B40: CA | C40: Montreal | D40: Laval extension | E40: Laval extension | F40: 2001 | G40: 2007 | H40: 0 | I40: 5.2 | J40: 1 | K40: 5.2 | L40: 0 | M40: 0 | N40: 3 | P40: Wiki | Q40: 745 | R40: CAD | S40: 2004 | T40: 0.81 | U40: =Q40*T40 -> 603.45 | V40: =U40/I40 -> 116.04808 | W40: =IF(OR(B40 = "BG",B40 = "GR",B40 = "IT",B40 = "ES",B40 = "PT",B40 = "TR", B40 = "KR",B40 = "SE",B40 = "CH",B40 = "NO",B40 = "DK",B40 = "FI"), 1, 0) -> 0 | X40: =W40*I40 -> 0 | Y40: =W40*K40 -> 0 | Z40: =IF(OR(B40 = "US",B40 = "CA",B40 = "UK",B40 = "NZ",B40 = "AU",B40 = "SG"), 1, 0) -> 1 | AA40: =VLOOKUP(S40,CPI!$A$2:$F$71,6,0) -> 1.7052118 | AB40: =U40*AA40 -> 1029.01 | AC40: =V40*AA40 -> 197.88654 | AD40: Media | AE40: https://montrealgazette.com/news/local-news/the-sleepy-success-story-of-the-laval-metro-extension
A41: 7146 | B41: CA | C41: Montreal | D41: Blue Line | E41: Blue Line | F41: 2020 | G41: 2026 | H41: 0 | I41: 5.8 | J41: 1 | K41: 5.8 | L41: 0 | M41: 0 | N41: 5 | P41: Media | Q41: 7600 | R41: CAD | S41: 2018 | T41: 0.84 | U41: =Q41*T41 -> 6384 | V41: =U41/I41 -> 1100.6897 | W41: =IF(OR(B41 = "BG",B41 = "GR",B41 = "IT",B41 = "ES",B41 = "PT",B41 = "TR", B41 = "KR",B41 = "SE",B41 = "CH",B41 = "NO",B41 = "DK",B41 = "FI"), 1, 0) -> 0 | X41: =W41*I41 -> 0 | Y41: =W41*K41 -> 0 | Z41: =IF(OR(B41 = "US",B41 = "CA",B41 = "UK",B41 = "NZ",B41 = "AU",B41 = "SG"), 1, 0) -> 1 | AA41: =VLOOKUP(S41,CPI!$A$2:$F$71,6,0) -> 1.2827779 | AB41: =U41*AA41 -> 8189.2539 | AC41: =V41*AA41 -> 1411.9403 | AD41: Media | AE41: https://montrealgazette.com/news/local-news/montreal-metro-green-light-for-blue-line-extension https://www.cbc.ca/news/canada/montreal/blue-line-extension-delayed-1.7303767
A42: 7130 | B42: CA | C42: Montreal | D42: PSE | E42: Phase 1 | F42: 2025 | G42: 2033 | H42: 0 | I42: 31 | J42: 0 | K42: 0 | L42: 0 | M42: 31 | N42: 36/22 | P42: Plan | Q42: 19000 | R42: CAD | S42: 2025 | T42: 1 | U42: 19000 | V42: =U42/I42 -> 612.90323 | Z42: 0 | AA42: =VLOOKUP(S42,CPI!$A$2:$F$71,6,0) -> 1 | AB42: =U42*AA42 -> 19000 | AC42: =V42*AA42 -> 612.90323 | AD42: Media | AE42: https://www.cbc.ca/news/canada/montreal/public-transit-project-announcement-eastern-montreal-1.7475018 https://www.artm.quebec/wp-content/uploads/2024/05/RP_PSE_AC_VFinale_2024-05-28.pdf
A43: 7125 | B43: CA | C43: Montreal | D43: REM | E43: Current Project Scope | F43: 2018 | G43: 2027 | H43: 0 | I43: 67 | J43: =10.5/67 -> 0.15671642 | K43: 10.5 | L43: 16.3 | M43: 36.7 | N43: 24 | O43: 26 | P43: Plan | Q43: 9400 | R43: CAD | S43: 2018 | T43: 0.84 | U43: =Q43*T43 -> 7896 | V43: =U43/I43 -> 117.85075 | W43: 0 | X43: =W43*I43 -> 0 | Y43: =X43*J43 -> 0 | Z43: 1 | AA43: =VLOOKUP(S43,CPI!$A$2:$F$71,6,0) -> 1.2827779 | AB43: =U43*AA43 -> 10128.814 | AC43: =V43*AA43 -> 151.17633 | AD43: Media | AE43: https://scfp.ca/sites/default/files/ppp201700191_ppp_canada_rem_01_01_2016_part2-opt_0.pdf https://montreal.citynews.ca/2024/11/20/quebec-educational-gap-indigenous-students-auditor-general-report/
A44: 7117 | B44: CA | C44: Ottawa | D44: Confederation | E44: Confederation | F44: 2013 | G44: 2019 | H44: 0 | I44: 12.5 | J44: 0.2 | K44: 2.5 | L44: 0.84 | M44: 9.16 | N44: 13 | O44: 90/120 | P44: Trade | Q44: 2100 | R44: CAD | S44: 2016 | T44: 0.83 | U44: =Q44*T44 -> 1743 | V44: =U44/I44 -> 139.44 | W44: =IF(OR(B44 = "BG",B44 = "GR",B44 = "IT",B44 = "ES",B44 = "PT",B44 = "TR", B44 = "KR",B44 = "SE",B44 = "CH",B44 = "NO",B44 = "DK",B44 = "FI"), 1, 0) -> 0 | X44: =W44*I44 -> 0 | Y44: =W44*K44 -> 0 | Z44: =IF(OR(B44 = "US",B44 = "CA",B44 = "UK",B44 = "NZ",B44 = "AU",B44 = "SG"), 1, 0) -> 1 | AA44: =VLOOKUP(S44,CPI!$A$2:$F$71,6,0) -> 1.3421046 | AB44: =U44*AA44 -> 2339.2883 | AC44: =V44*AA44 -> 187.14307 | AD44: Trade | AE44: https://www.aecom.com/projects/ottawa-light-rail/
A45: 7118 | B45: CA | C45: Ottawa | D45: Confederation | E45: East West Extensions | F45: 2019 | G45: 2025 | H45: 0 | I45: 28 | J45: =(3.4/28) -> 0.12142857 | K45: 3.4 | L45: 0 | M45: 12 | N45: 17 | O45: 90/120 | P45: Plan | Q45: 2600 | R45: CAD | S45: 2019 | T45: 0.802 | U45: =Q45*T45 -> 2085.2 | V45: =U45/I45 -> 74.471429 | Z45: 1 | AA45: =VLOOKUP(S45,CPI!$A$2:$F$71,6,0) -> 1.2599479 | AB45: =U45*AA45 -> 2627.2434 | AC45: =V45*AA45 -> 93.83012 | AD45: Trade | AE45: https://www.kiewit.com/projects/ottawa-lrt-stage-2/ https://pub-ottawa.escribemeetings.com/filestream.ashx?documentid=58389 https://delveunderground.com/projects/ottawa-light-rail-transit-stages-1-and-2
A46: 7121 | B46: CA | C46: Ottawa | D46: Line 2/Line 4 | E46: South Extension+Airport Link | F46: 2020 | G46: 2025 | H46: 0 | I46: 20 | J46: 0 | K46: 0 | L46: 0.5 | M46: 15.5 | N46: 13 | O46: 90/120 | P46: Plan | Q46: 1660 | R46: CAD | S46: 2019 | T46: 0.802 | U46: =Q46*T46 -> 1331.32 | V46: =U46/I46 -> 66.566 | AA46: =VLOOKUP(S46,CPI!$A$2:$F$71,6,0) -> 1.2599479 | AB46: =U46*AA46 -> 1677.3938 | AC46: =V46*AA46 -> 83.869692 | AD46: Media | AE46: https://www.renewcanada.net/ottawa-proceeding-with-4-67-billion-stage-2-lrt/ https://www.atkinsrealis.com/en/projects/o-train-extension
A47: 7400 | B47: CA | C47: Toronto | D47: Sheppard | E47: Sheppard | F47: 1994 | G47: 2002 | H47: 0 | I47: 5.5 | J47: 1 | K47: 5.5 | L47: 0 | M47: 0 | N47: 5 | P47: Media | Q47: 1000 | R47: CAD | S47: 1998 | T47: 0.81 | U47: =Q47*T47 -> 810 | V47: =U47/I47 -> 147.27273 | W47: =IF(OR(B47 = "BG",B47 = "GR",B47 = "IT",B47 = "ES",B47 = "PT",B47 = "TR", B47 = "KR",B47 = "SE",B47 = "CH",B47 = "NO",B47 = "DK",B47 = "FI"), 1, 0) -> 0 | X47: =W47*I47 -> 0 | Y47: =W47*K47 -> 0 | Z47: =IF(OR(B47 = "US",B47 = "CA",B47 = "UK",B47 = "NZ",B47 = "AU",B47 = "SG"), 1, 0) -> 1 | AA47: =VLOOKUP(S47,CPI!$A$2:$F$71,6,0) -> 1.9761626 | AB47: =U47*AA47 -> 1600.6917 | AC47: =V47*AA47 -> 291.03485 | AD47: Media | AE47: https://www.theglobeandmail.com/news/toronto/sheppard-subway-extension-a-quarter-the-stops-for-three-times-the-cost/article622366/
A48: 7108 | B48: CA | C48: Toronto | D48: YUS | E48: Vaughan | F48: 2009 | G48: 2017 | H48: 0 | I48: 8.6 | J48: 1 | K48: 8.6 | L48: 0 | M48: 0 | N48: 6 | P48: Media | Q48: 3200 | R48: CAD | S48: 2013 | T48: 0.81 | U48: =Q48*T48 -> 2592 | V48: =U48/I48 -> 301.39535 | W48: =IF(OR(B48 = "BG",B48 = "GR",B48 = "IT",B48 = "ES",B48 = "PT",B48 = "TR", B48 = "KR",B48 = "SE",B48 = "CH",B48 = "NO",B48 = "DK",B48 = "FI"), 1, 0) -> 0 | X48: =W48*I48 -> 0 | Y48: =W48*K48 -> 0 | Z48: 1 | AA48: =VLOOKUP(S48,CPI!$A$2:$F$71,6,0) -> 1.3827208 | AB48: =U48*AA48 -> 3584.0124 | AC48: =V48*AA48 -> 416.74563 | AD48: Media | AE48: https://www.thestar.com/news/gta/transportation/2017/12/15/trudeau-wynne-tory-on-hand-to-cut-ribbon-on-32-billion-subway-extension.html
A49: 7283 | B49: CA | C49: Toronto | D49: Eglinton Crosstown | E49: Eglinton Crosstown | F49: 2011 | G49: 2025 | H49: 0 | I49: 19 | J49: 0.53 | K49: 10 | L49: 0.62 | M49: 8.31 | N49: 25 | P49: Plan | Q49: 12800 | R49: CAD | S49: 2016 | T49: 0.83 | U49: =Q49*T49 -> 10624 | V49: =U49/I49 -> 559.15789 | W49: =IF(OR(B49 = "BG",B49 = "GR",B49 = "IT",B49 = "ES",B49 = "PT",B49 = "TR", B49 = "KR",B49 = "SE",B49 = "CH",B49 = "NO",B49 = "DK",B49 = "FI"), 1, 0) -> 0 | X49: =W49*I49 -> 0 | Y49: =W49*K49 -> 0 | Z49: =IF(OR(B49 = "US",B49 = "CA",B49 = "UK",B49 = "NZ",B49 = "AU",B49 = "SG"), 1, 0) -> 1 | AA49: =VLOOKUP(S49,CPI!$A$2:$F$71,6,0) -> 1.3421046 | AB49: =U49*AA49 -> 14258.519 | AC49: =V49*AA49 -> 750.44839 | AD49: Trade | AE49: https://www.cbc.ca/news/canada/toronto/eglinton-crosstown-opening-june-ttc-1.7400691#:~:text=Construction%20began%20in%202011%2C%20when,to%20at%20least%20%2412.8%20billion.
A50: 7115 | B50: CA | C50: Toronto | D50: Finch West LRT | E50: Phase 1 | F50: 2019 | G50: 2025 | H50: 0 | I50: 10.3 | J50: =(1/19)% -> 0.00052631579 | K50: 1 | M50: 17 | N50: 18 | O50: 50 | P50: Plan | Q50: 2500 | R50: CAD | S50: 2019 | T50: 0.84 | U50: =Q50*T50 -> 2100 | V50: =U50/I50 -> 203.8835 | AA50: =VLOOKUP(S50,CPI!$A$2:$F$71,6,0) -> 1.2599479 | AB50: =U50*AA50 -> 2645.8906 | AC50: =V50*AA50 -> 256.88258 | AD50: Media | AE50: https://www.infrastructureontario.ca/en/what-we-do/projectssearch/finch-west-light-rail-transit/
A51: 7109 | B51: CA | C51: Toronto | D51: Bloor/SSE | E51: Scarborough | F51: 2020 | G51: 2030 | H51: 0 | I51: 7.8 | J51: 1 | K51: 7.8 | L51: 0 | M51: 0 | N51: 3 | P51: Wiki | Q51: 5500 | R51: CAD | S51: 2018 | T51: 0.84 | U51: =Q51*T51 -> 4620 | V51: =U51/I51 -> 592.30769 | W51: =IF(OR(B51 = "BG",B51 = "GR",B51 = "IT",B51 = "ES",B51 = "PT",B51 = "TR", B51 = "KR",B51 = "SE",B51 = "CH",B51 = "NO",B51 = "DK",B51 = "FI"), 1, 0) -> 0 | X51: =W51*I51 -> 0 | Y51: =W51*K51 -> 0 | Z51: =IF(OR(B51 = "US",B51 = "CA",B51 = "UK",B51 = "NZ",B51 = "AU",B51 = "SG"), 1, 0) -> 1 | AA51: =VLOOKUP(S51,CPI!$A$2:$F$71,6,0) -> 1.2827779 | AB51: =U51*AA51 -> 5926.4337 | AC51: =V51*AA51 -> 759.79919 | AD51: Media | AE51: https://urbantoronto.ca/news/2020/03/metrolinxs-preliminary-business-case-scarborough-subway-extension-raises-questions
A52: 7111 | B52: CA | C52: Toronto | D52: YUS/YNSE | E52: Yonge to Richmond Hill | F52: 2020 | G52: 2030 | H52: 0 | I52: 7.4 | J52: 1 | K52: 7.4 | L52: 0 | M52: 0 | N52: 6 | P52: Plan | Q52: 5600 | R52: CAD | S52: 2020 | T52: 0.84 | U52: =Q52*T52 -> 4704 | V52: =U52/I52 -> 635.67568 | W52: =IF(OR(B52 = "BG",B52 = "GR",B52 = "IT",B52 = "ES",B52 = "PT",B52 = "TR", B52 = "KR",B52 = "SE",B52 = "CH",B52 = "NO",B52 = "DK",B52 = "FI"), 1, 0) -> 0 | X52: =W52*I52 -> 0 | Y52: =W52*K52 -> 0 | Z52: =IF(OR(B52 = "US",B52 = "CA",B52 = "UK",B52 = "NZ",B52 = "AU",B52 = "SG"), 1, 0) -> 1 | AA52: =VLOOKUP(S52,CPI!$A$2:$F$71,6,0) -> 1.2445935 | AB52: =U52*AA52 -> 5854.568 | AC52: =V52*AA52 -> 791.15784 | AD52: Media | AE52: https://www.thestar.com/news/gta/2020/06/24/metrolinx-considering-a-route-for-the-yonge-subway-extension-to-richmond-hill-that-would-take-it-above-ground.html
A53: 7113 | B53: CA | C53: Toronto | D53: Eglinton Crosstown | E53: Phase 1 West | F53: 2022 | G53: 2031 | H53: 0 | I53: 9.2 | J53: =6.8/9.2 -> 0.73913043 | K53: 6.8 | L53: 1.5 | M53: 0.9 | N53: 7 | O53: 50 | P53: Plan | Q53: 2500 | R53: CAD | S53: 2022 | T53: 0.84 | U53: =Q53*T53 -> 2100 | V53: =U53/I53 -> 228.26087 | AA53: =VLOOKUP(S53,CPI!$A$2:$F$71,6,0) -> 1.1006629 | AB53: =U53*AA53 -> 2311.3921 | AC53: =V53*AA53 -> 251.23827 | AD53: Media | AE53: https://www.infrastructureontario.ca/en/what-we-do/projectssearch/eglinton-crosstown-west-extension/ https://www.metrolinx.com/en/projects-and-programs/eglinton-crosstown-west-extension
A54: 7110 | B54: CA | C54: Toronto | D54: Ontario Line | E54: Ontario | F54: 2022 | G54: 2031 | H54: 0 | I54: 15.5 | J54: 0.57 | K54: 8.8 | L54: 5.76 | M54: 1.06 | N54: 15 | P54: Plan | Q54: 27200 | R54: CAD | S54: 2023 | T54: 0.84 | U54: =Q54*T54 -> 22848 | V54: =U54/I54 -> 1474.0645 | W54: =IF(OR(B54 = "BG",B54 = "GR",B54 = "IT",B54 = "ES",B54 = "PT",B54 = "TR", B54 = "KR",B54 = "SE",B54 = "CH",B54 = "NO",B54 = "DK",B54 = "FI"), 1, 0) -> 0 | X54: =W54*I54 -> 0 | Y54: =W54*K54 -> 0 | Z54: =IF(OR(B54 = "US",B54 = "CA",B54 = "UK",B54 = "NZ",B54 = "AU",B54 = "SG"), 1, 0) -> 1 | AA54: =VLOOKUP(S54,CPI!$A$2:$F$71,6,0) -> 1.057146 | AB54: =U54*AA54 -> 24153.672 | AC54: =V54*AA54 -> 1558.3014 | AD54: Plan | AE54: https://globalnews.ca/news/10579363/ontario-line-cost-increase/
A55: 9762 | B55: CA | C55: Vancouver | D55: Millennium Line | E55: Millennium Line Phase 1 | F55: 1998 | G55: 2002 | H55: 0 | I55: 19.9 | J55: 0 | K55: 0 | L55: 0 | M55: 0 | N55: 13 | P55: Wiki | Q55: 1200 | R55: CAD | S55: 2000 | T55: 0.81 | U55: =Q55*T55 -> 972 | V55: =U55/I55 -> 48.844221 | W55: =IF(OR(B55 = "BG",B55 = "GR",B55 = "IT",B55 = "ES",B55 = "PT",B55 = "TR", B55 = "KR",B55 = "SE",B55 = "CH",B55 = "NO",B55 = "DK",B55 = "FI"), 1, 0) -> 0 | X55: =W55*I55 -> 0 | Y55: =W55*K55 -> 0 | Z55: =IF(OR(B55 = "US",B55 = "CA",B55 = "UK",B55 = "NZ",B55 = "AU",B55 = "SG"), 1, 0) -> 1 | AA55: =VLOOKUP(S55,CPI!$A$2:$F$71,6,0) -> 1.8705836 | AB55: =U55*AA55 -> 1818.2073 | AC55: =V55*AA55 -> 91.3672 | AD55: Plan | AE55: https://web.archive.org/web/20181110080355/https://www.translink.ca/-/media/Documents/about_translink/corporate_overview/corporate_reports/history/translink_history_nov_2008.pdf
A56: 9763 | B56: CA | C56: Vancouver | D56: Canada Line | E56: Canada Line | F56: 2005 | G56: 2009 | H56: 0 | I56: 18.4 | J56: 0.49 | K56: 9.1 | L56: 0 | M56: 0 | N56: 16 | P56: Wiki | Q56: 2050 | R56: CAD | S56: 2007 | T56: 0.82 | U56: =Q56*T56 -> 1681 | V56: =U56/I56 -> 91.358696 | W56: =IF(OR(B56 = "BG",B56 = "GR",B56 = "IT",B56 = "ES",B56 = "PT",B56 = "TR", B56 = "KR",B56 = "SE",B56 = "CH",B56 = "NO",B56 = "DK",B56 = "FI"), 1, 0) -> 0 | X56: =W56*I56 -> 0 | Y56: =W56*K56 -> 0 | Z56: =IF(OR(B56 = "US",B56 = "CA",B56 = "UK",B56 = "NZ",B56 = "AU",B56 = "SG"), 1, 0) -> 1 | AA56: =VLOOKUP(S56,CPI!$A$2:$F$71,6,0) -> 1.553542 | AB56: =U56*AA56 -> 2611.5041 | AC56: =V56*AA56 -> 141.92957 | AD56: Media | AE56: https://vancouversun.com/news/local-news/by-the-numbers-canada-line-turns-10
A57: 9764 | B57: CA | C57: Vancouver | D57: Evergreen Line | E57: Evergreen Line | F57: 2012 | G57: 2016 | H57: 0 | I57: 10.9 | J57: 0.18 | K57: 2 | L57: 0 | M57: 0 | N57: 6 | P57: Wiki | Q57: 1430 | R57: CAD | S57: 2014 | T57: 0.81 | U57: =Q57*T57 -> 1158.3 | V57: =U57/I57 -> 106.26605 | W57: =IF(OR(B57 = "BG",B57 = "GR",B57 = "IT",B57 = "ES",B57 = "PT",B57 = "TR", B57 = "KR",B57 = "SE",B57 = "CH",B57 = "NO",B57 = "DK",B57 = "FI"), 1, 0) -> 0 | X57: =W57*I57 -> 0 | Y57: =W57*K57 -> 0 | Z57: =IF(OR(B57 = "US",B57 = "CA",B57 = "UK",B57 = "NZ",B57 = "AU",B57 = "SG"), 1, 0) -> 1 | AA57: =VLOOKUP(S57,CPI!$A$2:$F$71,6,0) -> 1.3606486 | AB57: =U57*AA57 -> 1576.0392 | AC57: =V57*AA57 -> 144.59076 | AD57: Media | AE57: https://thebreaker.news/news/evergreen-line-costs/
A58: 7136 | B58: CA | C58: Vancouver | D58: Millennium | E58: Broadway | F58: 2020 | G58: 2027 | H58: 0 | I58: 5.7 | J58: =5/5.7 -> 0.87719298 | K58: 5 | L58: 0.295 | M58: 0.446 | N58: 6 | P58: Plan | Q58: 2954 | R58: CAD | S58: 2018 | T58: 0.84 | U58: =Q58*T58 -> 2481.36 | V58: =U58/I58 -> 435.32632 | W58: =IF(OR(B58 = "BG",B58 = "GR",B58 = "IT",B58 = "ES",B58 = "PT",B58 = "TR", B58 = "KR",B58 = "SE",B58 = "CH",B58 = "NO",B58 = "DK",B58 = "FI"), 1, 0) -> 0 | X58: =W58*I58 -> 0 | Y58: =W58*K58 -> 0 | Z58: =IF(OR(B58 = "US",B58 = "CA",B58 = "UK",B58 = "NZ",B58 = "AU",B58 = "SG"), 1, 0) -> 1 | AA58: =VLOOKUP(S58,CPI!$A$2:$F$71,6,0) -> 1.2827779 | AB58: =U58*AA58 -> 3183.0337 | AC58: =V58*AA58 -> 558.42696 | AD58: Media | AE58: https://www.translink.ca/Plans-and-Projects/Rapid-Transit-Projects/Broadway-Subway-Project.aspx https://www2.gov.bc.ca/assets/gov/british-columbians-our-governments/government-finances/quarterly-reports/fall-2024-economic-fiscal-update.pdf
A59: 7102 | B59: CA | C59: Vancouver | D59: Surrey Langley SkyTrain | E59: Planning | F59: 2024 | G59: 2029 | H59: 0 | I59: 16 | J59: 0 | K59: 0 | L59: 1 | M59: 0 | N59: 8 | O59: 80 | P59: Plan | Q59: 5996 | R59: CAD | S59: 2024 | T59: 1 | U59: =Q59*T59 -> 5996 | V59: =U59/I59 -> 374.75 | W59: 0 | Z59: 1 | AA59: =VLOOKUP(S59,CPI!$A$2:$F$71,6,0) -> 1 | AB59: =U59*AA59 -> 5996 | AC59: =V59*AA59 -> 374.75 | AD59: Media | AE59: https://globalnews.ca/news/10701039/surrey-langley-skytrain-cost/ https://surreylangleyskytrain.gov.bc.ca/app/uploads/sites/938/2024/12/SLS_Monthly_Status_Report_August_2024.pdf
B60: CA | C60: Vancouver | D60: Expo Line | E60: Expo Line Surrey-Langley extension | F60: 2022 | H60: 0 | I60: 16 | J60: 0 | K60: 0 | N60: 8 | Q60: 3940 | R60: CAD | S60: 2021 | T60: 0.798 | U60: =Q60*T60 -> 3144.12 | V60: =U60/I60 -> 196.5075 | W60: =IF(OR(B60 = "BG",B60 = "GR",B60 = "IT",B60 = "ES",B60 = "PT",B60 = "TR", B60 = "KR",B60 = "SE",B60 = "CH",B60 = "NO",B60 = "DK",B60 = "FI"), 1, 0) -> 0 | X60: =W60*I60 -> 0 | Y60: =W60*K60 -> 0 | Z60: =IF(OR(B60 = "US",B60 = "CA",B60 = "UK",B60 = "NZ",B60 = "AU",B60 = "SG"), 1, 0) -> 1 | AA60: =VLOOKUP(S60,CPI!$A$2:$F$71,6,0) -> 1.188746 | AB60: =U60*AA60 -> 3737.56 | AC60: =V60*AA60 -> 233.5975 | AD60: Media | AE60: https://globalnews.ca/news/8016045/justin-trudeau-federal-funding-skytrain-surrey-langley/ | AF60: https://bc.ctvnews.ca/federal-government-providing-up-to-1-3-billion-for-surrey-langley-skytrain-extension-1.5502944
A61: 7101 | B61: CA | C61: Vancouver | D61: Millennium | E61: UBC | F61: 2028 | P61: Plan | AA61: =VLOOKUP(S61,CPI!$A$2:$F$71,6,0) -> #N/A | AE61: https://www.translink.ca/-/media/translink/documents/about-translink/governance-and-board/council-minutes-and-reports/2022/april/agenda_mayors_council_board_public_mtg_20220422.pdf
A62: 7560 | B62: CH | C62: Geneva | D62: CEVA | E62: CEVA | F62: 2013 | G62: 2019 | H62: 1 | I62: 8.8 | J62: 0.96 | K62: 8.4 | L62: 0.14 | M62: 0.212 | N62: 4 | P62: Measured | Q62: 1567 | R62: CHF | S62: 2016 | T62: 0.68 | U62: =Q62*T62 -> 1065.56 | V62: =U62/I62 -> 121.08636 | W62: =IF(OR(B62 = "BG",B62 = "GR",B62 = "IT",B62 = "ES",B62 = "PT",B62 = "TR", B62 = "KR",B62 = "SE",B62 = "CH",B62 = "NO",B62 = "DK",B62 = "FI"), 1, 0) -> 1 | X62: =W62*I62 -> 8.8 | Y62: =W62*K62 -> 8.4 | Z62: =IF(OR(B62 = "US",B62 = "CA",B62 = "UK",B62 = "NZ",B62 = "AU",B62 = "SG"), 1, 0) -> 0 | AA62: =VLOOKUP(S62,CPI!$A$2:$F$71,6,0) -> 1.3421046 | AB62: =U62*AA62 -> 1430.093 | AC62: =V62*AA62 -> 162.51057 | AD62: Plan | AE62: https://www.ceva.ch/2017/05/11/financement-et-organisation/?b=https://www.ceva.ch/category/projet
B63: CH | C63: Lausanne | D63: Line 2 | E63: Line 2 | F63: 2002 | G63: 2008 | H63: 0 | I63: 6 | K63: 4.5 | L63: 1.5 | M63: 0 | N63: 14 | O63: 30 | P63: Wiki | Q63: 410 | R63: CHF | S63: 2000 | T63: 0.65 | U63: =Q63*T63 -> 266.5 | V63: =U63/I63 -> 44.416667 | W63: =IF(OR(B63 = "BG",B63 = "GR",B63 = "IT",B63 = "ES",B63 = "PT",B63 = "TR", B63 = "KR",B63 = "SE",B63 = "CH",B63 = "NO",B63 = "DK",B63 = "FI"), 1, 0) -> 1 | X63: =W63*I63 -> 6 | Y63: =W63*K63 -> 4.5 | Z63: =IF(OR(B63 = "US",B63 = "CA",B63 = "UK",B63 = "NZ",B63 = "AU",B63 = "SG"), 1, 0) -> 0 | AA63: =VLOOKUP(S63,CPI!$A$2:$F$71,6,0) -> 1.8705836 | AB63: =U63*AA63 -> 498.51054 | AC63: =V63*AA63 -> 83.085089 | AD63: Plan | AE63: https://archive.wikiwix.com/cache/index2.php?url=http%3A%2F%2Fwww.publidoc.vd.ch%2FguestDownload%2Fdirect%2FTexte%2520adopt%25C3%25A9%2520par%2520CE.pdf%3Fpath%3D%2FCompany%2520Home%2FVD%2FCHANC%2FSIEL%2Fantilope%2Fobjet%2FCEGC%2FExpos%25C3%25A9%2520des%2520motifs%2F2002%2F05%2F174061_34_Texte%2520adopt%25C3%25A9%2520par%2520CE_20020604_234589.pdf%2Findex.html#federation=archive.wikiwix.com&tab=url
A64: 7529 | B64: CH | C64: Lucerne | D64: Zentralbahn | E64: Zentralbahn | F64: 2008 | G64: 2013 | H64: 1 | I64: 1.5 | J64: 0.9 | K64: 1.4 | L64: 0 | M64: 0 | N64: 1 | P64: Plan | Q64: 220.2 | R64: CHF | S64: 2010 | T64: 0.68 | U64: =Q64*T64 -> 149.736 | V64: =U64/I64 -> 99.824 | W64: =IF(OR(B64 = "BG",B64 = "GR",B64 = "IT",B64 = "ES",B64 = "PT",B64 = "TR", B64 = "KR",B64 = "SE",B64 = "CH",B64 = "NO",B64 = "DK",B64 = "FI"), 1, 0) -> 1 | X64: =W64*I64 -> 1.5 | Y64: =W64*K64 -> 1.4 | Z64: =IF(OR(B64 = "US",B64 = "CA",B64 = "UK",B64 = "NZ",B64 = "AU",B64 = "SG"), 1, 0) -> 0 | AA64: =VLOOKUP(S64,CPI!$A$2:$F$71,6,0) -> 1.47721 | AB64: =U64*AA64 -> 221.19151 | AC64: =V64*AA64 -> 147.46101 | AD64: Plan | AE64: https://www.luzernerzeitung.ch/zentralschweiz/luzern/seetalplatz-und-zentralbahn-60-millionen-guenstiger-als-budgetiert-ld.1150224
A65: 7530 | B65: CH | C65: Zurich | D65: Durchmesserlinie | E65: Durchmesserlinie | F65: 2007 | G65: 2014 | H65: 1 | I65: 9.6 | J65: 0.5 | K65: 4.8 | L65: 0.2 | M65: 4.6 | N65: 1 | P65: Trade | Q65: 2030 | R65: CHF | S65: 2010 | T65: 0.68 | U65: =Q65*T65 -> 1380.4 | V65: =U65/I65 -> 143.79167 | W65: =IF(OR(B65 = "BG",B65 = "GR",B65 = "IT",B65 = "ES",B65 = "PT",B65 = "TR", B65 = "KR",B65 = "SE",B65 = "CH",B65 = "NO",B65 = "DK",B65 = "FI"), 1, 0) -> 1 | X65: =W65*I65 -> 9.6 | Y65: =W65*K65 -> 4.8 | Z65: =IF(OR(B65 = "US",B65 = "CA",B65 = "UK",B65 = "NZ",B65 = "AU",B65 = "SG"), 1, 0) -> 0 | AA65: =VLOOKUP(S65,CPI!$A$2:$F$71,6,0) -> 1.47721 | AB65: =U65*AA65 -> 2039.1407 | AC65: =V65*AA65 -> 212.41049 | AD65: Trade | AE65: https://www.railwaygazette.com/infrastructure/cross-city-tunnel-opening-increases-capacity-in-zurich/39619.article
A66: 7338 | B66: CL | C66: Santiago | D66: Project 63 | E66: Project 63 | F66: 2013 | G66: 2019 | H66: 0 | I66: 37 | J66: 1 | K66: 37 | L66: 0 | M66: 0 | N66: 28 | P66: Plan | Q66: 3000 | R66: USD | S66: 2016 | T66: 1.7 | U66: =Q66*T66 -> 5100 | V66: =U66/I66 -> 137.83784 | W66: =IF(OR(B66 = "BG",B66 = "GR",B66 = "IT",B66 = "ES",B66 = "PT",B66 = "TR", B66 = "KR",B66 = "SE",B66 = "CH",B66 = "NO",B66 = "DK",B66 = "FI"), 1, 0) -> 0 | X66: =W66*I66 -> 0 | Y66: =W66*K66 -> 0 | Z66: =IF(OR(B66 = "US",B66 = "CA",B66 = "UK",B66 = "NZ",B66 = "AU",B66 = "SG"), 1, 0) -> 0 | AA66: =VLOOKUP(S66,CPI!$A$2:$F$71,6,0) -> 1.3421046 | AB66: =U66*AA66 -> 6844.7335 | AC66: =V66*AA66 -> 184.9928 | AD66: Plan | AE66: https://www.metro.cl/files/documentos/metro-investor-201709.pdf
A67: 7337 | B67: CL | C67: Santiago | D67: Line 7 | E67: Line 7 | F67: 2021 | G67: 2026 | H67: 0 | I67: 24.8 | J67: 1 | K67: 24.8 | L67: 0 | M67: 0 | N67: 21 | P67: Plan | Q67: 2900 | R67: USD | S67: 2022 | T67: 1.7 | U67: =Q67*T67 -> 4930 | V67: =U67/I67 -> 198.79032 | W67: =IF(OR(B67 = "BG",B67 = "GR",B67 = "IT",B67 = "ES",B67 = "PT",B67 = "TR", B67 = "KR",B67 = "SE",B67 = "CH",B67 = "NO",B67 = "DK",B67 = "FI"), 1, 0) -> 0 | X67: =W67*I67 -> 0 | Y67: =W67*K67 -> 0 | Z67: =IF(OR(B67 = "US",B67 = "CA",B67 = "UK",B67 = "NZ",B67 = "AU",B67 = "SG"), 1, 0) -> 0 | AA67: =VLOOKUP(S67,CPI!$A$2:$F$71,6,0) -> 1.1006629 | AB67: =U67*AA67 -> 5426.2681 | AC67: =V67*AA67 -> 218.80113 | AD67: Trade | AE67: https://www.railwaygazette.com/projects-and-planning/santiago-tenders-line-7-construction/56621.article
A68: 7641 | B68: CN | C68: Beijing | D68: Line 1 | E68: Line 1 Phase 1 | F68: 1965 | G68: 1969 | H68: 0 | I68: 23.6 | J68: 1 | K68: 23.6 | L68: 0 | M68: 0 | N68: 17 | P68: Baidu | Q68: =0.7*10^3 -> 700 | R68: CNY | S68: 1965 | W68: =IF(OR(B68 = "BG",B68 = "GR",B68 = "IT",B68 = "ES",B68 = "PT",B68 = "TR", B68 = "KR",B68 = "SE",B68 = "CH",B68 = "NO",B68 = "DK",B68 = "FI"), 1, 0) -> 0 | X68: =W68*I68 -> 0 | Y68: =W68*K68 -> 0 | Z68: =IF(OR(B68 = "US",B68 = "CA",B68 = "UK",B68 = "NZ",B68 = "AU",B68 = "SG"), 1, 0) -> 0 | AA68: =VLOOKUP(S68,CPI!$A$2:$F$71,6,0) -> 10.225857 | AD68: Media | AE68: https://baike.baidu.com/item/%E5%8C%97%E4%BA%AC%E5%9C%B0%E9%93%811%E5%8F%B7%E7%BA%BF/7646800?fromtitle=%E5%8C%97%E4%BA%AC%E5%9C%B0%E9%93%81%E4%B8%80%E5%8F%B7%E7%BA%BF&fromid=5427835&fr=aladdin
A69: 7649 | B69: CN | C69: Beijing | D69: Line 13 | E69: Line 13 | F69: 1999 | G69: 2003 | H69: 0 | I69: 40.85 | J69: 0 | K69: 0 | L69: 13.855 | M69: 26.995 | N69: 17 | O69: 117 | P69: Wiki | Q69: =6.57*10^3 -> 6570 | R69: CNY | S69: 1999 | T69: 0.367 | U69: =Q69*T69 -> 2411.19 | V69: =U69/I69 -> 59.025459 | W69: =IF(OR(B69 = "BG",B69 = "GR",B69 = "IT",B69 = "ES",B69 = "PT",B69 = "TR", B69 = "KR",B69 = "SE",B69 = "CH",B69 = "NO",B69 = "DK",B69 = "FI"), 1, 0) -> 0 | X69: =W69*I69 -> 0 | Y69: =W69*K69 -> 0 | Z69: =IF(OR(B69 = "US",B69 = "CA",B69 = "UK",B69 = "NZ",B69 = "AU",B69 = "SG"), 1, 0) -> 0 | AA69: =VLOOKUP(S69,CPI!$A$2:$F$71,6,0) -> 1.9334604 | AB69: =U69*AA69 -> 4661.9403 | AC69: =V69*AA69 -> 114.12339 | AD69: Media | AE69: http://www.wikiwand.com/zh-sg/%E5%8C%97%E4%BA%AC%E5%9C%B0%E9%93%8113%E5%8F%B7%E7%BA%BF
A70: 8065 | B70: CN | C70: Beijing | D70: Line 5 | E70: Line 5 | F70: 2002 | G70: 2007 | H70: 0 | I70: 27.6 | L70: #N/A | M70: #N/A | N70: 23 | P70: Media | Q70: 12000 | R70: CNY | S70: 2004 | T70: 0.355 | U70: =T70*Q70 -> 4260 | V70: =U70/I70 -> 154.34783 | W70: =IF(OR(B70 = "BG",B70 = "GR",B70 = "IT",B70 = "ES",B70 = "PT",B70 = "TR", B70 = "KR",B70 = "SE",B70 = "CH",B70 = "NO",B70 = "DK",B70 = "FI"), 1, 0) -> 0 | X70: =W70*I70 -> 0 | Y70: =W70*K70 -> 0 | Z70: =IF(OR(B70 = "US",B70 = "CA",B70 = "UK",B70 = "NZ",B70 = "AU",B70 = "SG"), 1, 0) -> 0 | AA70: =VLOOKUP(S70,CPI!$A$2:$F$71,6,0) -> 1.7052118 | AB70: =U70*AA70 -> 7264.2021 | AC70: =V70*AA70 -> 263.19573 | AD70: Media | AE70: http://finance.sina.com.cn/b/20040419/0854725033.shtml
A71: 7960 | B71: CN | C71: Beijing | D71: Line 10 | E71: Line 10 North and East | F71: 2003 | G71: 2008 | H71: 0 | I71: 24.64 | J71: 1 | K71: 24.64 | L71: 0 | M71: 0 | N71: 22 | P71: Media | Q71: 13700 | R71: CNY | S71: 2005 | T71: 0.3519 | U71: =Q71*T71 -> 4821.03 | V71: =U71/I71 -> 195.65869 | W71: =IF(OR(B71 = "BG",B71 = "GR",B71 = "IT",B71 = "ES",B71 = "PT",B71 = "TR", B71 = "KR",B71 = "SE",B71 = "CH",B71 = "NO",B71 = "DK",B71 = "FI"), 1, 0) -> 0 | X71: =W71*I71 -> 0 | Y71: =W71*K71 -> 0 | Z71: =IF(OR(B71 = "US",B71 = "CA",B71 = "UK",B71 = "NZ",B71 = "AU",B71 = "SG"), 1, 0) -> 0 | AA71: =VLOOKUP(S71,CPI!$A$2:$F$71,6,0) -> 1.6493318 | AB71: =U71*AA71 -> 7951.4781 | AC71: =V71*AA71 -> 322.70609 | AD71: Media | AE71: http://news.sciencenet.cn/sbhtmlnews/2008/8/209799.html
A72: 8139 | B72: CN | C72: Beijing | D72: Capital Airport Express | E72: Capital Airport Express | F72: 2005 | G72: 2008 | H72: 0 | I72: 28.1 | J72: 0 | K72: 0 | L72: 17.315 | M72: 10.785 | N72: 4 | P72: Measured | Q72: 622.3 | R72: CNY | S72: 2005 | T72: 0.3519 | U72: =T72*Q72 -> 218.98737 | V72: =U72/I72 -> 7.7931448 | W72: =IF(OR(B72 = "BG",B72 = "GR",B72 = "IT",B72 = "ES",B72 = "PT",B72 = "TR", B72 = "KR",B72 = "SE",B72 = "CH",B72 = "NO",B72 = "DK",B72 = "FI"), 1, 0) -> 0 | X72: =W72*I72 -> 0 | Y72: =W72*K72 -> 0 | Z72: =IF(OR(B72 = "US",B72 = "CA",B72 = "UK",B72 = "NZ",B72 = "AU",B72 = "SG"), 1, 0) -> 0 | AA72: =VLOOKUP(S72,CPI!$A$2:$F$71,6,0) -> 1.6493318 | AB72: =U72*AA72 -> 361.18283 | AC72: =V72*AA72 -> 12.853482 | AD72: Media | AE72: http://news.sciencenet.cn/sbhtmlnews/2008/8/209799.html
A73: 7987 | B73: CN | C73: Beijing | D73: Line 8 | E73: Line 8 Phase 1 for Olympics | F73: 2005 | G73: 2008 | H73: 0 | I73: 4.528 | J73: 1 | K73: 4.528 | L73: 0 | M73: 0 | N73: 4 | P73: Media | Q73: 2420 | R73: CNY | S73: 2005 | T73: 0.3519 | U73: =T73*Q73 -> 851.598 | V73: =U73/I73 -> 188.07376 | W73: =IF(OR(B73 = "BG",B73 = "GR",B73 = "IT",B73 = "ES",B73 = "PT",B73 = "TR", B73 = "KR",B73 = "SE",B73 = "CH",B73 = "NO",B73 = "DK",B73 = "FI"), 1, 0) -> 0 | X73: =W73*I73 -> 0 | Y73: =W73*K73 -> 0 | Z73: =IF(OR(B73 = "US",B73 = "CA",B73 = "UK",B73 = "NZ",B73 = "AU",B73 = "SG"), 1, 0) -> 0 | AA73: =VLOOKUP(S73,CPI!$A$2:$F$71,6,0) -> 1.6493318 | AB73: =U73*AA73 -> 1404.5677 | AC73: =V73*AA73 -> 310.19604 | AD73: Media | AE73: https://www.360kuai.com/pc/9fb76b182add530db?cota=4&kuai_so=1&tj_url=so_rec&sign=360_7bc3b157; http://itdzs.org/OnLineMagazine/PDFView.aspx?ID=4
A74: 7640 | B74: CN | C74: Beijing | D74: Line 4 | E74: Line 4 | F74: 2004 | G74: 2009 | H74: 0 | I74: 28.2 | J74: =K74/I74 -> 0.95166667 | K74: 26.837 | L74: 0 | M74: 0 | N74: 24 | O74: 117 | P74: Media | Q74: 15380 | R74: CNY | S74: 2005 | T74: 0.3519 | U74: =Q74*T74 -> 5412.222 | V74: =U74/I74 -> 191.92277 | W74: =IF(OR(B74 = "BG",B74 = "GR",B74 = "IT",B74 = "ES",B74 = "PT",B74 = "TR", B74 = "KR",B74 = "SE",B74 = "CH",B74 = "NO",B74 = "DK",B74 = "FI"), 1, 0) -> 0 | X74: =W74*I74 -> 0 | Y74: =W74*K74 -> 0 | Z74: =IF(OR(B74 = "US",B74 = "CA",B74 = "UK",B74 = "NZ",B74 = "AU",B74 = "SG"), 1, 0) -> 0 | AA74: =VLOOKUP(S74,CPI!$A$2:$F$71,6,0) -> 1.6493318 | AB74: =U74*AA74 -> 8926.5498 | AC74: =V74*AA74 -> 316.54432 | AD74: Media | AE74: http://zizhan.mot.gov.cn/zhuantizhuanlan/qita/quanqiuhuanjingjijin/zhishigongxiang/201601/P020160125565596507649.pdf
A75: 8041 | B75: CN | C75: Beijing | D75: Daxing Line | E75: Daxing Line | F75: 2007 | G75: 2010 | H75: 0 | I75: 21.8 | J75: 0.80275229 | K75: 17.5 | L75: 4.36 | M75: 0 | N75: 11 | P75: Media | Q75: 10930 | R75: CNY | S75: 2007 | T75: 0.333 | U75: =T75*Q75 -> 3639.69 | V75: =U75/I75 -> 166.95826 | W75: =IF(OR(B75 = "BG",B75 = "GR",B75 = "IT",B75 = "ES",B75 = "PT",B75 = "TR", B75 = "KR",B75 = "SE",B75 = "CH",B75 = "NO",B75 = "DK",B75 = "FI"), 1, 0) -> 0 | X75: =W75*I75 -> 0 | Y75: =W75*K75 -> 0 | Z75: =IF(OR(B75 = "US",B75 = "CA",B75 = "UK",B75 = "NZ",B75 = "AU",B75 = "SG"), 1, 0) -> 0 | AA75: =VLOOKUP(S75,CPI!$A$2:$F$71,6,0) -> 1.553542 | AB75: =U75*AA75 -> 5654.4112 | AC75: =V75*AA75 -> 259.37666 | AD75: Media | AE75: http://www.mtr.bj.cn/article/5d510c0aebb1a36f5ef5981f.html
A76: 7650 | B76: CN | C76: Beijing | D76: Line 8 | E76: Line 8 Phase 2 North | G76: 2011 | H76: 0 | I76: 10.7 | J76: 1 | K76: 10.7 | L76: 0 | M76: 0 | N76: 6 | P76: Media | R76: CNY | S76: 2011 | T76: 0.284 | W76: =IF(OR(B76 = "BG",B76 = "GR",B76 = "IT",B76 = "ES",B76 = "PT",B76 = "TR", B76 = "KR",B76 = "SE",B76 = "CH",B76 = "NO",B76 = "DK",B76 = "FI"), 1, 0) -> 0 | X76: =W76*I76 -> 0 | Y76: =W76*K76 -> 0 | Z76: =IF(OR(B76 = "US",B76 = "CA",B76 = "UK",B76 = "NZ",B76 = "AU",B76 = "SG"), 1, 0) -> 0 | AA76: =VLOOKUP(S76,CPI!$A$2:$F$71,6,0) -> 1.4320082 | AD76: Media | AE76: https://zh.wikipedia.org/wiki/%E5%8C%97%E4%BA%AC%E5%9C%B0%E9%93%818%E5%8F%B7%E7%BA%BF#%E4%BA%8C%E6%9C%9F%E5%B7%A5%E7%A8%8B
A77: 8145 | B77: CN | C77: Beijing | D77: Line 10 | E77: Line 10 South and West | F77: 2007 | G77: 2012 | H77: 0 | I77: 32.46 | J77: 1 | K77: 32.46 | L77: 0 | M77: 0 | N77: 24 | P77: Measured | R77: CNY | S77: 2007 | T77: 0.333 | W77: =IF(OR(B77 = "BG",B77 = "GR",B77 = "IT",B77 = "ES",B77 = "PT",B77 = "TR", B77 = "KR",B77 = "SE",B77 = "CH",B77 = "NO",B77 = "DK",B77 = "FI"), 1, 0) -> 0 | X77: =W77*I77 -> 0 | Y77: =W77*K77 -> 0 | Z77: =IF(OR(B77 = "US",B77 = "CA",B77 = "UK",B77 = "NZ",B77 = "AU",B77 = "SG"), 1, 0) -> 0 | AA77: =VLOOKUP(S77,CPI!$A$2:$F$71,6,0) -> 1.553542 | AD77: Media | AE77: https://zh.wikipedia.org/wiki/%E5%8C%97%E4%BA%AC%E5%9C%B0%E9%93%8110%E5%8F%B7%E7%BA%BF#%E4%BA%8C%E6%9C%9F%E5%B7%A5%E7%A8%8B
B78: CN | C78: Beijing | D78: Line 9 | E78: Line 9 | F78: 2007 | G78: 2012 | H78: 0 | I78: 16.5 | J78: 1 | K78: 16.5 | N78: 13 | O78: 117 | Q78: 12900 | R78: CNY | S78: 2010 | T78: 0.3 | U78: =Q78*T78 -> 3870 | V78: =U78/I78 -> 234.54545 | W78: =IF(OR(B78 = "BG",B78 = "GR",B78 = "IT",B78 = "ES",B78 = "PT",B78 = "TR", B78 = "KR",B78 = "SE",B78 = "CH",B78 = "NO",B78 = "DK",B78 = "FI"), 1, 0) -> 0 | X78: =W78*I78 -> 0 | Y78: =W78*K78 -> 0 | Z78: =IF(OR(B78 = "US",B78 = "CA",B78 = "UK",B78 = "NZ",B78 = "AU",B78 = "SG"), 1, 0) -> 0 | AA78: =VLOOKUP(S78,CPI!$A$2:$F$71,6,0) -> 1.47721 | AB78: =U78*AA78 -> 5716.8026 | AC78: =V78*AA78 -> 346.47289 | AE78: http://zqb.cyol.com/html/2012-12/31/nw.D110000zgqnb_20121231_3-06.htm
A79: 7832 | B79: CN | C79: Beijing | D79: Line 6 | E79: Line 6 Phase 1 | F79: 2008 | G79: 2012 | H79: 0 | I79: 30.4 | J79: 1 | K79: 30.4 | N79: 20 | O79: 156 | P79: Wiki | Q79: 28000 | R79: CNY | S79: 2010 | T79: 0.3 | U79: =Q79*T79 -> 8400 | V79: =U79/I79 -> 276.31579 | W79: =IF(OR(B79 = "BG",B79 = "GR",B79 = "IT",B79 = "ES",B79 = "PT",B79 = "TR", B79 = "KR",B79 = "SE",B79 = "CH",B79 = "NO",B79 = "DK",B79 = "FI"), 1, 0) -> 0 | X79: =W79*I79 -> 0 | Y79: =W79*K79 -> 0 | Z79: =IF(OR(B79 = "US",B79 = "CA",B79 = "UK",B79 = "NZ",B79 = "AU",B79 = "SG"), 1, 0) -> 0 | AA79: =VLOOKUP(S79,CPI!$A$2:$F$71,6,0) -> 1.47721 | AB79: =U79*AA79 -> 12408.564 | AC79: =V79*AA79 -> 408.17644 | AD79: Media | AE79: http://zqb.cyol.com/html/2012-12/31/nw.D110000zgqnb_20121231_3-06.htm
A80: 8131 | B80: CN | C80: Beijing | D80: Line 8 | E80: Line 8 Northern Extension | F80: 2011 | G80: 2013 | H80: 0 | I80: 6.328 | J80: 0.73451327 | K80: 4.648 | L80: 1.7091 | M80: 0 | N80: 3 | P80: Measured | Q80: 3212.2 | R80: CNY | S80: 2011 | T80: 0.284 | U80: =T80*Q80 -> 912.2648 | V80: =U80/I80 -> 144.16321 | W80: =IF(OR(B80 = "BG",B80 = "GR",B80 = "IT",B80 = "ES",B80 = "PT",B80 = "TR", B80 = "KR",B80 = "SE",B80 = "CH",B80 = "NO",B80 = "DK",B80 = "FI"), 1, 0) -> 0 | X80: =W80*I80 -> 0 | Y80: =W80*K80 -> 0 | Z80: =IF(OR(B80 = "US",B80 = "CA",B80 = "UK",B80 = "NZ",B80 = "AU",B80 = "SG"), 1, 0) -> 0 | AA80: =VLOOKUP(S80,CPI!$A$2:$F$71,6,0) -> 1.4320082 | AB80: =U80*AA80 -> 1306.3707 | AC80: =V80*AA80 -> 206.44291 | AD80: Media | AE80: https://max.book118.com/html/2017/1209/143431974.shtm
A81: 7651 | B81: CN | C81: Beijing | D81: Line 8 | E81: Line 8 Phase 2 South | G81: 2013 | H81: 0 | I81: 4.447 | J81: 1 | K81: 4.447 | L81: 0 | M81: 0 | N81: 6 | P81: Wiki | R81: CNY | S81: 2013 | T81: 0.273 | W81: =IF(OR(B81 = "BG",B81 = "GR",B81 = "IT",B81 = "ES",B81 = "PT",B81 = "TR", B81 = "KR",B81 = "SE",B81 = "CH",B81 = "NO",B81 = "DK",B81 = "FI"), 1, 0) -> 0 | X81: =W81*I81 -> 0 | Y81: =W81*K81 -> 0 | Z81: =IF(OR(B81 = "US",B81 = "CA",B81 = "UK",B81 = "NZ",B81 = "AU",B81 = "SG"), 1, 0) -> 0 | AA81: =VLOOKUP(S81,CPI!$A$2:$F$71,6,0) -> 1.3827208 | AD81: Media | AE81: https://zh.wikipedia.org/wiki/%E5%8C%97%E4%BA%AC%E5%9C%B0%E9%93%818%E5%8F%B7%E7%BA%BF
A82: 8112 | B82: CN | C82: Beijing | D82: Line 15 | E82: Line 15 Phase 1 | F82: 2009 | G82: 2014 | H82: 0 | I82: 41.4 | J82: 0.66908213 | K82: 27.7 | L82: 13.605 | M82: 0.471 | N82: 18 | O82: 117 | P82: Media | Q82: 18100 | R82: CNY | S82: 2010 | T82: 0.3 | U82: =T82*Q82 -> 5430 | V82: =U82/I82 -> 131.15942 | W82: =IF(OR(B82 = "BG",B82 = "GR",B82 = "IT",B82 = "ES",B82 = "PT",B82 = "TR", B82 = "KR",B82 = "SE",B82 = "CH",B82 = "NO",B82 = "DK",B82 = "FI"), 1, 0) -> 0 | X82: =W82*I82 -> 0 | Y82: =W82*K82 -> 0 | Z82: =IF(OR(B82 = "US",B82 = "CA",B82 = "UK",B82 = "NZ",B82 = "AU",B82 = "SG"), 1, 0) -> 0 | AA82: =VLOOKUP(S82,CPI!$A$2:$F$71,6,0) -> 1.47721 | AB82: =U82*AA82 -> 8021.2502 | AC82: =V82*AA82 -> 193.75 | AD82: Media | AE82: http://finance.ifeng.com/city/bj/20101117/2902241.shtml
A83: 7904 | B83: CN | C83: Beijing | D83: Line 7 | E83: Line 7 Phase 1 | F83: 2009 | G83: 2014 | H83: 0 | I83: 23.7 | J83: 1 | K83: 23.7 | L83: 0 | M83: 0 | N83: 21 | P83: Plan | Q83: 16000 | R83: CNY | S83: 2014 | T83: 0.266 | U83: =Q83*T83 -> 4256 | V83: =U83/I83 -> 179.57806 | W83: =IF(OR(B83 = "BG",B83 = "GR",B83 = "IT",B83 = "ES",B83 = "PT",B83 = "TR", B83 = "KR",B83 = "SE",B83 = "CH",B83 = "NO",B83 = "DK",B83 = "FI"), 1, 0) -> 0 | X83: =W83*I83 -> 0 | Y83: =W83*K83 -> 0 | Z83: =IF(OR(B83 = "US",B83 = "CA",B83 = "UK",B83 = "NZ",B83 = "AU",B83 = "SG"), 1, 0) -> 0 | AA83: =VLOOKUP(S83,CPI!$A$2:$F$71,6,0) -> 1.3606486 | AB83: =U83*AA83 -> 5790.9203 | AC83: =V83*AA83 -> 244.34263 | AD83: Media | AE83: http://bj.bendibao.com/news/20141120/171344.shtm
B84: CN | C84: Beijing | D84: Line 6 | E84: Line 6 Phase 2 | F84: 2011 | G84: 2014 | H84: 0 | I84: 12.4 | J84: 1 | K84: 12.4 | N84: 8 | O84: 156 | Q84: 6000 | R84: CNY | S84: 2013 | T84: 0.273 | U84: =Q84*T84 -> 1638 | V84: =U84/I84 -> 132.09677 | W84: =IF(OR(B84 = "BG",B84 = "GR",B84 = "IT",B84 = "ES",B84 = "PT",B84 = "TR", B84 = "KR",B84 = "SE",B84 = "CH",B84 = "NO",B84 = "DK",B84 = "FI"), 1, 0) -> 0 | X84: =W84*I84 -> 0 | Y84: =W84*K84 -> 0 | Z84: =IF(OR(B84 = "US",B84 = "CA",B84 = "UK",B84 = "NZ",B84 = "AU",B84 = "SG"), 1, 0) -> 0 | AA84: =VLOOKUP(S84,CPI!$A$2:$F$71,6,0) -> 1.3827208 | AB84: =U84*AA84 -> 2264.8967 | AC84: =V84*AA84 -> 182.65296 | AE84: http://politics.people.com.cn/n/2014/1105/c70731-25980932.html
A85: 7643 | B85: CN | C85: Beijing | D85: Line 14 | E85: Line 14 East | F85: 2010 | G85: 2015 | H85: 0 | I85: 31.4 | J85: 1 | K85: 31.4 | L85: 0 | M85: 0 | N85: 23 | P85: Media | R85: CNY | S85: 2012 | T85: 0.2808 | W85: =IF(OR(B85 = "BG",B85 = "GR",B85 = "IT",B85 = "ES",B85 = "PT",B85 = "TR", B85 = "KR",B85 = "SE",B85 = "CH",B85 = "NO",B85 = "DK",B85 = "FI"), 1, 0) -> 0 | X85: =W85*I85 -> 0 | Y85: =W85*K85 -> 0 | Z85: =IF(OR(B85 = "US",B85 = "CA",B85 = "UK",B85 = "NZ",B85 = "AU",B85 = "SG"), 1, 0) -> 0 | AA85: =VLOOKUP(S85,CPI!$A$2:$F$71,6,0) -> 1.4029744 | AD85: Media | AE85: http://www.mtr.bj.cn/article/5d510c13ebb1a36f5ef598dd.html; https://baike.baidu.com/item/%E5%8C%97%E4%BA%AC%E5%9C%B0%E9%93%8114%E5%8F%B7%E7%BA%BF#reference-[2]-1443669-wrap
A86: 8144 | B86: CN | C86: Beijing | D86: Line 8 | E86: Line 8 Phase 3 South | F86: 2014 | G86: 2018 | H86: 0 | I86: 13 | J86: 1 | K86: 13 | L86: 0 | M86: 0 | N86: 11 | P86: Measured | R86: CNY | S86: 2014 | T86: 0.266 | W86: =IF(OR(B86 = "BG",B86 = "GR",B86 = "IT",B86 = "ES",B86 = "PT",B86 = "TR", B86 = "KR",B86 = "SE",B86 = "CH",B86 = "NO",B86 = "DK",B86 = "FI"), 1, 0) -> 0 | X86: =W86*I86 -> 0 | Y86: =W86*K86 -> 0 | Z86: =IF(OR(B86 = "US",B86 = "CA",B86 = "UK",B86 = "NZ",B86 = "AU",B86 = "SG"), 1, 0) -> 0 | AA86: =VLOOKUP(S86,CPI!$A$2:$F$71,6,0) -> 1.3606486 | AD86: Media | AE86: https://www.bjsubway.com/news/ghjs/2013-12-30/1316.html
A87: 7785 | B87: CN | C87: Beijing | D87: Line 8 | E87: Line 8 Phase 4 | F87: 2016 | G87: 2018 | H87: 0 | I87: 3.4 | J87: =K87/I87 -> 0.29076471 | K87: 0.9886 | L87: 2.414 | M87: 0 | N87: 2 | P87: Wiki | Q87: 3420 | R87: CNY | S87: 2015 | T87: 0.258 | U87: =Q87*T87 -> 882.36 | V87: =U87/I87 -> 259.51765 | W87: =IF(OR(B87 = "BG",B87 = "GR",B87 = "IT",B87 = "ES",B87 = "PT",B87 = "TR", B87 = "KR",B87 = "SE",B87 = "CH",B87 = "NO",B87 = "DK",B87 = "FI"), 1, 0) -> 0 | X87: =W87*I87 -> 0 | Y87: =W87*K87 -> 0 | Z87: =IF(OR(B87 = "US",B87 = "CA",B87 = "UK",B87 = "NZ",B87 = "AU",B87 = "SG"), 1, 0) -> 0 | AA87: =VLOOKUP(S87,CPI!$A$2:$F$71,6,0) -> 1.3590354 | AB87: =U87*AA87 -> 1199.1585 | AC87: =V87*AA87 -> 352.69368 | AD87: Media | AE87: https://zh.wikipedia.org/wiki/%E5%8C%97%E4%BA%AC%E5%9C%B0%E9%93%818%E5%8F%B7%E7%BA%BF#%E4%B8%89%E6%9C%9F%E5%8F%8A%E5%9B%9B%E6%9C%9F%E5%B7%A5%E7%A8%8B
A88: 7985 | B88: CN | C88: Beijing | D88: Daxing Airport Express | E88: Daxing Airport Express Phase 1 | F88: 2016 | G88: 2019 | H88: 0 | I88: 44 | L88: #N/A | M88: #N/A | N88: 3 | P88: Plan | Q88: 27820 | R88: CNY | S88: 2019 | T88: 0.238 | U88: =T88*Q88 -> 6621.16 | V88: =U88/I88 -> 150.48091 | W88: =IF(OR(B88 = "BG",B88 = "GR",B88 = "IT",B88 = "ES",B88 = "PT",B88 = "TR", B88 = "KR",B88 = "SE",B88 = "CH",B88 = "NO",B88 = "DK",B88 = "FI"), 1, 0) -> 0 | X88: =W88*I88 -> 0 | Y88: =W88*K88 -> 0 | Z88: =IF(OR(B88 = "US",B88 = "CA",B88 = "UK",B88 = "NZ",B88 = "AU",B88 = "SG"), 1, 0) -> 0 | AA88: =VLOOKUP(S88,CPI!$A$2:$F$71,6,0) -> 1.2599479 | AB88: =U88*AA88 -> 8342.3166 | AC88: =V88*AA88 -> 189.59811 | AD88: Plan | AE88: http://www.tzxm.gov.cn/flfg/law/201912/t20191220_12825.html
A89: 7648 | B89: CN | C89: Beijing | D89: Capital Airport Express | E89: Capital Airport Express west extenion | F89: 2016 | G89: 2020 | H89: 0 | I89: 1.83 | J89: 1 | K89: 1.83 | N89: 1 | O89: 68 | Q89: 1800 | R89: CNY | S89: 2018 | T89: 0.237 | U89: =Q89*T89 -> 426.6 | V89: =U89/I89 -> 233.11475 | W89: =IF(OR(B89 = "BG",B89 = "GR",B89 = "IT",B89 = "ES",B89 = "PT",B89 = "TR", B89 = "KR",B89 = "SE",B89 = "CH",B89 = "NO",B89 = "DK",B89 = "FI"), 1, 0) -> 0 | X89: =W89*I89 -> 0 | Y89: =W89*K89 -> 0 | Z89: =IF(OR(B89 = "US",B89 = "CA",B89 = "UK",B89 = "NZ",B89 = "AU",B89 = "SG"), 1, 0) -> 0 | AA89: =VLOOKUP(S89,CPI!$A$2:$F$71,6,0) -> 1.2827779 | AB89: =U89*AA89 -> 547.23303 | AC89: =V89*AA89 -> 299.03445 | AD89: Media | AE89: https://new.qq.com/omn/20210301/20210301A0E4JW00.html
A90: 7816 | B90: CN | C90: Beijing | D90: Line 7 | E90: Line 7 Phase 2 (Eastern Extension) | F90: 2016 | G90: 2020 | H90: 0 | I90: 17.2 | J90: 0.87209302 | K90: 15 | L90: 0 | M90: 0 | N90: 9 | P90: Plan | Q90: 15330 | R90: CNY | S90: 2016 | T90: 0.251 | U90: =Q90*T90 -> 3847.83 | V90: =U90/I90 -> 223.71105 | W90: =IF(OR(B90 = "BG",B90 = "GR",B90 = "IT",B90 = "ES",B90 = "PT",B90 = "TR", B90 = "KR",B90 = "SE",B90 = "CH",B90 = "NO",B90 = "DK",B90 = "FI"), 1, 0) -> 0 | X90: =W90*I90 -> 0 | Y90: =W90*K90 -> 0 | Z90: =IF(OR(B90 = "US",B90 = "CA",B90 = "UK",B90 = "NZ",B90 = "AU",B90 = "SG"), 1, 0) -> 0 | AA90: =VLOOKUP(S90,CPI!$A$2:$F$71,6,0) -> 1.3421046 | AB90: =U90*AA90 -> 5164.1904 | AC90: =V90*AA90 -> 300.24363 | AD90: Media | AE90: https://zh.wikisource.org/zh-hans/%E5%8C%97%E4%BA%AC%E5%B8%82%E5%9F%8E%E5%B8%82%E8%BD%A8%E9%81%93%E4%BA%A4%E9%80%9A%E7%AC%AC%E4%BA%8C%E6%9C%9F%E5%BB%BA%E8%AE%BE%E8%A7%84%E5%88%92%EF%BC%882015%EF%BD%9E2021%E5%B9%B4%EF%BC%89
A91: 7795 | B91: CN | C91: Beijing | D91: Line 25 | E91: Line 25 Phase 2 (Fangshan Northern Extension) | F91: 2017 | G91: 2020 | H91: 0 | I91: 5 | L91: #N/A | M91: #N/A | N91: 4 | P91: Plan | Q91: 4860 | R91: CNY | S91: 2015 | T91: 0.258 | U91: =Q91*T91 -> 1253.88 | V91: =U91/I91 -> 250.776 | W91: =IF(OR(B91 = "BG",B91 = "GR",B91 = "IT",B91 = "ES",B91 = "PT",B91 = "TR", B91 = "KR",B91 = "SE",B91 = "CH",B91 = "NO",B91 = "DK",B91 = "FI"), 1, 0) -> 0 | X91: =W91*I91 -> 0 | Y91: =W91*K91 -> 0 | Z91: =IF(OR(B91 = "US",B91 = "CA",B91 = "UK",B91 = "NZ",B91 = "AU",B91 = "SG"), 1, 0) -> 0 | AA91: =VLOOKUP(S91,CPI!$A$2:$F$71,6,0) -> 1.3590354 | AB91: =U91*AA91 -> 1704.0673 | AC91: =V91*AA91 -> 340.81347 | AD91: Media | AE91: https://zh.wikisource.org/zh-hans/%E5%8C%97%E4%BA%AC%E5%B8%82%E5%9F%8E%E5%B8%82%E8%BD%A8%E9%81%93%E4%BA%A4%E9%80%9A%E7%AC%AC%E4%BA%8C%E6%9C%9F%E5%BB%BA%E8%AE%BE%E8%A7%84%E5%88%92%EF%BC%882015%EF%BD%9E2021%E5%B9%B4%EF%BC%89
A92: 7794 | B92: CN | C92: Beijing | D92: Line 16 | E92: Line 16 | F92: 2013 | G92: 2021 | H92: 0 | I92: 49.8 | J92: 1 | K92: 49.8 | L92: 0 | M92: 0 | N92: 29 | P92: Media | Q92: 49500 | R92: CNY | S92: 2013 | T92: 0.273 | U92: =Q92*T92 -> 13513.5 | V92: =U92/I92 -> 271.35542 | W92: =IF(OR(B92 = "BG",B92 = "GR",B92 = "IT",B92 = "ES",B92 = "PT",B92 = "TR", B92 = "KR",B92 = "SE",B92 = "CH",B92 = "NO",B92 = "DK",B92 = "FI"), 1, 0) -> 0 | X92: =W92*I92 -> 0 | Y92: =W92*K92 -> 0 | Z92: =IF(OR(B92 = "US",B92 = "CA",B92 = "UK",B92 = "NZ",B92 = "AU",B92 = "SG"), 1, 0) -> 0 | AA92: =VLOOKUP(S92,CPI!$A$2:$F$71,6,0) -> 1.3827208 | AB92: =U92*AA92 -> 18685.398 | AC92: =V92*AA92 -> 375.2088 | AD92: Media | AE92: http://www.bjnews.com.cn/news/2016/11/25/424943.html; https://baijiahao.baidu.com/s?id=1633332748114018963&wfr=spider&for=pc
A93: 7776 | B93: CN | C93: Beijing | D93: Line 3 | E93: Line 3 Phase 1+2 | F93: 2016 | G93: 2021 | H93: 0 | I93: 37.4 | J93: 0.55614973 | K93: 20.8 | L93: 0 | M93: 0 | N93: 27 | P93: Plan | Q93: 41500 | R93: CNY | S93: 2015 | T93: 0.258 | U93: =Q93*T93 -> 10707 | V93: =U93/I93 -> 286.28342 | W93: =IF(OR(B93 = "BG",B93 = "GR",B93 = "IT",B93 = "ES",B93 = "PT",B93 = "TR", B93 = "KR",B93 = "SE",B93 = "CH",B93 = "NO",B93 = "DK",B93 = "FI"), 1, 0) -> 0 | X93: =W93*I93 -> 0 | Y93: =W93*K93 -> 0 | Z93: =IF(OR(B93 = "US",B93 = "CA",B93 = "UK",B93 = "NZ",B93 = "AU",B93 = "SG"), 1, 0) -> 0 | AA93: =VLOOKUP(S93,CPI!$A$2:$F$71,6,0) -> 1.3590354 | AB93: =U93*AA93 -> 14551.192 | AC93: =V93*AA93 -> 389.06931 | AD93: Plan | AE93: http://www.gov.cn/xinwen/2018-02/18/content_5267552.htm; https://zh.m.wikisource.org/zh-hans/%E5%8C%97%E4%BA%AC%E5%B8%82%E5%9F%8E%E5%B8%82%E8%BD%A8%E9%81%93%E4%BA%A4%E9%80%9A%E7%AC%AC%E4%BA%8C%E6%9C%9F%E5%BB%BA%E8%AE%BE%E8%A7%84%E5%88%92%EF%BC%882015%EF%BD%9E2021%E5%B9%B4%EF%BC%89
A94: 7777 | B94: CN | C94: Beijing | D94: Line 12 | E94: Line 12 | F94: 2017 | G94: 2021 | H94: 0 | I94: 29.2 | J94: 1 | K94: 29.2 | L94: 0 | M94: 0 | N94: 21 | P94: Plan | Q94: 32400 | R94: CNY | S94: 2015 | T94: 0.258 | U94: =Q94*T94 -> 8359.2 | V94: =U94/I94 -> 286.27397 | W94: =IF(OR(B94 = "BG",B94 = "GR",B94 = "IT",B94 = "ES",B94 = "PT",B94 = "TR", B94 = "KR",B94 = "SE",B94 = "CH",B94 = "NO",B94 = "DK",B94 = "FI"), 1, 0) -> 0 | X94: =W94*I94 -> 0 | Y94: =W94*K94 -> 0 | Z94: =IF(OR(B94 = "US",B94 = "CA",B94 = "UK",B94 = "NZ",B94 = "AU",B94 = "SG"), 1, 0) -> 0 | AA94: =VLOOKUP(S94,CPI!$A$2:$F$71,6,0) -> 1.3590354 | AB94: =U94*AA94 -> 11360.449 | AC94: =V94*AA94 -> 389.05647 | AD94: Media | AE94: https://zh.wikisource.org/zh-hans/%E5%8C%97%E4%BA%AC%E5%B8%82%E5%9F%8E%E5%B8%82%E8%BD%A8%E9%81%93%E4%BA%A4%E9%80%9A%E7%AC%AC%E4%BA%8C%E6%9C%9F%E5%BB%BA%E8%AE%BE%E8%A7%84%E5%88%92%EF%BC%882015%EF%BD%9E2021%E5%B9%B4%EF%BC%89
A95: 7792 | B95: CN | C95: Beijing | D95: Line 19 | E95: Line 19 Phase 1 | F95: 2017 | G95: 2021 | H95: 0 | I95: 22.4 | J95: 1 | K95: 22.4 | L95: 0 | M95: 0 | N95: 10 | P95: Plan | Q95: 22180 | R95: CNY | S95: 2015 | T95: 0.258 | U95: =Q95*T95 -> 5722.44 | V95: =U95/I95 -> 255.46607 | W95: =IF(OR(B95 = "BG",B95 = "GR",B95 = "IT",B95 = "ES",B95 = "PT",B95 = "TR", B95 = "KR",B95 = "SE",B95 = "CH",B95 = "NO",B95 = "DK",B95 = "FI"), 1, 0) -> 0 | X95: =W95*I95 -> 0 | Y95: =W95*K95 -> 0 | Z95: =IF(OR(B95 = "US",B95 = "CA",B95 = "UK",B95 = "NZ",B95 = "AU",B95 = "SG"), 1, 0) -> 0 | AA95: =VLOOKUP(S95,CPI!$A$2:$F$71,6,0) -> 1.3590354 | AB95: =U95*AA95 -> 7776.9987 | AC95: =V95*AA95 -> 347.18744 | AD95: Media | AE95: https://zh.wikisource.org/zh-hans/%E5%8C%97%E4%BA%AC%E5%B8%82%E5%9F%8E%E5%B8%82%E8%BD%A8%E9%81%93%E4%BA%A4%E9%80%9A%E7%AC%AC%E4%BA%8C%E6%9C%9F%E5%BB%BA%E8%AE%BE%E8%A7%84%E5%88%92%EF%BC%882015%EF%BD%9E2021%E5%B9%B4%EF%BC%89
A96: 7760 | B96: CN | C96: Beijing | D96: Line 28 | E96: Line 28 | F96: 2017 | G96: 2021 | H96: 0 | I96: 8.777 | J96: 1 | K96: 8.777 | L96: 0 | M96: 0 | N96: 9 | P96: Media | Q96: =12.75*1000 -> 12750 | R96: CNY | S96: 2019 | T96: 0.238 | U96: =Q96*T96 -> 3034.5 | V96: =U96/I96 -> 345.73317 | W96: =IF(OR(B96 = "BG",B96 = "GR",B96 = "IT",B96 = "ES",B96 = "PT",B96 = "TR", B96 = "KR",B96 = "SE",B96 = "CH",B96 = "NO",B96 = "DK",B96 = "FI"), 1, 0) -> 0 | X96: =W96*I96 -> 0 | Y96: =W96*K96 -> 0 | Z96: =IF(OR(B96 = "US",B96 = "CA",B96 = "UK",B96 = "NZ",B96 = "AU",B96 = "SG"), 1, 0) -> 0 | AA96: =VLOOKUP(S96,CPI!$A$2:$F$71,6,0) -> 1.2599479 | AB96: =U96*AA96 -> 3823.3119 | AC96: =V96*AA96 -> 435.60578 | AD96: Media | AE96: http://www.tzxm.gov.cn/flfg/law/201912/t20191220_12825.html; https://new.qq.com/rain/a/20200812A0UGAJ00
A97: 7769 | B97: CN | C97: Beijing | D97: Line 11 | E97: Line 11 West | F97: 2019 | G97: 2021 | H97: 0 | I97: 4.2 | J97: 1 | K97: 4.2 | N97: 4 | O97: 138 | Q97: 5715 | R97: CNY | S97: 2020 | T97: 0.239 | U97: =Q97*T97 -> 1365.885 | V97: =U97/I97 -> 325.21071 | W97: =IF(OR(B97 = "BG",B97 = "GR",B97 = "IT",B97 = "ES",B97 = "PT",B97 = "TR", B97 = "KR",B97 = "SE",B97 = "CH",B97 = "NO",B97 = "DK",B97 = "FI"), 1, 0) -> 0 | X97: =W97*I97 -> 0 | Y97: =W97*K97 -> 0 | Z97: =IF(OR(B97 = "US",B97 = "CA",B97 = "UK",B97 = "NZ",B97 = "AU",B97 = "SG"), 1, 0) -> 0 | AA97: =VLOOKUP(S97,CPI!$A$2:$F$71,6,0) -> 1.2445935 | AB97: =U97*AA97 -> 1699.9717 | AC97: =V97*AA97 -> 404.75516 | AD97: Trade | AE97: http://www.rail-transit.com/project/show.php?itemid=360
A98: 7824 | B98: CN | C98: Beijing | D98: Line 27 | E98: Line 27 Phase 2 (Changping Southern Extension) | F98: 2019 | G98: 2021 | H98: 0 | I98: 16.6 | L98: #N/A | M98: #N/A | N98: 8 | P98: Plan | Q98: 14230 | R98: CNY | S98: 2015 | T98: 0.258 | U98: =Q98*T98 -> 3671.34 | V98: =U98/I98 -> 221.16506 | W98: =IF(OR(B98 = "BG",B98 = "GR",B98 = "IT",B98 = "ES",B98 = "PT",B98 = "TR", B98 = "KR",B98 = "SE",B98 = "CH",B98 = "NO",B98 = "DK",B98 = "FI"), 1, 0) -> 0 | X98: =W98*I98 -> 0 | Y98: =W98*K98 -> 0 | Z98: =IF(OR(B98 = "US",B98 = "CA",B98 = "UK",B98 = "NZ",B98 = "AU",B98 = "SG"), 1, 0) -> 0 | AA98: =VLOOKUP(S98,CPI!$A$2:$F$71,6,0) -> 1.3590354 | AB98: =U98*AA98 -> 4989.4811 | AC98: =V98*AA98 -> 300.57115 | AD98: Media | AE98: https://zh.wikisource.org/zh-hans/%E5%8C%97%E4%BA%AC%E5%B8%82%E5%9F%8E%E5%B8%82%E8%BD%A8%E9%81%93%E4%BA%A4%E9%80%9A%E7%AC%AC%E4%BA%8C%E6%9C%9F%E5%BB%BA%E8%AE%BE%E8%A7%84%E5%88%92%EF%BC%882015%EF%BD%9E2021%E5%B9%B4%EF%BC%89
A99: 7635 | B99: CN | C99: Beijing | D99: Line 8 | E99: Line 8 Phase 3 North | F99: 2019 | G99: 2021 | H99: 0 | I99: 3.6 | J99: 1 | K99: =I99 -> 3.6 | L99: 0 | M99: 0 | N99: 3 | P99: Media | R99: CNY | S99: 2020 | T99: 0.239 | W99: =IF(OR(B99 = "BG",B99 = "GR",B99 = "IT",B99 = "ES",B99 = "PT",B99 = "TR", B99 = "KR",B99 = "SE",B99 = "CH",B99 = "NO",B99 = "DK",B99 = "FI"), 1, 0) -> 0 | X99: =W99*I99 -> 0 | Y99: =W99*K99 -> 0 | Z99: =IF(OR(B99 = "US",B99 = "CA",B99 = "UK",B99 = "NZ",B99 = "AU",B99 = "SG"), 1, 0) -> 0 | AA99: =VLOOKUP(S99,CPI!$A$2:$F$71,6,0) -> 1.2445935 | AD99: Media | AE99: https://www.bjsubway.com/news/ghjs/2013-12-30/1316.html
A100: 7793 | B100: CN | C100: Beijing | D100: Line 17 | E100: Line 17 | F100: 2015 | G100: 2022 | H100: 0 | I100: 49.7 | J100: 1 | K100: 49.7 | N100: 20 | O100: 184 | Q100: 51085 | R100: CNY | S100: 2019 | T100: 0.238 | U100: =Q100*T100 -> 12158.23 | V100: =U100/I100 -> 244.63239 | W100: =IF(OR(B100 = "BG",B100 = "GR",B100 = "IT",B100 = "ES",B100 = "PT",B100 = "TR", B100 = "KR",B100 = "SE",B100 = "CH",B100 = "NO",B100 = "DK",B100 = "FI"), 1, 0) -> 0 | X100: =W100*I100 -> 0 | Y100: =W100*K100 -> 0 | Z100: =IF(OR(B100 = "US",B100 = "CA",B100 = "UK",B100 = "NZ",B100 = "AU",B100 = "SG"), 1, 0) -> 0 | AA100: =VLOOKUP(S100,CPI!$A$2:$F$71,6,0) -> 1.2599479 | AB100: =U100*AA100 -> 15318.736 | AC100: =V100*AA100 -> 308.22407 | AD100: Trade | AE100: http://www.rail-transit.com/project/show.php?itemid=92
A101: 7883 | B101: CN | C101: Beijing | D101: Line 13 | E101: Line 13A | F101: 2019 | G101: 2022 | H101: 0 | I101: 30.2 | J101: =K101/I101 -> 0.60264901 | K101: 18.2 | L101: 12.08 | M101: 0 | N101: 18 | P101: Plan | Q101: 23960 | R101: CNY | S101: 2019 | T101: 0.238 | U101: =Q101*T101 -> 5702.48 | V101: =U101/I101 -> 188.82384 | W101: =IF(OR(B101 = "BG",B101 = "GR",B101 = "IT",B101 = "ES",B101 = "PT",B101 = "TR", B101 = "KR",B101 = "SE",B101 = "CH",B101 = "NO",B101 = "DK",B101 = "FI"), 1, 0) -> 0 | X101: =W101*I101 -> 0 | Y101: =W101*K101 -> 0 | Z101: =IF(OR(B101 = "US",B101 = "CA",B101 = "UK",B101 = "NZ",B101 = "AU",B101 = "SG"), 1, 0) -> 0 | AA101: =VLOOKUP(S101,CPI!$A$2:$F$71,6,0) -> 1.2599479 | AB101: =U101*AA101 -> 7184.8277 | AC101: =V101*AA101 -> 237.9082 | AD101: Plan | AE101: http://www.tzxm.gov.cn/flfg/law/201912/t20191220_12825.html; https://baijiahao.baidu.com/s?id=1636643464335769195&wfr=spider&for=pc
A102: 8129 | B102: CN | C102: Beijing | D102: Line 13 | E102: Line 13B | F102: 2019 | G102: 2022 | H102: 0 | I102: 32.2 | J102: =K102/I102 -> 0.31987578 | K102: 10.3 | L102: 12.11 | M102: 10.108 | N102: 15 | P102: Plan | Q102: 12640 | R102: CNY | S102: 2019 | T102: 0.238 | U102: =T102*Q102 -> 3008.32 | V102: =U102/I102 -> 93.426087 | W102: =IF(OR(B102 = "BG",B102 = "GR",B102 = "IT",B102 = "ES",B102 = "PT",B102 = "TR", B102 = "KR",B102 = "SE",B102 = "CH",B102 = "NO",B102 = "DK",B102 = "FI"), 1, 0) -> 0 | X102: =W102*I102 -> 0 | Y102: =W102*K102 -> 0 | Z102: =IF(OR(B102 = "US",B102 = "CA",B102 = "UK",B102 = "NZ",B102 = "AU",B102 = "SG"), 1, 0) -> 0 | AA102: =VLOOKUP(S102,CPI!$A$2:$F$71,6,0) -> 1.2599479 | AB102: =U102*AA102 -> 3790.3265 | AC102: =V102*AA102 -> 117.712 | AD102: Plan | AE102: http://www.tzxm.gov.cn/flfg/law/201912/t20191220_12825.html
A103: 7864 | B103: CN | C103: Beijing | D103: Line 22 | E103: Line 22 | F103: 2019 | G103: 2022 | H103: 0 | I103: 78.6 | J103: 0.62 | K103: 48.5 | L103: 0 | M103: 0 | N103: 20 | P103: Plan | Q103: 63930 | R103: CNY | S103: 2019 | T103: 0.238 | U103: =Q103*T103 -> 15215.34 | V103: =U103/I103 -> 193.57939 | W103: =IF(OR(B103 = "BG",B103 = "GR",B103 = "IT",B103 = "ES",B103 = "PT",B103 = "TR", B103 = "KR",B103 = "SE",B103 = "CH",B103 = "NO",B103 = "DK",B103 = "FI"), 1, 0) -> 0 | X103: =W103*I103 -> 0 | Y103: =W103*K103 -> 0 | Z103: =IF(OR(B103 = "US",B103 = "CA",B103 = "UK",B103 = "NZ",B103 = "AU",B103 = "SG"), 1, 0) -> 0 | AA103: =VLOOKUP(S103,CPI!$A$2:$F$71,6,0) -> 1.2599479 | AB103: =U103*AA103 -> 19170.536 | AC103: =V103*AA103 -> 243.89994 | AD103: Plan | AE103: http://www.tzxm.gov.cn/flfg/law/201912/t20191220_12825.html
B104: CN | C104: Beijing | D104: Line M101 | E104: Line M101 | F104: 2022 | G104: 2027 | H104: 0 | I104: 19 | J104: 1 | K104: 19 | N104: 14 | O104: 138 | Q104: 18753.93 | R104: CNY | S104: 2021 | T104: 0.239 | U104: =Q104*T104 -> 4482.1893 | V104: =U104/I104 -> 235.9047 | W104: =IF(OR(B104 = "BG",B104 = "GR",B104 = "IT",B104 = "ES",B104 = "PT",B104 = "TR", B104 = "KR",B104 = "SE",B104 = "CH",B104 = "NO",B104 = "DK",B104 = "FI"), 1, 0) -> 0 | X104: =W104*I104 -> 0 | Y104: =W104*K104 -> 0 | Z104: =IF(OR(B104 = "US",B104 = "CA",B104 = "UK",B104 = "NZ",B104 = "AU",B104 = "SG"), 1, 0) -> 0 | AA104: =VLOOKUP(S104,CPI!$A$2:$F$71,6,0) -> 1.188746 | AB104: =U104*AA104 -> 5328.1845 | AC104: =V104*AA104 -> 280.43076 | AE104: https://web.archive.org/web/20220515142603/https://www.rails.cn/download/2022/20220418_%E9%99%84%E4%BB%B61%EF%BC%9A%E5%8C%97%E4%BA%AC%E8%BD%A8%E9%81%93%E4%BA%A4%E9%80%9AM101%E7%BA%BF%E4%B8%80%E6%9C%9F%E5%B7%A5%E7%A8%8B%E7%8E%AF%E5%A2%83%E5%BD%B1%E5%93%8D%E6%8A%A5%E5%91%8A%E4%B9%A6%EF%BC%88%E5%BE%81%E6%B1%82%E6%84%8F%E8%A7%81%E7%A8%BF%EF%BC%89.pdf
A105: 7642 | B105: CN | C105: Beijing | D105: Line 14 | E105: Line 14 West | F105: 2010 | H105: 0 | I105: 12.4 | J105: 0.59677419 | K105: 7.4 | L105: 4.565 | M105: 0.519 | N105: 7 | P105: Media | R105: CNY | S105: 2012 | T105: 0.2808 | W105: =IF(OR(B105 = "BG",B105 = "GR",B105 = "IT",B105 = "ES",B105 = "PT",B105 = "TR", B105 = "KR",B105 = "SE",B105 = "CH",B105 = "NO",B105 = "DK",B105 = "FI"), 1, 0) -> 0 | X105: =W105*I105 -> 0 | Y105: =W105*K105 -> 0 | Z105: =IF(OR(B105 = "US",B105 = "CA",B105 = "UK",B105 = "NZ",B105 = "AU",B105 = "SG"), 1, 0) -> 0 | AA105: =VLOOKUP(S105,CPI!$A$2:$F$71,6,0) -> 1.4029744 | AD105: Media | AE105: http://www.mtr.bj.cn/article/5d510c13ebb1a36f5ef598dd.html; https://baike.baidu.com/item/%E5%8C%97%E4%BA%AC%E5%9C%B0%E9%93%8114%E5%8F%B7%E7%BA%BF#reference-[2]-1443669-wrap
...

Sheet Sheet3
D7: 3928.5714
D8: 1792.4528
D9: 888.53333
D10: 292.5
D11: 854.76086
D12: 287.5
D13: 394.90244
D14: 535.71429
D15: 276.26
D16: 99.824
D17: 121.08636
D18: 391.72291
... D29: 160.5
D30: =QUARTILE(D7:D29,1) -> 207.97179
D31: =QUARTILE(D7:D30,3) -> 582.20759
D33: =MEDIAN(D7:D29) -> 287.5 | E33: =PERCENTILE(D7:D29,0.28) -> 228.583

Sheet 2_28_2026
A1: Country | B1: City | C1: Line | D1: Phase | E1: Start year | F1: End year | G1: RR? | H1: Length | I1: TunnelPer | J1: Tunnel | K1: Elevated | L1: Atgrade | M1: Stations | N1: Platform Length (Meters) | O1: Source1 | P1: Cost | Q1: Currency | R1: Year | S1: PPP rate | T1: Real cost | U1: Cost/km (Millions) | V1: Cheap? | W1: Clength | X1: Ctunnel | Y1: Anglo? | Z1: Inflation Index | AA1: Real cost (2025 dollars) | AB1: Cost/km (2025 dollars) | AC1: Source2 | AD1: Reference
A2: AE | B2: Dubai | C2: Phase 1 | D2: Phase 1 - Red Line | E2: 2005 | F2: 2010 | G2: 0 | H2: 35 | I2: =J2/H2 -> 0.13428571 | J2: 4.7 | K2: 0 | L2: 0 | M2: 29 | O2: Trade | P2: 4200 | Q2: USD | R2: 2005 | S2: 1.8 | T2: =P2*S2 -> 7560 | U2: =T2/H2 -> 216 | V2: =IF(OR(A2 = "BG",A2 = "GR",A2 = "IT",A2 = "ES",A2 = "PT",A2 = "TR", A2 = "KR",A2 = "SE",A2 = "CH",A2 = "NO",A2 = "DK",A2 = "FI"), 1, 0) -> 0 | W2: =V2*H2 -> 0 | X2: =V2*J2 -> 0 | Y2: =IF(OR(A2 = "US",A2 = "CA",A2 = "UK",A2 = "NZ",A2 = "AU",A2 = "SG"), 1, 0) -> 0 | Z2: =VLOOKUP(R2,CPI!$A$2:$F$71,6,0) -> 1.6493318 | AA2: =T2*Z2 -> 12468.948 | AB2: =U2*Z2 -> 356.25567
A3: AE | B3: Dubai | C3: Phase 2 | D3: Phase 2 - Green Line | E3: 2006 | F3: 2010 | G3: 0 | H3: 22.5 | I3: =J3/H3 -> 0.35111111 | J3: 7.9 | K3: 0 | L3: 0 | M3: 20 | P3: 3600 | Q3: USD | R3: 2006 | S3: 1.9 | T3: =P3*S3 -> 6840 | U3: =T3/H3 -> 304 | V3: =IF(OR(A3 = "BG",A3 = "GR",A3 = "IT",A3 = "ES",A3 = "PT",A3 = "TR", A3 = "KR",A3 = "SE",A3 = "CH",A3 = "NO",A3 = "DK",A3 = "FI"), 1, 0) -> 0 | W3: =V3*H3 -> 0 | X3: =V3*J3 -> 0 | Y3: =IF(OR(A3 = "US",A3 = "CA",A3 = "UK",A3 = "NZ",A3 = "AU",A3 = "SG"), 1, 0) -> 0 | Z3: =VLOOKUP(R3,CPI!$A$2:$F$71,6,0) -> 1.5977902 | AA3: =T3*Z3 -> 10928.885 | AB3: =U3*Z3 -> 485.72821
A4: AE | B4: Dubai | C4: Red Line | D4: Phase 3 (Red Line Extension/Route 2020) | E4: 2016 | F4: 2020 | G4: 0 | H4: 15 | I4: =J4/H4 -> 0.21333333 | J4: 3.2 | K4: 0 | L4: 0 | M4: 7 | O4: Trade | P4: 2900 | Q4: USD | R4: 2016 | S4: 1.9 | T4: =P4*S4 -> 5510 | U4: =T4/H4 -> 367.33333 | V4: =IF(OR(A4 = "BG",A4 = "GR",A4 = "IT",A4 = "ES",A4 = "PT",A4 = "TR", A4 = "KR",A4 = "SE",A4 = "CH",A4 = "NO",A4 = "DK",A4 = "FI"), 1, 0) -> 0 | W4: =V4*H4 -> 0 | X4: =V4*J4 -> 0 | Y4: =IF(OR(A4 = "US",A4 = "CA",A4 = "UK",A4 = "NZ",A4 = "AU",A4 = "SG"), 1, 0) -> 0 | Z4: =VLOOKUP(R4,CPI!$A$2:$F$71,6,0) -> 1.3421046 | AA4: =T4*Z4 -> 7394.9964 | AB4: =U4*Z4 -> 492.99976 | AC4: Media | AD4: https://www.railway-technology.com/projects/route-2020-dubai/
A5: AR | B5: Buenos Aires | C5: RER | D5: RER | E5: 2020 | F5: 2026 | G5: 1 | H5: 20 | I5: 1 | J5: 20 | K5: 0 | L5: 0 | M5: 4 | O5: Media | P5: 2300 | Q5: USD | R5: 2023 | S5: 2.02 | T5: =P5*S5 -> 4646 | U5: =T5/H5 -> 232.3 | V5: =IF(OR(A5 = "BG",A5 = "GR",A5 = "IT",A5 = "ES",A5 = "PT",A5 = "TR", A5 = "KR",A5 = "SE",A5 = "CH",A5 = "NO",A5 = "DK",A5 = "FI"), 1, 0) -> 0 | W5: =V5*H5 -> 0 | X5: =V5*J5 -> 0 | Y5: =IF(OR(A5 = "US",A5 = "CA",A5 = "UK",A5 = "NZ",A5 = "AU",A5 = "SG"), 1, 0) -> 0 | Z5: =VLOOKUP(R5,CPI!$A$2:$F$71,6,0) -> 1.057146 | AA5: =T5*Z5 -> 4911.5003 | AB5: =U5*Z5 -> 245.57502 | AC5: Media | AD5: https://tn.com.ar/economia/el-gobierno-relanzo-el-rer-el-proyecto-para-conectar-los-trenes-del-area-metropolitana_856411
A6: AT | B6: Vienna | C6: va | D6: Lainz Tunnel | E6: 1999 | F6: 2012 | G6: 1 | H6: 12.8 | I6: 1 | J6: 12.8 | K6: 0 | L6: 0 | M6: 0 | O6: Media | P6: 1300 | Q6: EUR | R6: 2005 | S6: 1.25 | T6: =P6*S6 -> 1625 | U6: =T6/H6 -> 126.95312 | V6: =IF(OR(A6 = "BG",A6 = "GR",A6 = "IT",A6 = "ES",A6 = "PT",A6 = "TR", A6 = "KR",A6 = "SE",A6 = "CH",A6 = "NO",A6 = "DK",A6 = "FI"), 1, 0) -> 0 | W6: =V6*H6 -> 0 | X6: =V6*J6 -> 0 | Y6: =IF(OR(A6 = "US",A6 = "CA",A6 = "UK",A6 = "NZ",A6 = "AU",A6 = "SG"), 1, 0) -> 0 | Z6: =VLOOKUP(R6,CPI!$A$2:$F$71,6,0) -> 1.6493318 | AA6: =T6*Z6 -> 2680.1642 | AB6: =U6*Z6 -> 209.38783 | AC6: Media | AD6: https://wien.orf.at/v2/news/stories/2537074/
A7: AT | B7: Vienna | C7: Line 2 | D7: Line 2 extension | E7: 2010 | F7: 2013 | G7: 0 | H7: 4.2 | I7: 0 | J7: 0 | K7: 2.63 | L7: 1.57 | M7: 3 | O7: Media | P7: 320 | Q7: EUR | R7: 2012 | S7: 1.3 | T7: =P7*S7 -> 416 | U7: =T7/H7 -> 99.047619 | V7: =IF(OR(A7 = "BG",A7 = "GR",A7 = "IT",A7 = "ES",A7 = "PT",A7 = "TR", A7 = "KR",A7 = "SE",A7 = "CH",A7 = "NO",A7 = "DK",A7 = "FI"), 1, 0) -> 0 | W7: =V7*H7 -> 0 | X7: =V7*J7 -> 0 | Y7: =IF(OR(A7 = "US",A7 = "CA",A7 = "UK",A7 = "NZ",A7 = "AU",A7 = "SG"), 1, 0) -> 0 | Z7: =VLOOKUP(R7,CPI!$A$2:$F$71,6,0) -> 1.4029744 | AA7: =T7*Z7 -> 583.63734 | AB7: =U7*Z7 -> 138.96127 | AC7: Media | AD7: https://wien.orf.at/news/stories/2607445/
A8: AT | B8: Vienna | C8: Line 1 | D8: Line 1 extension | E8: 2012 | F8: 2017 | G8: 0 | H8: 4.7 | I8: 0.57 | J8: 2.7 | K8: 0.06 | L8: 2.008 | M8: 5 | O8: Measured | P8: 600 | Q8: EUR | R8: 2015 | S8: 1.3 | T8: =P8*S8 -> 780 | U8: =T8/H8 -> 165.95745 | V8: =IF(OR(A8 = "BG",A8 = "GR",A8 = "IT",A8 = "ES",A8 = "PT",A8 = "TR", A8 = "KR",A8 = "SE",A8 = "CH",A8 = "NO",A8 = "DK",A8 = "FI"), 1, 0) -> 0 | W8: =V8*H8 -> 0 | X8: =V8*J8 -> 0 | Y8: =IF(OR(A8 = "US",A8 = "CA",A8 = "UK",A8 = "NZ",A8 = "AU",A8 = "SG"), 1, 0) -> 0 | Z8: =VLOOKUP(R8,CPI!$A$2:$F$71,6,0) -> 1.3590354 | AA8: =T8*Z8 -> 1060.0476 | AB8: =U8*Z8 -> 225.54205 | AC8: Plan | AD8: https://www.wien.gv.at/stadtentwicklung/projekte/verkehrsplanung/u-bahn/u1-oberlaa.html
A9: AT | B9: Vienna | C9: U2/U5 cross | D9: U2/U5 cross | E9: 2019 | F9: 2029 | G9: 0 | H9: 9 | I9: 1 | J9: 9 | K9: 0 | L9: 0 | M9: 11 | O9: Plan | P9: 2200 | Q9: EUR | R9: 2023 | S9: 1.3 | T9: =P9*S9 -> 2860 | U9: =T9/H9 -> 317.77778 | V9: =IF(OR(A9 = "BG",A9 = "GR",A9 = "IT",A9 = "ES",A9 = "PT",A9 = "TR", A9 = "KR",A9 = "SE",A9 = "CH",A9 = "NO",A9 = "DK",A9 = "FI"), 1, 0) -> 0 | W9: =V9*H9 -> 0 | X9: =V9*J9 -> 0 | Y9: =IF(OR(A9 = "US",A9 = "CA",A9 = "UK",A9 = "NZ",A9 = "AU",A9 = "SG"), 1, 0) -> 0 | Z9: =VLOOKUP(R9,CPI!$A$2:$F$71,6,0) -> 1.057146 | AA9: =T9*Z9 -> 3023.4376 | AB9: =U9*Z9 -> 335.93751 | AC9: Media | AD9: https://wien.orf.at/news/stories/2940360/
A10: AU | B10: Melbourne | C10: Metro Tunnel | D10: Metro Tunnel | E10: 2018 | F10: 2025 | G10: 0 | H10: 9 | I10: 1 | J10: 9 | K10: 0 | L10: 0 | M10: 5 | O10: Plan | P10: 12584.4 | Q10: AUD | R10: 2021 | S10: 0.69 | T10: =P10*S10 -> 8683.236 | U10: =T10/H10 -> 964.804 | V10: =IF(OR(A10 = "BG",A10 = "GR",A10 = "IT",A10 = "ES",A10 = "PT",A10 = "TR", A10 = "KR",A10 = "SE",A10 = "CH",A10 = "NO",A10 = "DK",A10 = "FI"), 1, 0) -> 0 | W10: =V10*H10 -> 0 | X10: =V10*J10 -> 0 | Y10: =IF(OR(A10 = "US",A10 = "CA",A10 = "UK",A10 = "NZ",A10 = "AU",A10 = "SG"), 1, 0) -> 1 | Z10: =VLOOKUP(R10,CPI!$A$2:$F$71,6,0) -> 1.188746 | AA10: =T10*Z10 -> 10322.162 | AB10: =U10*Z10 -> 1146.9069 | AC10: Plan | AD10: https://www.audit.vic.gov.au/report/melbourne-metro-tunnel-project-phase-2-main-works?section=
A11: AU | B11: Perth | C11: Forrestfield-Airport Link | D11: Forrestfield-Airport Link | E11: 2016 | F11: 2021 | G11: 1 | H11: 8.5 | I11: 1 | J11: 8.5 | K11: 0 | L11: 0 | M11: 3 | O11: Plan | P11: 1860 | Q11: AUD | R11: 2018 | S11: 0.69 | T11: =P11*S11 -> 1283.4 | U11: =T11/H11 -> 150.98824 | V11: =IF(OR(A11 = "BG",A11 = "GR",A11 = "IT",A11 = "ES",A11 = "PT",A11 = "TR", A11 = "KR",A11 = "SE",A11 = "CH",A11 = "NO",A11 = "DK",A11 = "FI"), 1, 0) -> 0 | W11: =V11*H11 -> 0 | X11: =V11*J11 -> 0 | Y11: =IF(OR(A11 = "US",A11 = "CA",A11 = "UK",A11 = "NZ",A11 = "AU",A11 = "SG"), 1, 0) -> 1 | Z11: =VLOOKUP(R11,CPI!$A$2:$F$71,6,0) -> 1.2827779 | AA11: =T11*Z11 -> 1646.3171 | AB11: =U11*Z11 -> 193.68437 | AC11: Plan | AD11: https://www.forrestfieldairportlink.wa.gov.au/Portals/14/Project%20Overview%20Fact%20Sheet%20-%20Dec18%20WEB.pdf
A12: AU | B12: Sydney | C12: Metro NW | D12: Metro NW | E12: 2013 | F12: 2019 | G12: 0 | H12: 36 | I12: 0.42 | J12: 15.1 | K12: 0 | L12: 0 | M12: 13 | O12: Wiki | P12: 7800 | Q12: AUD | R12: 2016 | S12: 0.69 | T12: =P12*S12 -> 5382 | U12: =T12/H12 -> 149.5 | V12: =IF(OR(A12 = "BG",A12 = "GR",A12 = "IT",A12 = "ES",A12 = "PT",A12 = "TR", A12 = "KR",A12 = "SE",A12 = "CH",A12 = "NO",A12 = "DK",A12 = "FI"), 1, 0) -> 0 | W12: =V12*H12 -> 0 | X12: =V12*J12 -> 0 | Y12: =IF(OR(A12 = "US",A12 = "CA",A12 = "UK",A12 = "NZ",A12 = "AU",A12 = "SG"), 1, 0) -> 1 | Z12: =VLOOKUP(R12,CPI!$A$2:$F$71,6,0) -> 1.3421046 | AA12: =T12*Z12 -> 7223.207 | AB12: =U12*Z12 -> 200.64464 | AC12: Plan | AD12: https://www.transport.nsw.gov.au/news-and-events/media-releases/sydney-metro-northwest-under-budget
A13: AU | B13: Sydney | C13: Metro City & SW | D13: Metro City & SW | E13: 2017 | F13: 2024 | G13: 0 | H13: 30 | I13: 0.51 | J13: 15.3 | K13: 0 | L13: 0 | M13: 7 | O13: Wiki | P13: 15500 | Q13: AUD | R13: 2021 | S13: 0.69 | T13: =P13*S13 -> 10695 | U13: =T13/H13 -> 356.5 | V13: =IF(OR(A13 = "BG",A13 = "GR",A13 = "IT",A13 = "ES",A13 = "PT",A13 = "TR", A13 = "KR",A13 = "SE",A13 = "CH",A13 = "NO",A13 = "DK",A13 = "FI"), 1, 0) -> 0 | W13: =V13*H13 -> 0 | X13: =V13*J13 -> 0 | Y13: =IF(OR(A13 = "US",A13 = "CA",A13 = "UK",A13 = "NZ",A13 = "AU",A13 = "SG"), 1, 0) -> 1 | Z13: =VLOOKUP(R13,CPI!$A$2:$F$71,6,0) -> 1.188746 | AA13: =T13*Z13 -> 12713.638 | AB13: =U13*Z13 -> 423.78794 | AC13: Media | AD13: https://www.abc.net.au/news/2020-02-21/nsw-government-confirms-three-billion-metro-budget-blowout/11986968
A14: BD | B14: Dhaka | C14: Line 6 | D14: Line 6 | E14: 2015 | F14: 2022 | G14: 0 | H14: 21.3 | I14: 0 | J14: 0 | K14: 0 | L14: 0 | M14: 16 | O14: Media | P14: 334720 | Q14: BDT | R14: 2019 | S14: 0.032 | T14: =P14*S14 -> 10711.04 | U14: =T14/H14 -> 502.86573 | V14: =IF(OR(A14 = "BG",A14 = "GR",A14 = "IT",A14 = "ES",A14 = "PT",A14 = "TR", A14 = "KR",A14 = "SE",A14 = "CH",A14 = "NO",A14 = "DK",A14 = "FI"), 1, 0) -> 0 | W14: =V14*H14 -> 0 | X14: =V14*J14 -> 0 | Y14: =IF(OR(A14 = "US",A14 = "CA",A14 = "UK",A14 = "NZ",A14 = "AU",A14 = "SG"), 1, 0) -> 0 | Z14: =VLOOKUP(R14,CPI!$A$2:$F$71,6,0) -> 1.2599479 | AA14: =T14*Z14 -> 13495.352 | AB14: =U14*Z14 -> 633.58462 | AC14: Media | AD14: https://www.thedailystar.net/news/bangladesh/transport/news/metro-now-set-cost-50pc-more-3072816
A15: BD | B15: Dhaka | C15: Line 1 | D15: Line 1 | E15: 2020 | F15: 2026 | G15: 0 | H15: 31.2 | I15: 0.64 | J15: 19.9 | K15: 0 | L15: 0 | M15: 19 | O15: Media | P15: 525610 | Q15: BDT | R15: 2023 | S15: 0.032 | T15: =P15*S15 -> 16819.52 | U15: =T15/H15 -> 539.08718 | V15: =IF(OR(A15 = "BG",A15 = "GR",A15 = "IT",A15 = "ES",A15 = "PT",A15 = "TR", A15 = "KR",A15 = "SE",A15 = "CH",A15 = "NO",A15 = "DK",A15 = "FI"), 1, 0) -> 0 | W15: =V15*H15 -> 0 | X15: =V15*J15 -> 0 | Y15: =IF(OR(A15 = "US",A15 = "CA",A15 = "UK",A15 = "NZ",A15 = "AU",A15 = "SG"), 1, 0) -> 0 | Z15: =VLOOKUP(R15,CPI!$A$2:$F$71,6,0) -> 1.057146 | AA15: =T15*Z15 -> 17780.688 | AB15: =U15*Z15 -> 569.89385 | AC15: Media | AD15: https://bdnews24.com/economy/2019/10/15/govt-approves-two-more-metro-rail-projects-worth-tk-938bn
A16: BD | B16: Dhaka | C16: Line 5 | D16: Line 5 | E16: 2020 | F16: 2028 | G16: 0 | H16: 19.6 | I16: 0.7 | J16: 14 | K16: 0 | L16: 0 | M16: 14 | O16: Media | P16: 412380 | Q16: BDT | R16: 2024 | S16: 0.032 | T16: =P16*S16 -> 13196.16 | U16: =T16/H16 -> 673.27347 | V16: =IF(OR(A16 = "BG",A16 = "GR",A16 = "IT",A16 = "ES",A16 = "PT",A16 = "TR", A16 = "KR",A16 = "SE",A16 = "CH",A16 = "NO",A16 = "DK",A16 = "FI"), 1, 0) -> 0 | W16: =V16*H16 -> 0 | X16: =V16*J16 -> 0 | Y16: =IF(OR(A16 = "US",A16 = "CA",A16 = "UK",A16 = "NZ",A16 = "AU",A16 = "SG"), 1, 0) -> 0 | Z16: =VLOOKUP(R16,CPI!$A$2:$F$71,6,0) -> 1 | AA16: =T16*Z16 -> 13196.16 | AB16: =U16*Z16 -> 673.27347 | AC16: Media | AD16: https://bdnews24.com/economy/2019/10/15/govt-approves-two-more-metro-rail-projects-worth-tk-938bn
... A22: BG | B22: Sofia | C22: Line 3 | D22: Line 3 extension (Third Stage) | E22: 2021 | F22: 2026 | G22: 0 | H22: 3.1 | I22: 1 | J22: 3.1 | K22: 0 | L22: 0 | M22: 4 | O22: Plan | P22: 112.5 | Q22: EUR | R22: 2021 | S22: 3.32 | T22: =P22*S22 -> 373.5 | U22: =T22/H22 -> 120.48387 | V22: =IF(OR(A22 = "BG",A22 = "GR",A22 = "IT",A22 = "ES",A22 = "PT",A22 = "TR", A22 = "KR",A22 = "SE",A22 = "CH",A22 = "NO",A22 = "DK",A22 = "FI"), 1, 0) -> 1 | W22: =V22*H22 -> 3.1 | X22: =V22*J22 -> 3.1 | Y22: =IF(OR(A22 = "US",A22 = "CA",A22 = "UK",A22 = "NZ",A22 = "AU",A22 = "SG"), 1, 0) -> 0 | Z22: =VLOOKUP(R22,CPI!$A$2:$F$71,6,0) -> 1.188746 | AA22: =T22*Z22 -> 443.99663 | AB22: =U22*Z22 -> 143.22472 | AC22: Trade | AD22: https://seenews.com/news/sofia-opens-1125-mln-euro-tender-for-subway-expansion-681553
A23: BG | B23: Sofia | C23: Line 1 | D23: Line 1 northern | E23: 2009 | F23: cond | G23: 0 | H23: 5.1 | I23: 0.6 | J23: 3.1 | K23: 0 | L23: 0 | M23: 4 | O23: Measured | P23: 407 | Q23: BGN | R23: 2010 | S23: 1.69 | T23: =P23*S23 -> 687.83 | U23: =T23/H23 -> 134.86863 | V23: =IF(OR(A23 = "BG",A23 = "GR",A23 = "IT",A23 = "ES",A23 = "PT",A23 = "TR", A23 = "KR",A23 = "SE",A23 = "CH",A23 = "NO",A23 = "DK",A23 = "FI"), 1, 0) -> 1 | W23: =V23*H23 -> 5.1 | X23: =V23*J23 -> 3.1 | Y23: =IF(OR(A23 = "US",A23 = "CA",A23 = "UK",A23 = "NZ",A23 = "AU",A23 = "SG"), 1, 0) -> 0 | Z23: =VLOOKUP(R23,CPI!$A$2:$F$71,6,0) -> 1.47721 | AA23: =T23*Z23 -> 1016.0693 | AB23: =U23*Z23 -> 199.22928 | AC23: Media | AD23: https://www.novinite.com/articles/167648/Subway+Trains+to+Sofia+Airport+Start+Running+at+1+pm+on+April+2
A24: BH | B24: Bahrain | C24: Phase 1 | D24: Phase 1 (Red & Blue) | E24: 2018 | F24: 2023 | G24: 1 | H24: 28.6 | I24: =J24/H24 -> 0 | J24: 0 | K24: 0 | L24: 0 | M24: 20 | P24: 453 | Q24: BD | R24: 2019 | S24: =1/0.2 -> 5 | T24: =P24*S24 -> 2265 | U24: =T24/H24 -> 79.195804 | V24: =IF(OR(A24 = "BG",A24 = "GR",A24 = "IT",A24 = "ES",A24 = "PT",A24 = "TR", A24 = "KR",A24 = "SE",A24 = "CH",A24 = "NO",A24 = "DK",A24 = "FI"), 1, 0) -> 0 | W24: =V24*H24 -> 0 | X24: =V24*J24 -> 0 | Y24: =IF(OR(A24 = "US",A24 = "CA",A24 = "UK",A24 = "NZ",A24 = "AU",A24 = "SG"), 1, 0) -> 0 | Z24: =VLOOKUP(R24,CPI!$A$2:$F$71,6,0) -> 1.2599479 | AA24: =T24*Z24 -> 2853.782 | AB24: =U24*Z24 -> 99.782587 | AC24: Media | AD24: https://www.urbantransportnews.com/bahrain-to-finalise-109-km-light-metro-rail-bids-in-march-2020/
A25: BH | B25: Bahrain | C25: Phase 2 | D25: Phase 2 | E25: 2020 | F25: X | G25: 1 | H25: 72.7 | I25: =J25/H25 -> 0 | J25: 0 | K25: 0 | L25: 0 | P25: 1500 | Q25: BD | R25: 2010 | S25: =1/0.2 -> 5 | T25: =P25*S25 -> 7500 | U25: =T25/H25 -> 103.16369 | V25: =IF(OR(A25 = "BG",A25 = "GR",A25 = "IT",A25 = "ES",A25 = "PT",A25 = "TR", A25 = "KR",A25 = "SE",A25 = "CH",A25 = "NO",A25 = "DK",A25 = "FI"), 1, 0) -> 0 | W25: =V25*H25 -> 0 | X25: =V25*J25 -> 0 | Y25: =IF(OR(A25 = "US",A25 = "CA",A25 = "UK",A25 = "NZ",A25 = "AU",A25 = "SG"), 1, 0) -> 0 | Z25: =VLOOKUP(R25,CPI!$A$2:$F$71,6,0) -> 1.47721 | AA25: =T25*Z25 -> 11079.075 | AB25: =U25*Z25 -> 152.39443 | AC25: Media | AD25: http://www.tradearabia.com/news/stn_178416.html
A26: BR | B26: Rio de Janeiro | C26: Line 4 | D26: Line 4 | E26: 2010 | F26: 2016 | G26: 0 | H26: 16 | I26: 0.96 | J26: 15.4 | K26: 0 | L26: 0 | M26: 7 | O26: Measured | P26: 10300 | Q26: BRL | R26: 2013 | S26: 0.59 | T26: =P26*S26 -> 6077 | U26: =T26/H26 -> 379.8125 | V26: =IF(OR(A26 = "BG",A26 = "GR",A26 = "IT",A26 = "ES",A26 = "PT",A26 = "TR", A26 = "KR",A26 = "SE",A26 = "CH",A26 = "NO",A26 = "DK",A26 = "FI"), 1, 0) -> 0 | W26: =V26*H26 -> 0 | X26: =V26*J26 -> 0 | Y26: =IF(OR(A26 = "US",A26 = "CA",A26 = "UK",A26 = "NZ",A26 = "AU",A26 = "SG"), 1, 0) -> 0 | Z26: =VLOOKUP(R26,CPI!$A$2:$F$71,6,0) -> 1.3827208 | AA26: =T26*Z26 -> 8402.7946 | AB26: =U26*Z26 -> 525.17466 | AC26: Trade | AD26: http://itdpbrasil.org.br/wp-content/uploads/2018/05/ITDP_PP_Linha_4_Maio_2018.pdf
A27: BR | B27: Salvador | C27: Lines 1-2 | D27: Lines 1-2 | E27: 2000 | F27: 2017 | G27: 0 | H27: 33 | I27: 0.04 | J27: 1.4 | K27: 10.935 | L27: 20.745 | M27: 20 | O27: Wiki | P27: 4800 | Q27: BRL | R27: 2012 | S27: 0.62 | T27: =P27*S27 -> 2976 | U27: =T27/H27 -> 90.181818 | V27: =IF(OR(A27 = "BG",A27 = "GR",A27 = "IT",A27 = "ES",A27 = "PT",A27 = "TR", A27 = "KR",A27 = "SE",A27 = "CH",A27 = "NO",A27 = "DK",A27 = "FI"), 1, 0) -> 0 | W27: =V27*H27 -> 0 | X27: =V27*J27 -> 0 | Y27: =IF(OR(A27 = "US",A27 = "CA",A27 = "UK",A27 = "NZ",A27 = "AU",A27 = "SG"), 1, 0) -> 0 | Z27: =VLOOKUP(R27,CPI!$A$2:$F$71,6,0) -> 1.4029744 | AA27: =T27*Z27 -> 4175.2518 | AB27: =U27*Z27 -> 126.52278 | AC27: Media | AD27: http://patrocinados.estadao.com.br/ccr/salvadors-subway-becomes-a-model-of-success/
A28: BR | B28: Salvador | C28: SkyRail Bahia | D28: SkyRail Bahia | E28: 2020 | F28: 2022 | G28: 0 | H28: 23.3 | I28: 0 | J28: 0 | K28: 0 | L28: 0 | M28: 26 | O28: Trade | P28: 689 | Q28: USD | R28: 2021 | S28: 2.3 | T28: =P28*S28 -> 1584.7 | U28: =T28/H28 -> 68.012876 | V28: =IF(OR(A28 = "BG",A28 = "GR",A28 = "IT",A28 = "ES",A28 = "PT",A28 = "TR", A28 = "KR",A28 = "SE",A28 = "CH",A28 = "NO",A28 = "DK",A28 = "FI"), 1, 0) -> 0 | W28: =V28*H28 -> 0 | X28: =V28*J28 -> 0 | Y28: =IF(OR(A28 = "US",A28 = "CA",A28 = "UK",A28 = "NZ",A28 = "AU",A28 = "SG"), 1, 0) -> 0 | Z28: =VLOOKUP(R28,CPI!$A$2:$F$71,6,0) -> 1.188746 | AA28: =T28*Z28 -> 1883.8058 | AB28: =U28*Z28 -> 80.850033 | AC28: Trade | AD28: https://www.yicaiglobal.com/news/byd-design-for-usd689-million-brazil-monorail-gets-green-light
A29: BR | B29: Sao Paulo | C29: Line 5 | D29: Line 5 extension | E29: 2010 | F29: 2019 | G29: 0 | H29: 12 | I29: 1 | J29: 12 | K29: 0 | L29: 0 | M29: 11 | O29: Wiki | P29: 6900 | Q29: BRL | R29: 2014 | S29: 0.55 | T29: =P29*S29 -> 3795 | U29: =T29/H29 -> 316.25 | V29: =IF(OR(A29 = "BG",A29 = "GR",A29 = "IT",A29 = "ES",A29 = "PT",A29 = "TR", A29 = "KR",A29 = "SE",A29 = "CH",A29 = "NO",A29 = "DK",A29 = "FI"), 1, 0) -> 0 | W29: =V29*H29 -> 0 | X29: =V29*J29 -> 0 | Y29: =IF(OR(A29 = "US",A29 = "CA",A29 = "UK",A29 = "NZ",A29 = "AU",A29 = "SG"), 1, 0) -> 0 | Z29: =VLOOKUP(R29,CPI!$A$2:$F$71,6,0) -> 1.3606486 | AA29: =T29*Z29 -> 5163.6613 | AB29: =U29*Z29 -> 430.30511 | AC29: Trade | AD29: https://www.bnamericas.com/en/news/brazil-metro-cost-overruns-top-us9bn1
A30: BR | B30: Sao Paulo | C30: Line 17 | D30: Line 17 | E30: 2012 | F30: 2021 | G30: 0 | H30: 7.7 | I30: 0 | J30: 0 | K30: 0 | L30: 0 | M30: 8 | O30: Trade | P30: 1300 | Q30: USD | R30: 2016 | S30: 2.3 | T30: =P30*S30 -> 2990 | U30: =T30/H30 -> 388.31169 | V30: =IF(OR(A30 = "BG",A30 = "GR",A30 = "IT",A30 = "ES",A30 = "PT",A30 = "TR", A30 = "KR",A30 = "SE",A30 = "CH",A30 = "NO",A30 = "DK",A30 = "FI"), 1, 0) -> 0 | W30: =V30*H30 -> 0 | X30: =V30*J30 -> 0 | Y30: =IF(OR(A30 = "US",A30 = "CA",A30 = "UK",A30 = "NZ",A30 = "AU",A30 = "SG"), 1, 0) -> 0 | Z30: =VLOOKUP(R30,CPI!$A$2:$F$71,6,0) -> 1.3421046 | AA30: =T30*Z30 -> 4012.8928 | AB30: =U30*Z30 -> 521.15491 | AC30: Trade | AD30: https://www.railjournal.com/in_depth/21-rail-projects-to-watch-in-2021
A31: BR | B31: Sao Paulo | C31: Line 6 | D31: Line 6 phase 1 | E31: 2015 | F31: 2023 | G31: 0 | H31: 15.9 | I31: 0.84 | J31: 13.4 | K31: 0 | L31: 0 | M31: 15 | O31: Trade | P31: 9600 | Q31: BRL | R31: 2020 | S31: 0.44 | T31: =P31*S31 -> 4224 | U31: =T31/H31 -> 265.66038 | V31: =IF(OR(A31 = "BG",A31 = "GR",A31 = "IT",A31 = "ES",A31 = "PT",A31 = "TR", A31 = "KR",A31 = "SE",A31 = "CH",A31 = "NO",A31 = "DK",A31 = "FI"), 1, 0) -> 0 | W31: =V31*H31 -> 0 | X31: =V31*J31 -> 0 | Y31: =IF(OR(A31 = "US",A31 = "CA",A31 = "UK",A31 = "NZ",A31 = "AU",A31 = "SG"), 1, 0) -> 0 | Z31: =VLOOKUP(R31,CPI!$A$2:$F$71,6,0) -> 1.2445935 | AA31: =T31*Z31 -> 5257.1631 | AB31: =U31*Z31 -> 330.63919 | AC31: Trade | AD31: https://www.railjournal.com/passenger/metros/revival-of-sao-paulo-metro-line-6-orange-project-a-step-closer/
A32: CA | B32: Calgary | C32: Green Line | D32: Green Line stage 1 | E32: 2021 | F32: 2027 | G32: 0 | H32: 20 | I32: 0.2 | J32: 4 | K32: 0 | L32: 0 | M32: 15 | O32: Wiki | P32: 5500 | Q32: CAD | R32: 2024 | S32: 0.84 | T32: =P32*S32 -> 4620 | U32: =T32/H32 -> 231 | V32: =IF(OR(A32 = "BG",A32 = "GR",A32 = "IT",A32 = "ES",A32 = "PT",A32 = "TR", A32 = "KR",A32 = "SE",A32 = "CH",A32 = "NO",A32 = "DK",A32 = "FI"), 1, 0) -> 0 | W32: =V32*H32 -> 0 | X32: =V32*J32 -> 0 | Y32: =IF(OR(A32 = "US",A32 = "CA",A32 = "UK",A32 = "NZ",A32 = "AU",A32 = "SG"), 1, 0) -> 1 | Z32: =VLOOKUP(R32,CPI!$A$2:$F$71,6,0) -> 1 | AA32: =T32*Z32 -> 4620 | AB32: =U32*Z32 -> 231 | AC32: Media | AD32: https://globalnews.ca/news/7527443/green-line-lrt-calgary-alberta-government/
A33: CA | B33: Edmonton | C33: Valley Line Southeast | D33: Southeast | E33: 2016 | F33: 2023 | G33: 0 | H33: 13.1 | I33: 0.03 | J33: 0.4 | M33: 12 | N33: 125 | O33: Wiki | P33: 1800 | Q33: CAD | R33: 2019 | S33: 0.802 | T33: =P33*S33 -> 1443.6 | U33: =T33/H33 -> 110.19847 | V33: =IF(OR(A33 = "BG",A33 = "GR",A33 = "IT",A33 = "ES",A33 = "PT",A33 = "TR", A33 = "KR",A33 = "SE",A33 = "CH",A33 = "NO",A33 = "DK",A33 = "FI"), 1, 0) -> 0 | W33: =V33*H33 -> 0 | X33: =V33*J33 -> 0 | Y33: =IF(OR(A33 = "US",A33 = "CA",A33 = "UK",A33 = "NZ",A33 = "AU",A33 = "SG"), 1, 0) -> 1 | Z33: =VLOOKUP(R33,CPI!$A$2:$F$71,6,0) -> 1.2599479 | AA33: =T33*Z33 -> 1818.8608 | AB33: =U33*Z33 -> 138.84433 | AC33: Media | AD33: https://edmontonjournal.com/news/local-news/long-delayed-1-8-billion-valley-line-lrt-stymied-yet-again
A34: CA | B34: Edmonton | C34: Metro Line Extension | D34: Northwest Phase 1 | E34: 2020 | F34: 2024 | G34: 0 | H34: 1.6 | I34: 0 | J34: 0 | K34: 0 | L34: 1.6 | M34: 2 | N34: 125 | O34: Plan | P34: 291 | Q34: CAD | R34: 2020 | S34: 0.81 | T34: =P34*S34 -> 235.71 | U34: =T34/H34 -> 147.31875 | Y34: 1 | Z34: =VLOOKUP(R34,CPI!$A$2:$F$71,6,0) -> 1.2445935 | AA34: =T34*Z34 -> 293.36314 | AB34: =U34*Z34 -> 183.35197 | AD34: https://www.edmonton.ca/projects_plans/transit/nw-lrt https://tam-america.com/article/edmonton-metro-northwest-lrt-extension-phase-completed-on-budget-before-time#:~:text=Phase%201%20construction%20was%20originally,million%20(US%24215%20million).
A35: CA | B35: Edmonton | C35: Valley Line Extension | D35: West | E35: 2022 | F35: 2028 | G35: 0 | H35: 14 | I35: 0 | J35: 0 | K35: 2.1 | L35: =14-2.1 -> 11.9 | M35: 14 | N35: 125 | O35: Plan | P35: 2700 | Q35: CAD | R35: 2022 | S35: 0.88 | T35: =P35*S35 -> 2376 | U35: =T35/H35 -> 169.71429 | V35: 0 | Y35: 1 | Z35: =VLOOKUP(R35,CPI!$A$2:$F$71,6,0) -> 1.1006629 | AA35: =T35*Z35 -> 2615.175 | AB35: =U35*Z35 -> 186.79822 | AC35: Media | AD35: https://majorprojects.alberta.ca/details/Valley-Line-West-LRT/3692 https://www.operis.com/case-study/edmonton-valley-line-west/
A36: CA | B36: Hamilton | C36: Hamilton LRT | D36: Phase 1 | E36: 2025 | F36: 2029 | G36: 0 | H36: 14 | I36: 0 | J36: 0 | K36: 0 | L36: 14 | M36: 17 | N36: 50 | O36: Plan | P36: 3400 | Q36: CAD | R36: 2025 | S36: 1 | T36: =P36*S36 -> 3400 | U36: =T36/H36 -> 242.85714 | Z36: =VLOOKUP(R36,CPI!$A$2:$F$71,6,0) -> 1 | AA36: =T36*Z36 -> 3400 | AB36: =U36*Z36 -> 242.85714 | AC36: Media | AD36: https://www.metrolinx.com/en/projects-and-programs/hamilton-lrt https://canada.constructconnect.com/dcn/news/infrastructure/2024/11/request-for-qualifications-issued-for-hamilton-lrt-project
A37: CA | B37: Mississauga | C37: Hazel McCallion LRT | D37: Phase 1 | E37: 2020 | F37: 2027 | G37: 0 | H37: 18 | I37: =(1/19)% -> 0.00052631579 | J37: 1 | L37: 18 | M37: 19 | N37: 50 | O37: Plan | P37: 4700 | Q37: CAD | R37: 2020 | S37: 0.84 | T37: =P37*S37 -> 3948 | U37: =T37/H37 -> 219.33333 | Z37: =VLOOKUP(R37,CPI!$A$2:$F$71,6,0) -> 1.2445935 | AA37: =T37*Z37 -> 4913.6553 | AB37: =U37*Z37 -> 272.98085 | AC37: Media | AD37: https://www.metrolinx.com/en/projects-and-programs/hazel-mccallion-lrt/faqs
A38: CA | B38: Montreal | C38: Laval extension | D38: Laval extension | E38: 2001 | F38: 2007 | G38: 0 | H38: 5.2 | I38: 1 | J38: 5.2 | K38: 0 | L38: 0 | M38: 3 | O38: Wiki | P38: 745 | Q38: CAD | R38: 2004 | S38: 0.81 | T38: =P38*S38 -> 603.45 | U38: =T38/H38 -> 116.04808 | V38: =IF(OR(A38 = "BG",A38 = "GR",A38 = "IT",A38 = "ES",A38 = "PT",A38 = "TR", A38 = "KR",A38 = "SE",A38 = "CH",A38 = "NO",A38 = "DK",A38 = "FI"), 1, 0) -> 0 | W38: =V38*H38 -> 0 | X38: =V38*J38 -> 0 | Y38: =IF(OR(A38 = "US",A38 = "CA",A38 = "UK",A38 = "NZ",A38 = "AU",A38 = "SG"), 1, 0) -> 1 | Z38: =VLOOKUP(R38,CPI!$A$2:$F$71,6,0) -> 1.7052118 | AA38: =T38*Z38 -> 1029.01 | AB38: =U38*Z38 -> 197.88654 | AC38: Media | AD38: https://montrealgazette.com/news/local-news/the-sleepy-success-story-of-the-laval-metro-extension
A39: CA | B39: Montreal | C39: Blue Line | D39: Blue Line | E39: 2020 | F39: 2026 | G39: 0 | H39: 5.8 | I39: 1 | J39: 5.8 | K39: 0 | L39: 0 | M39: 5 | O39: Media | P39: 7600 | Q39: CAD | R39: 2018 | S39: 0.84 | T39: =P39*S39 -> 6384 | U39: =T39/H39 -> 1100.6897 | V39: =IF(OR(A39 = "BG",A39 = "GR",A39 = "IT",A39 = "ES",A39 = "PT",A39 = "TR", A39 = "KR",A39 = "SE",A39 = "CH",A39 = "NO",A39 = "DK",A39 = "FI"), 1, 0) -> 0 | W39: =V39*H39 -> 0 | X39: =V39*J39 -> 0 | Y39: =IF(OR(A39 = "US",A39 = "CA",A39 = "UK",A39 = "NZ",A39 = "AU",A39 = "SG"), 1, 0) -> 1 | Z39: =VLOOKUP(R39,CPI!$A$2:$F$71,6,0) -> 1.2827779 | AA39: =T39*Z39 -> 8189.2539 | AB39: =U39*Z39 -> 1411.9403 | AC39: Media | AD39: https://montrealgazette.com/news/local-news/montreal-metro-green-light-for-blue-line-extension https://www.cbc.ca/news/canada/montreal/blue-line-extension-delayed-1.7303767
A40: CA | B40: Montreal | C40: PSE | D40: Phase 1 | E40: 2025 | F40: 2033 | G40: 0 | H40: 31 | I40: 0 | J40: 0 | K40: 0 | L40: 31 | M40: 36/22 | O40: Plan | P40: 19000 | Q40: CAD | R40: 2025 | S40: 1 | T40: 19000 | U40: =T40/H40 -> 612.90323 | Y40: 0 | Z40: =VLOOKUP(R40,CPI!$A$2:$F$71,6,0) -> 1 | AA40: =T40*Z40 -> 19000 | AB40: =U40*Z40 -> 612.90323 | AC40: Media | AD40: https://www.cbc.ca/news/canada/montreal/public-transit-project-announcement-eastern-montreal-1.7475018 https://www.artm.quebec/wp-content/uploads/2024/05/RP_PSE_AC_VFinale_2024-05-28.pdf
A41: CA | B41: Ottawa | C41: Confederation | D41: Confederation | E41: 2013 | F41: 2019 | G41: 0 | H41: 12.5 | I41: 0.2 | J41: 2.5 | K41: 0.84 | L41: 9.16 | M41: 13 | N41: 90/120 | O41: Trade | P41: 2100 | Q41: CAD | R41: 2016 | S41: 0.83 | T41: =P41*S41 -> 1743 | U41: =T41/H41 -> 139.44 | V41: =IF(OR(A41 = "BG",A41 = "GR",A41 = "IT",A41 = "ES",A41 = "PT",A41 = "TR", A41 = "KR",A41 = "SE",A41 = "CH",A41 = "NO",A41 = "DK",A41 = "FI"), 1, 0) -> 0 | W41: =V41*H41 -> 0 | X41: =V41*J41 -> 0 | Y41: =IF(OR(A41 = "US",A41 = "CA",A41 = "UK",A41 = "NZ",A41 = "AU",A41 = "SG"), 1, 0) -> 1 | Z41: =VLOOKUP(R41,CPI!$A$2:$F$71,6,0) -> 1.3421046 | AA41: =T41*Z41 -> 2339.2883 | AB41: =U41*Z41 -> 187.14307 | AC41: Trade | AD41: https://www.aecom.com/projects/ottawa-light-rail/
A42: CA | B42: Ottawa | C42: Confederation | D42: East West Extensions | E42: 2019 | F42: 2025 | G42: 0 | H42: 28 | I42: =(3.4/28) -> 0.12142857 | J42: 3.4 | K42: 0 | L42: 12 | M42: 17 | N42: 90/120 | O42: Plan | P42: 2600 | Q42: CAD | R42: 2019 | S42: 0.802 | T42: =P42*S42 -> 2085.2 | U42: =T42/H42 -> 74.471429 | Y42: 1 | Z42: =VLOOKUP(R42,CPI!$A$2:$F$71,6,0) -> 1.2599479 | AA42: =T42*Z42 -> 2627.2434 | AB42: =U42*Z42 -> 93.83012 | AC42: Trade | AD42: https://www.kiewit.com/projects/ottawa-lrt-stage-2/ https://pub-ottawa.escribemeetings.com/filestream.ashx?documentid=58389 https://delveunderground.com/projects/ottawa-light-rail-transit-stages-1-and-2
A43: CA | B43: Ottawa | C43: Line 2/Line 4 | D43: South Extension+Airport Link | E43: 2020 | F43: 2025 | G43: 0 | H43: 20 | I43: 0 | J43: 0 | K43: 0.5 | L43: 15.5 | M43: 13 | N43: 90/120 | O43: Plan | P43: 1660 | Q43: CAD | R43: 2019 | S43: 0.802 | T43: =P43*S43 -> 1331.32 | U43: =T43/H43 -> 66.566 | Z43: =VLOOKUP(R43,CPI!$A$2:$F$71,6,0) -> 1.2599479 | AA43: =T43*Z43 -> 1677.3938 | AB43: =U43*Z43 -> 83.869692 | AC43: Media | AD43: https://www.renewcanada.net/ottawa-proceeding-with-4-67-billion-stage-2-lrt/ https://www.atkinsrealis.com/en/projects/o-train-extension
A44: CA | B44: Toronto | C44: Sheppard | D44: Sheppard | E44: 1994 | F44: 2002 | G44: 0 | H44: 5.5 | I44: 1 | J44: 5.5 | K44: 0 | L44: 0 | M44: 5 | O44: Media | P44: 1000 | Q44: CAD | R44: 1998 | S44: 0.81 | T44: =P44*S44 -> 810 | U44: =T44/H44 -> 147.27273 | V44: =IF(OR(A44 = "BG",A44 = "GR",A44 = "IT",A44 = "ES",A44 = "PT",A44 = "TR", A44 = "KR",A44 = "SE",A44 = "CH",A44 = "NO",A44 = "DK",A44 = "FI"), 1, 0) -> 0 | W44: =V44*H44 -> 0 | X44: =V44*J44 -> 0 | Y44: =IF(OR(A44 = "US",A44 = "CA",A44 = "UK",A44 = "NZ",A44 = "AU",A44 = "SG"), 1, 0) -> 1 | Z44: =VLOOKUP(R44,CPI!$A$2:$F$71,6,0) -> 1.9761626 | AA44: =T44*Z44 -> 1600.6917 | AB44: =U44*Z44 -> 291.03485 | AC44: Media | AD44: https://www.theglobeandmail.com/news/toronto/sheppard-subway-extension-a-quarter-the-stops-for-three-times-the-cost/article622366/
A45: CA | B45: Toronto | C45: YUS | D45: Vaughan | E45: 2009 | F45: 2017 | G45: 0 | H45: 8.6 | I45: 1 | J45: 8.6 | K45: 0 | L45: 0 | M45: 6 | O45: Media | P45: 3200 | Q45: CAD | R45: 2013 | S45: 0.81 | T45: =P45*S45 -> 2592 | U45: =T45/H45 -> 301.39535 | V45: =IF(OR(A45 = "BG",A45 = "GR",A45 = "IT",A45 = "ES",A45 = "PT",A45 = "TR", A45 = "KR",A45 = "SE",A45 = "CH",A45 = "NO",A45 = "DK",A45 = "FI"), 1, 0) -> 0 | W45: =V45*H45 -> 0 | X45: =V45*J45 -> 0 | Y45: 1 | Z45: =VLOOKUP(R45,CPI!$A$2:$F$71,6,0) -> 1.3827208 | AA45: =T45*Z45 -> 3584.0124 | AB45: =U45*Z45 -> 416.74563 | AC45: Media | AD45: https://www.thestar.com/news/gta/transportation/2017/12/15/trudeau-wynne-tory-on-hand-to-cut-ribbon-on-32-billion-subway-extension.html
A46: CA | B46: Toronto | C46: Eglinton Crosstown | D46: Eglinton Crosstown | E46: 2011 | F46: 2025 | G46: 0 | H46: 19 | I46: 0.53 | J46: 10 | K46: 0.62 | L46: 8.31 | M46: 25 | O46: Plan | P46: 12800 | Q46: CAD | R46: 2016 | S46: 0.83 | T46: =P46*S46 -> 10624 | U46: =T46/H46 -> 559.15789 | V46: =IF(OR(A46 = "BG",A46 = "GR",A46 = "IT",A46 = "ES",A46 = "PT",A46 = "TR", A46 = "KR",A46 = "SE",A46 = "CH",A46 = "NO",A46 = "DK",A46 = "FI"), 1, 0) -> 0 | W46: =V46*H46 -> 0 | X46: =V46*J46 -> 0 | Y46: =IF(OR(A46 = "US",A46 = "CA",A46 = "UK",A46 = "NZ",A46 = "AU",A46 = "SG"), 1, 0) -> 1 | Z46: =VLOOKUP(R46,CPI!$A$2:$F$71,6,0) -> 1.3421046 | AA46: =T46*Z46 -> 14258.519 | AB46: =U46*Z46 -> 750.44839 | AC46: Trade | AD46: https://www.cbc.ca/news/canada/toronto/eglinton-crosstown-opening-june-ttc-1.7400691#:~:text=Construction%20began%20in%202011%2C%20when,to%20at%20least%20%2412.8%20billion.
A47: CA | B47: Toronto | C47: Finch West LRT | D47: Phase 1 | E47: 2019 | F47: 2025 | G47: 0 | H47: 10.3 | I47: =(1/19)% -> 0.00052631579 | J47: 1 | L47: 17 | M47: 18 | N47: 50 | O47: Plan | P47: 2500 | Q47: CAD | R47: 2019 | S47: 0.84 | T47: =P47*S47 -> 2100 | U47: =T47/H47 -> 203.8835 | Z47: =VLOOKUP(R47,CPI!$A$2:$F$71,6,0) -> 1.2599479 | AA47: =T47*Z47 -> 2645.8906 | AB47: =U47*Z47 -> 256.88258 | AC47: Media | AD47: https://www.infrastructureontario.ca/en/what-we-do/projectssearch/finch-west-light-rail-transit/
A48: CA | B48: Toronto | C48: Bloor/SSE | D48: Scarborough | E48: 2020 | F48: 2030 | G48: 0 | H48: 7.8 | I48: 1 | J48: 7.8 | K48: 0 | L48: 0 | M48: 3 | O48: Wiki | P48: 5500 | Q48: CAD | R48: 2018 | S48: 0.84 | T48: =P48*S48 -> 4620 | U48: =T48/H48 -> 592.30769 | V48: =IF(OR(A48 = "BG",A48 = "GR",A48 = "IT",A48 = "ES",A48 = "PT",A48 = "TR", A48 = "KR",A48 = "SE",A48 = "CH",A48 = "NO",A48 = "DK",A48 = "FI"), 1, 0) -> 0 | W48: =V48*H48 -> 0 | X48: =V48*J48 -> 0 | Y48: =IF(OR(A48 = "US",A48 = "CA",A48 = "UK",A48 = "NZ",A48 = "AU",A48 = "SG"), 1, 0) -> 1 | Z48: =VLOOKUP(R48,CPI!$A$2:$F$71,6,0) -> 1.2827779 | AA48: =T48*Z48 -> 5926.4337 | AB48: =U48*Z48 -> 759.79919 | AC48: Media | AD48: https://urbantoronto.ca/news/2020/03/metrolinxs-preliminary-business-case-scarborough-subway-extension-raises-questions
A49: CA | B49: Toronto | C49: YUS/YNSE | D49: Yonge to Richmond Hill | E49: 2020 | F49: 2030 | G49: 0 | H49: 7.4 | I49: 1 | J49: 7.4 | K49: 0 | L49: 0 | M49: 6 | O49: Plan | P49: 5600 | Q49: CAD | R49: 2020 | S49: 0.84 | T49: =P49*S49 -> 4704 | U49: =T49/H49 -> 635.67568 | V49: =IF(OR(A49 = "BG",A49 = "GR",A49 = "IT",A49 = "ES",A49 = "PT",A49 = "TR", A49 = "KR",A49 = "SE",A49 = "CH",A49 = "NO",A49 = "DK",A49 = "FI"), 1, 0) -> 0 | W49: =V49*H49 -> 0 | X49: =V49*J49 -> 0 | Y49: =IF(OR(A49 = "US",A49 = "CA",A49 = "UK",A49 = "NZ",A49 = "AU",A49 = "SG"), 1, 0) -> 1 | Z49: =VLOOKUP(R49,CPI!$A$2:$F$71,6,0) -> 1.2445935 | AA49: =T49*Z49 -> 5854.568 | AB49: =U49*Z49 -> 791.15784 | AC49: Media | AD49: https://www.thestar.com/news/gta/2020/06/24/metrolinx-considering-a-route-for-the-yonge-subway-extension-to-richmond-hill-that-would-take-it-above-ground.html
A50: CA | B50: Toronto | C50: Eglinton Crosstown | D50: Phase 1 West | E50: 2022 | F50: 2031 | G50: 0 | H50: 9.2 | I50: =6.8/9.2 -> 0.73913043 | J50: 6.8 | K50: 1.5 | L50: 0.9 | M50: 7 | N50: 50 | O50: Plan | P50: 2500 | Q50: CAD | R50: 2022 | S50: 0.84 | T50: =P50*S50 -> 2100 | U50: =T50/H50 -> 228.26087 | Z50: =VLOOKUP(R50,CPI!$A$2:$F$71,6,0) -> 1.1006629 | AA50: =T50*Z50 -> 2311.3921 | AB50: =U50*Z50 -> 251.23827 | AC50: Media | AD50: https://www.infrastructureontario.ca/en/what-we-do/projectssearch/eglinton-crosstown-west-extension/ https://www.metrolinx.com/en/projects-and-programs/eglinton-crosstown-west-extension
A51: CA | B51: Toronto | C51: Ontario Line | D51: Ontario | E51: 2022 | F51: 2031 | G51: 0 | H51: 15.5 | I51: 0.57 | J51: 8.8 | K51: 5.76 | L51: 1.06 | M51: 15 | O51: Plan | P51: 27200 | Q51: CAD | R51: 2023 | S51: 0.84 | T51: =P51*S51 -> 22848 | U51: =T51/H51 -> 1474.0645 | V51: =IF(OR(A51 = "BG",A51 = "GR",A51 = "IT",A51 = "ES",A51 = "PT",A51 = "TR", A51 = "KR",A51 = "SE",A51 = "CH",A51 = "NO",A51 = "DK",A51 = "FI"), 1, 0) -> 0 | W51: =V51*H51 -> 0 | X51: =V51*J51 -> 0 | Y51: =IF(OR(A51 = "US",A51 = "CA",A51 = "UK",A51 = "NZ",A51 = "AU",A51 = "SG"), 1, 0) -> 1 | Z51: =VLOOKUP(R51,CPI!$A$2:$F$71,6,0) -> 1.057146 | AA51: =T51*Z51 -> 24153.672 | AB51: =U51*Z51 -> 1558.3014 | AC51: Plan | AD51: https://globalnews.ca/news/10579363/ontario-line-cost-increase/
A52: CA | B52: Vancouver | C52: Millennium Line | D52: Millennium Line Phase 1 | E52: 1998 | F52: 2002 | G52: 0 | H52: 19.9 | I52: 0 | J52: 0 | K52: 0 | L52: 0 | M52: 13 | O52: Wiki | P52: 1200 | Q52: CAD | R52: 2000 | S52: 0.81 | T52: =P52*S52 -> 972 | U52: =T52/H52 -> 48.844221 | V52: =IF(OR(A52 = "BG",A52 = "GR",A52 = "IT",A52 = "ES",A52 = "PT",A52 = "TR", A52 = "KR",A52 = "SE",A52 = "CH",A52 = "NO",A52 = "DK",A52 = "FI"), 1, 0) -> 0 | W52: =V52*H52 -> 0 | X52: =V52*J52 -> 0 | Y52: =IF(OR(A52 = "US",A52 = "CA",A52 = "UK",A52 = "NZ",A52 = "AU",A52 = "SG"), 1, 0) -> 1 | Z52: =VLOOKUP(R52,CPI!$A$2:$F$71,6,0) -> 1.8705836 | AA52: =T52*Z52 -> 1818.2073 | AB52: =U52*Z52 -> 91.3672 | AC52: Plan | AD52: https://web.archive.org/web/20181110080355/https://www.translink.ca/-/media/Documents/about_translink/corporate_overview/corporate_reports/history/translink_history_nov_2008.pdf
A53: CA | B53: Vancouver | C53: Canada Line | D53: Canada Line | E53: 2005 | F53: 2009 | G53: 0 | H53: 18.4 | I53: 0.49 | J53: 9.1 | K53: 0 | L53: 0 | M53: 16 | O53: Wiki | P53: 2050 | Q53: CAD | R53: 2007 | S53: 0.82 | T53: =P53*S53 -> 1681 | U53: =T53/H53 -> 91.358696 | V53: =IF(OR(A53 = "BG",A53 = "GR",A53 = "IT",A53 = "ES",A53 = "PT",A53 = "TR", A53 = "KR",A53 = "SE",A53 = "CH",A53 = "NO",A53 = "DK",A53 = "FI"), 1, 0) -> 0 | W53: =V53*H53 -> 0 | X53: =V53*J53 -> 0 | Y53: =IF(OR(A53 = "US",A53 = "CA",A53 = "UK",A53 = "NZ",A53 = "AU",A53 = "SG"), 1, 0) -> 1 | Z53: =VLOOKUP(R53,CPI!$A$2:$F$71,6,0) -> 1.553542 | AA53: =T53*Z53 -> 2611.5041 | AB53: =U53*Z53 -> 141.92957 | AC53: Media | AD53: https://vancouversun.com/news/local-news/by-the-numbers-canada-line-turns-10
A54: CA | B54: Vancouver | C54: Evergreen Line | D54: Evergreen Line | E54: 2012 | F54: 2016 | G54: 0 | H54: 10.9 | I54: 0.18 | J54: 2 | K54: 0 | L54: 0 | M54: 6 | O54: Wiki | P54: 1430 | Q54: CAD | R54: 2014 | S54: 0.81 | T54: =P54*S54 -> 1158.3 | U54: =T54/H54 -> 106.26605 | V54: =IF(OR(A54 = "BG",A54 = "GR",A54 = "IT",A54 = "ES",A54 = "PT",A54 = "TR", A54 = "KR",A54 = "SE",A54 = "CH",A54 = "NO",A54 = "DK",A54 = "FI"), 1, 0) -> 0 | W54: =V54*H54 -> 0 | X54: =V54*J54 -> 0 | Y54: =IF(OR(A54 = "US",A54 = "CA",A54 = "UK",A54 = "NZ",A54 = "AU",A54 = "SG"), 1, 0) -> 1 | Z54: =VLOOKUP(R54,CPI!$A$2:$F$71,6,0) -> 1.3606486 | AA54: =T54*Z54 -> 1576.0392 | AB54: =U54*Z54 -> 144.59076 | AC54: Media | AD54: https://thebreaker.news/news/evergreen-line-costs/
A55: CA | B55: Vancouver | C55: Millennium | D55: Broadway | E55: 2020 | F55: 2027 | G55: 0 | H55: 5.7 | I55: =5/5.7 -> 0.87719298 | J55: 5 | K55: 0.295 | L55: 0.446 | M55: 6 | O55: Plan | P55: 2954 | Q55: CAD | R55: 2018 | S55: 0.84 | T55: =P55*S55 -> 2481.36 | U55: =T55/H55 -> 435.32632 | V55: =IF(OR(A55 = "BG",A55 = "GR",A55 = "IT",A55 = "ES",A55 = "PT",A55 = "TR", A55 = "KR",A55 = "SE",A55 = "CH",A55 = "NO",A55 = "DK",A55 = "FI"), 1, 0) -> 0 | W55: =V55*H55 -> 0 | X55: =V55*J55 -> 0 | Y55: =IF(OR(A55 = "US",A55 = "CA",A55 = "UK",A55 = "NZ",A55 = "AU",A55 = "SG"), 1, 0) -> 1 | Z55: =VLOOKUP(R55,CPI!$A$2:$F$71,6,0) -> 1.2827779 | AA55: =T55*Z55 -> 3183.0337 | AB55: =U55*Z55 -> 558.42696 | AC55: Media | AD55: https://www.translink.ca/Plans-and-Projects/Rapid-Transit-Projects/Broadway-Subway-Project.aspx https://www2.gov.bc.ca/assets/gov/british-columbians-our-governments/government-finances/quarterly-reports/fall-2024-economic-fiscal-update.pdf
A56: CA | B56: Vancouver | C56: Surrey Langley SkyTrain | D56: Planning | E56: 2024 | F56: 2029 | G56: 0 | H56: 16 | I56: 0 | J56: 0 | K56: 1 | L56: 0 | M56: 8 | N56: 80 | O56: Plan | P56: 5996 | Q56: CAD | R56: 2024 | S56: 1 | T56: =P56*S56 -> 5996 | U56: =T56/H56 -> 374.75 | V56: 0 | Y56: 1 | Z56: =VLOOKUP(R56,CPI!$A$2:$F$71,6,0) -> 1 | AA56: =T56*Z56 -> 5996 | AB56: =U56*Z56 -> 374.75 | AC56: Media | AD56: https://globalnews.ca/news/10701039/surrey-langley-skytrain-cost/ https://surreylangleyskytrain.gov.bc.ca/app/uploads/sites/938/2024/12/SLS_Monthly_Status_Report_August_2024.pdf
A57: CA | B57: Vancouver | C57: Expo Line | D57: Expo Line Surrey-Langley extension | E57: 2022 | G57: 0 | H57: 16 | I57: 0 | J57: 0 | M57: 8 | P57: 3940 | Q57: CAD | R57: 2021 | S57: 0.798 | T57: =P57*S57 -> 3144.12 | U57: =T57/H57 -> 196.5075 | V57: =IF(OR(A57 = "BG",A57 = "GR",A57 = "IT",A57 = "ES",A57 = "PT",A57 = "TR", A57 = "KR",A57 = "SE",A57 = "CH",A57 = "NO",A57 = "DK",A57 = "FI"), 1, 0) -> 0 | W57: =V57*H57 -> 0 | X57: =V57*J57 -> 0 | Y57: =IF(OR(A57 = "US",A57 = "CA",A57 = "UK",A57 = "NZ",A57 = "AU",A57 = "SG"), 1, 0) -> 1 | Z57: =VLOOKUP(R57,CPI!$A$2:$F$71,6,0) -> 1.188746 | AA57: =T57*Z57 -> 3737.56 | AB57: =U57*Z57 -> 233.5975 | AC57: Media | AD57: https://globalnews.ca/news/8016045/justin-trudeau-federal-funding-skytrain-surrey-langley/ | AE57: https://bc.ctvnews.ca/federal-government-providing-up-to-1-3-billion-for-surrey-langley-skytrain-extension-1.5502944
A58: CH | B58: Geneva | C58: CEVA | D58: CEVA | E58: 2013 | F58: 2019 | G58: 1 | H58: 8.8 | I58: 0.96 | J58: 8.4 | K58: 0.14 | L58: 0.212 | M58: 4 | O58: Measured | P58: 1567 | Q58: CHF | R58: 2016 | S58: 0.68 | T58: =P58*S58 -> 1065.56 | U58: =T58/H58 -> 121.08636 | V58: =IF(OR(A58 = "BG",A58 = "GR",A58 = "IT",A58 = "ES",A58 = "PT",A58 = "TR", A58 = "KR",A58 = "SE",A58 = "CH",A58 = "NO",A58 = "DK",A58 = "FI"), 1, 0) -> 1 | W58: =V58*H58 -> 8.8 | X58: =V58*J58 -> 8.4 | Y58: =IF(OR(A58 = "US",A58 = "CA",A58 = "UK",A58 = "NZ",A58 = "AU",A58 = "SG"), 1, 0) -> 0 | Z58: =VLOOKUP(R58,CPI!$A$2:$F$71,6,0) -> 1.3421046 | AA58: =T58*Z58 -> 1430.093 | AB58: =U58*Z58 -> 162.51057 | AC58: Plan | AD58: https://www.ceva.ch/2017/05/11/financement-et-organisation/?b=https://www.ceva.ch/category/projet
A59: CH | B59: Lausanne | C59: Line 2 | D59: Line 2 | E59: 2002 | F59: 2008 | G59: 0 | H59: 6 | J59: 4.5 | K59: 1.5 | L59: 0 | M59: 14 | N59: 30 | O59: Wiki | P59: 410 | Q59: CHF | R59: 2000 | S59: 0.65 | T59: =P59*S59 -> 266.5 | U59: =T59/H59 -> 44.416667 | V59: =IF(OR(A59 = "BG",A59 = "GR",A59 = "IT",A59 = "ES",A59 = "PT",A59 = "TR", A59 = "KR",A59 = "SE",A59 = "CH",A59 = "NO",A59 = "DK",A59 = "FI"), 1, 0) -> 1 | W59: =V59*H59 -> 6 | X59: =V59*J59 -> 4.5 | Y59: =IF(OR(A59 = "US",A59 = "CA",A59 = "UK",A59 = "NZ",A59 = "AU",A59 = "SG"), 1, 0) -> 0 | Z59: =VLOOKUP(R59,CPI!$A$2:$F$71,6,0) -> 1.8705836 | AA59: =T59*Z59 -> 498.51054 | AB59: =U59*Z59 -> 83.085089 | AC59: Plan | AD59: https://archive.wikiwix.com/cache/index2.php?url=http%3A%2F%2Fwww.publidoc.vd.ch%2FguestDownload%2Fdirect%2FTexte%2520adopt%25C3%25A9%2520par%2520CE.pdf%3Fpath%3D%2FCompany%2520Home%2FVD%2FCHANC%2FSIEL%2Fantilope%2Fobjet%2FCEGC%2FExpos%25C3%25A9%2520des%2520motifs%2F2002%2F05%2F174061_34_Texte%2520adopt%25C3%25A9%2520par%2520CE_20020604_234589.pdf%2Findex.html#federation=archive.wikiwix.com&tab=url
A60: CH | B60: Lucerne | C60: Zentralbahn | D60: Zentralbahn | E60: 2008 | F60: 2013 | G60: 1 | H60: 1.5 | I60: 0.9 | J60: 1.4 | K60: 0 | L60: 0 | M60: 1 | O60: Plan | P60: 220.2 | Q60: CHF | R60: 2010 | S60: 0.68 | T60: =P60*S60 -> 149.736 | U60: =T60/H60 -> 99.824 | V60: =IF(OR(A60 = "BG",A60 = "GR",A60 = "IT",A60 = "ES",A60 = "PT",A60 = "TR", A60 = "KR",A60 = "SE",A60 = "CH",A60 = "NO",A60 = "DK",A60 = "FI"), 1, 0) -> 1 | W60: =V60*H60 -> 1.5 | X60: =V60*J60 -> 1.4 | Y60: =IF(OR(A60 = "US",A60 = "CA",A60 = "UK",A60 = "NZ",A60 = "AU",A60 = "SG"), 1, 0) -> 0 | Z60: =VLOOKUP(R60,CPI!$A$2:$F$71,6,0) -> 1.47721 | AA60: =T60*Z60 -> 221.19151 | AB60: =U60*Z60 -> 147.46101 | AC60: Plan | AD60: https://www.luzernerzeitung.ch/zentralschweiz/luzern/seetalplatz-und-zentralbahn-60-millionen-guenstiger-als-budgetiert-ld.1150224
A61: CH | B61: Zurich | C61: Durchmesserlinie | D61: Durchmesserlinie | E61: 2007 | F61: 2014 | G61: 1 | H61: 9.6 | I61: 0.5 | J61: 4.8 | K61: 0.2 | L61: 4.6 | M61: 1 | O61: Trade | P61: 2030 | Q61: CHF | R61: 2010 | S61: 0.68 | T61: =P61*S61 -> 1380.4 | U61: =T61/H61 -> 143.79167 | V61: =IF(OR(A61 = "BG",A61 = "GR",A61 = "IT",A61 = "ES",A61 = "PT",A61 = "TR", A61 = "KR",A61 = "SE",A61 = "CH",A61 = "NO",A61 = "DK",A61 = "FI"), 1, 0) -> 1 | W61: =V61*H61 -> 9.6 | X61: =V61*J61 -> 4.8 | Y61: =IF(OR(A61 = "US",A61 = "CA",A61 = "UK",A61 = "NZ",A61 = "AU",A61 = "SG"), 1, 0) -> 0 | Z61: =VLOOKUP(R61,CPI!$A$2:$F$71,6,0) -> 1.47721 | AA61: =T61*Z61 -> 2039.1407 | AB61: =U61*Z61 -> 212.41049 | AC61: Trade | AD61: https://www.railwaygazette.com/infrastructure/cross-city-tunnel-opening-increases-capacity-in-zurich/39619.article
A62: CL | B62: Santiago | C62: Project 63 | D62: Project 63 | E62: 2013 | F62: 2019 | G62: 0 | H62: 37 | I62: 1 | J62: 37 | K62: 0 | L62: 0 | M62: 28 | O62: Plan | P62: 3000 | Q62: USD | R62: 2016 | S62: 1.7 | T62: =P62*S62 -> 5100 | U62: =T62/H62 -> 137.83784 | V62: =IF(OR(A62 = "BG",A62 = "GR",A62 = "IT",A62 = "ES",A62 = "PT",A62 = "TR", A62 = "KR",A62 = "SE",A62 = "CH",A62 = "NO",A62 = "DK",A62 = "FI"), 1, 0) -> 0 | W62: =V62*H62 -> 0 | X62: =V62*J62 -> 0 | Y62: =IF(OR(A62 = "US",A62 = "CA",A62 = "UK",A62 = "NZ",A62 = "AU",A62 = "SG"), 1, 0) -> 0 | Z62: =VLOOKUP(R62,CPI!$A$2:$F$71,6,0) -> 1.3421046 | AA62: =T62*Z62 -> 6844.7335 | AB62: =U62*Z62 -> 184.9928 | AC62: Plan | AD62: https://www.metro.cl/files/documentos/metro-investor-201709.pdf
A63: CL | B63: Santiago | C63: Line 7 | D63: Line 7 | E63: 2021 | F63: 2026 | G63: 0 | H63: 24.8 | I63: 1 | J63: 24.8 | K63: 0 | L63: 0 | M63: 21 | O63: Plan | P63: 2900 | Q63: USD | R63: 2022 | S63: 1.7 | T63: =P63*S63 -> 4930 | U63: =T63/H63 -> 198.79032 | V63: =IF(OR(A63 = "BG",A63 = "GR",A63 = "IT",A63 = "ES",A63 = "PT",A63 = "TR", A63 = "KR",A63 = "SE",A63 = "CH",A63 = "NO",A63 = "DK",A63 = "FI"), 1, 0) -> 0 | W63: =V63*H63 -> 0 | X63: =V63*J63 -> 0 | Y63: =IF(OR(A63 = "US",A63 = "CA",A63 = "UK",A63 = "NZ",A63 = "AU",A63 = "SG"), 1, 0) -> 0 | Z63: =VLOOKUP(R63,CPI!$A$2:$F$71,6,0) -> 1.1006629 | AA63: =T63*Z63 -> 5426.2681 | AB63: =U63*Z63 -> 218.80113 | AC63: Trade | AD63: https://www.railwaygazette.com/projects-and-planning/santiago-tenders-line-7-construction/56621.article
A64: CN | B64: Beijing | C64: Line 13 | D64: Line 13 | E64: 1999 | F64: 2003 | G64: 0 | H64: 40.85 | I64: 0 | J64: 0 | K64: 13.855 | L64: 26.995 | M64: 17 | N64: 117 | O64: Wiki | P64: =6.57*10^3 -> 6570 | Q64: CNY | R64: 1999 | S64: 0.367 | T64: =P64*S64 -> 2411.19 | U64: =T64/H64 -> 59.025459 | V64: =IF(OR(A64 = "BG",A64 = "GR",A64 = "IT",A64 = "ES",A64 = "PT",A64 = "TR", A64 = "KR",A64 = "SE",A64 = "CH",A64 = "NO",A64 = "DK",A64 = "FI"), 1, 0) -> 0 | W64: =V64*H64 -> 0 | X64: =V64*J64 -> 0 | Y64: =IF(OR(A64 = "US",A64 = "CA",A64 = "UK",A64 = "NZ",A64 = "AU",A64 = "SG"), 1, 0) -> 0 | Z64: =VLOOKUP(R64,CPI!$A$2:$F$71,6,0) -> 1.9334604 | AA64: =T64*Z64 -> 4661.9403 | AB64: =U64*Z64 -> 114.12339 | AC64: Media | AD64: http://www.wikiwand.com/zh-sg/%E5%8C%97%E4%BA%AC%E5%9C%B0%E9%93%8113%E5%8F%B7%E7%BA%BF
A65: CN | B65: Beijing | C65: Line 5 | D65: Line 5 | E65: 2002 | F65: 2007 | G65: 0 | H65: 27.6 | K65: #N/A | L65: #N/A | M65: 23 | O65: Media | P65: 12000 | Q65: CNY | R65: 2004 | S65: 0.355 | T65: =S65*P65 -> 4260 | U65: =T65/H65 -> 154.34783 | V65: =IF(OR(A65 = "BG",A65 = "GR",A65 = "IT",A65 = "ES",A65 = "PT",A65 = "TR", A65 = "KR",A65 = "SE",A65 = "CH",A65 = "NO",A65 = "DK",A65 = "FI"), 1, 0) -> 0 | W65: =V65*H65 -> 0 | X65: =V65*J65 -> 0 | Y65: =IF(OR(A65 = "US",A65 = "CA",A65 = "UK",A65 = "NZ",A65 = "AU",A65 = "SG"), 1, 0) -> 0 | Z65: =VLOOKUP(R65,CPI!$A$2:$F$71,6,0) -> 1.7052118 | AA65: =T65*Z65 -> 7264.2021 | AB65: =U65*Z65 -> 263.19573 | AC65: Media | AD65: http://finance.sina.com.cn/b/20040419/0854725033.shtml
A66: CN | B66: Beijing | C66: Line 10 | D66: Line 10 North and East | E66: 2003 | F66: 2008 | G66: 0 | H66: 24.64 | I66: 1 | J66: 24.64 | K66: 0 | L66: 0 | M66: 22 | O66: Media | P66: 13700 | Q66: CNY | R66: 2005 | S66: 0.3519 | T66: =P66*S66 -> 4821.03 | U66: =T66/H66 -> 195.65869 | V66: =IF(OR(A66 = "BG",A66 = "GR",A66 = "IT",A66 = "ES",A66 = "PT",A66 = "TR", A66 = "KR",A66 = "SE",A66 = "CH",A66 = "NO",A66 = "DK",A66 = "FI"), 1, 0) -> 0 | W66: =V66*H66 -> 0 | X66: =V66*J66 -> 0 | Y66: =IF(OR(A66 = "US",A66 = "CA",A66 = "UK",A66 = "NZ",A66 = "AU",A66 = "SG"), 1, 0) -> 0 | Z66: =VLOOKUP(R66,CPI!$A$2:$F$71,6,0) -> 1.6493318 | AA66: =T66*Z66 -> 7951.4781 | AB66: =U66*Z66 -> 322.70609 | AC66: Media | AD66: http://news.sciencenet.cn/sbhtmlnews/2008/8/209799.html
A67: CN | B67: Beijing | C67: Capital Airport Express | D67: Capital Airport Express | E67: 2005 | F67: 2008 | G67: 0 | H67: 28.1 | I67: 0 | J67: 0 | K67: 17.315 | L67: 10.785 | M67: 4 | O67: Measured | P67: 622.3 | Q67: CNY | R67: 2005 | S67: 0.3519 | T67: =S67*P67 -> 218.98737 | U67: =T67/H67 -> 7.7931448 | V67: =IF(OR(A67 = "BG",A67 = "GR",A67 = "IT",A67 = "ES",A67 = "PT",A67 = "TR", A67 = "KR",A67 = "SE",A67 = "CH",A67 = "NO",A67 = "DK",A67 = "FI"), 1, 0) -> 0 | W67: =V67*H67 -> 0 | X67: =V67*J67 -> 0 | Y67: =IF(OR(A67 = "US",A67 = "CA",A67 = "UK",A67 = "NZ",A67 = "AU",A67 = "SG"), 1, 0) -> 0 | Z67: =VLOOKUP(R67,CPI!$A$2:$F$71,6,0) -> 1.6493318 | AA67: =T67*Z67 -> 361.18283 | AB67: =U67*Z67 -> 12.853482 | AC67: Media | AD67: http://news.sciencenet.cn/sbhtmlnews/2008/8/209799.html
A68: CN | B68: Beijing | C68: Line 8 | D68: Line 8 Phase 1 for Olympics | E68: 2005 | F68: 2008 | G68: 0 | H68: 4.528 | I68: 1 | J68: 4.528 | K68: 0 | L68: 0 | M68: 4 | O68: Media | P68: 2420 | Q68: CNY | R68: 2005 | S68: 0.3519 | T68: =S68*P68 -> 851.598 | U68: =T68/H68 -> 188.07376 | V68: =IF(OR(A68 = "BG",A68 = "GR",A68 = "IT",A68 = "ES",A68 = "PT",A68 = "TR", A68 = "KR",A68 = "SE",A68 = "CH",A68 = "NO",A68 = "DK",A68 = "FI"), 1, 0) -> 0 | W68: =V68*H68 -> 0 | X68: =V68*J68 -> 0 | Y68: =IF(OR(A68 = "US",A68 = "CA",A68 = "UK",A68 = "NZ",A68 = "AU",A68 = "SG"), 1, 0) -> 0 | Z68: =VLOOKUP(R68,CPI!$A$2:$F$71,6,0) -> 1.6493318 | AA68: =T68*Z68 -> 1404.5677 | AB68: =U68*Z68 -> 310.19604 | AC68: Media | AD68: https://www.360kuai.com/pc/9fb76b182add530db?cota=4&kuai_so=1&tj_url=so_rec&sign=360_7bc3b157; http://itdzs.org/OnLineMagazine/PDFView.aspx?ID=4
A69: CN | B69: Beijing | C69: Line 4 | D69: Line 4 | E69: 2004 | F69: 2009 | G69: 0 | H69: 28.2 | I69: =J69/H69 -> 0.95166667 | J69: 26.837 | K69: 0 | L69: 0 | M69: 24 | N69: 117 | O69: Media | P69: 15380 | Q69: CNY | R69: 2005 | S69: 0.3519 | T69: =P69*S69 -> 5412.222 | U69: =T69/H69 -> 191.92277 | V69: =IF(OR(A69 = "BG",A69 = "GR",A69 = "IT",A69 = "ES",A69 = "PT",A69 = "TR", A69 = "KR",A69 = "SE",A69 = "CH",A69 = "NO",A69 = "DK",A69 = "FI"), 1, 0) -> 0 | W69: =V69*H69 -> 0 | X69: =V69*J69 -> 0 | Y69: =IF(OR(A69 = "US",A69 = "CA",A69 = "UK",A69 = "NZ",A69 = "AU",A69 = "SG"), 1, 0) -> 0 | Z69: =VLOOKUP(R69,CPI!$A$2:$F$71,6,0) -> 1.6493318 | AA69: =T69*Z69 -> 8926.5498 | AB69: =U69*Z69 -> 316.54432 | AC69: Media | AD69: http://zizhan.mot.gov.cn/zhuantizhuanlan/qita/quanqiuhuanjingjijin/zhishigongxiang/201601/P020160125565596507649.pdf
A70: CN | B70: Beijing | C70: Daxing Line | D70: Daxing Line | E70: 2007 | F70: 2010 | G70: 0 | H70: 21.8 | I70: 0.80275229 | J70: 17.5 | K70: 4.36 | L70: 0 | M70: 11 | O70: Media | P70: 10930 | Q70: CNY | R70: 2007 | S70: 0.333 | T70: =S70*P70 -> 3639.69 | U70: =T70/H70 -> 166.95826 | V70: =IF(OR(A70 = "BG",A70 = "GR",A70 = "IT",A70 = "ES",A70 = "PT",A70 = "TR", A70 = "KR",A70 = "SE",A70 = "CH",A70 = "NO",A70 = "DK",A70 = "FI"), 1, 0) -> 0 | W70: =V70*H70 -> 0 | X70: =V70*J70 -> 0 | Y70: =IF(OR(A70 = "US",A70 = "CA",A70 = "UK",A70 = "NZ",A70 = "AU",A70 = "SG"), 1, 0) -> 0 | Z70: =VLOOKUP(R70,CPI!$A$2:$F$71,6,0) -> 1.553542 | AA70: =T70*Z70 -> 5654.4112 | AB70: =U70*Z70 -> 259.37666 | AC70: Media | AD70: http://www.mtr.bj.cn/article/5d510c0aebb1a36f5ef5981f.html
A71: CN | B71: Beijing | C71: Line 9 | D71: Line 9 | E71: 2007 | F71: 2012 | G71: 0 | H71: 16.5 | I71: 1 | J71: 16.5 | M71: 13 | N71: 117 | P71: 12900 | Q71: CNY | R71: 2010 | S71: 0.3 | T71: =P71*S71 -> 3870 | U71: =T71/H71 -> 234.54545 | V71: =IF(OR(A71 = "BG",A71 = "GR",A71 = "IT",A71 = "ES",A71 = "PT",A71 = "TR", A71 = "KR",A71 = "SE",A71 = "CH",A71 = "NO",A71 = "DK",A71 = "FI"), 1, 0) -> 0 | W71: =V71*H71 -> 0 | X71: =V71*J71 -> 0 | Y71: =IF(OR(A71 = "US",A71 = "CA",A71 = "UK",A71 = "NZ",A71 = "AU",A71 = "SG"), 1, 0) -> 0 | Z71: =VLOOKUP(R71,CPI!$A$2:$F$71,6,0) -> 1.47721 | AA71: =T71*Z71 -> 5716.8026 | AB71: =U71*Z71 -> 346.47289 | AD71: http://zqb.cyol.com/html/2012-12/31/nw.D110000zgqnb_20121231_3-06.htm
A72: CN | B72: Beijing | C72: Line 6 | D72: Line 6 Phase 1 | E72: 2008 | F72: 2012 | G72: 0 | H72: 30.4 | I72: 1 | J72: 30.4 | M72: 20 | N72: 156 | O72: Wiki | P72: 28000 | Q72: CNY | R72: 2010 | S72: 0.3 | T72: =P72*S72 -> 8400 | U72: =T72/H72 -> 276.31579 | V72: =IF(OR(A72 = "BG",A72 = "GR",A72 = "IT",A72 = "ES",A72 = "PT",A72 = "TR", A72 = "KR",A72 = "SE",A72 = "CH",A72 = "NO",A72 = "DK",A72 = "FI"), 1, 0) -> 0 | W72: =V72*H72 -> 0 | X72: =V72*J72 -> 0 | Y72: =IF(OR(A72 = "US",A72 = "CA",A72 = "UK",A72 = "NZ",A72 = "AU",A72 = "SG"), 1, 0) -> 0 | Z72: =VLOOKUP(R72,CPI!$A$2:$F$71,6,0) -> 1.47721 | AA72: =T72*Z72 -> 12408.564 | AB72: =U72*Z72 -> 408.17644 | AC72: Media | AD72: http://zqb.cyol.com/html/2012-12/31/nw.D110000zgqnb_20121231_3-06.htm
A73: CN | B73: Beijing | C73: Line 8 | D73: Line 8 Northern Extension | E73: 2011 | F73: 2013 | G73: 0 | H73: 6.328 | I73: 0.73451327 | J73: 4.648 | K73: 1.7091 | L73: 0 | M73: 3 | O73: Measured | P73: 3212.2 | Q73: CNY | R73: 2011 | S73: 0.284 | T73: =S73*P73 -> 912.2648 | U73: =T73/H73 -> 144.16321 | V73: =IF(OR(A73 = "BG",A73 = "GR",A73 = "IT",A73 = "ES",A73 = "PT",A73 = "TR", A73 = "KR",A73 = "SE",A73 = "CH",A73 = "NO",A73 = "DK",A73 = "FI"), 1, 0) -> 0 | W73: =V73*H73 -> 0 | X73: =V73*J73 -> 0 | Y73: =IF(OR(A73 = "US",A73 = "CA",A73 = "UK",A73 = "NZ",A73 = "AU",A73 = "SG"), 1, 0) -> 0 | Z73: =VLOOKUP(R73,CPI!$A$2:$F$71,6,0) -> 1.4320082 | AA73: =T73*Z73 -> 1306.3707 | AB73: =U73*Z73 -> 206.44291 | AC73: Media | AD73: https://max.book118.com/html/2017/1209/143431974.shtm
A74: CN | B74: Beijing | C74: Line 15 | D74: Line 15 Phase 1 | E74: 2009 | F74: 2014 | G74: 0 | H74: 41.4 | I74: 0.66908213 | J74: 27.7 | K74: 13.605 | L74: 0.471 | M74: 18 | N74: 117 | O74: Media | P74: 18100 | Q74: CNY | R74: 2010 | S74: 0.3 | T74: =S74*P74 -> 5430 | U74: =T74/H74 -> 131.15942 | V74: =IF(OR(A74 = "BG",A74 = "GR",A74 = "IT",A74 = "ES",A74 = "PT",A74 = "TR", A74 = "KR",A74 = "SE",A74 = "CH",A74 = "NO",A74 = "DK",A74 = "FI"), 1, 0) -> 0 | W74: =V74*H74 -> 0 | X74: =V74*J74 -> 0 | Y74: =IF(OR(A74 = "US",A74 = "CA",A74 = "UK",A74 = "NZ",A74 = "AU",A74 = "SG"), 1, 0) -> 0 | Z74: =VLOOKUP(R74,CPI!$A$2:$F$71,6,0) -> 1.47721 | AA74: =T74*Z74 -> 8021.2502 | AB74: =U74*Z74 -> 193.75 | AC74: Media | AD74: http://finance.ifeng.com/city/bj/20101117/2902241.shtml
A75: CN | B75: Beijing | C75: Line 7 | D75: Line 7 Phase 1 | E75: 2009 | F75: 2014 | G75: 0 | H75: 23.7 | I75: 1 | J75: 23.7 | K75: 0 | L75: 0 | M75: 21 | O75: Plan | P75: 16000 | Q75: CNY | R75: 2014 | S75: 0.266 | T75: =P75*S75 -> 4256 | U75: =T75/H75 -> 179.57806 | V75: =IF(OR(A75 = "BG",A75 = "GR",A75 = "IT",A75 = "ES",A75 = "PT",A75 = "TR", A75 = "KR",A75 = "SE",A75 = "CH",A75 = "NO",A75 = "DK",A75 = "FI"), 1, 0) -> 0 | W75: =V75*H75 -> 0 | X75: =V75*J75 -> 0 | Y75: =IF(OR(A75 = "US",A75 = "CA",A75 = "UK",A75 = "NZ",A75 = "AU",A75 = "SG"), 1, 0) -> 0 | Z75: =VLOOKUP(R75,CPI!$A$2:$F$71,6,0) -> 1.3606486 | AA75: =T75*Z75 -> 5790.9203 | AB75: =U75*Z75 -> 244.34263 | AC75: Media | AD75: http://bj.bendibao.com/news/20141120/171344.shtm
A76: CN | B76: Beijing | C76: Line 6 | D76: Line 6 Phase 2 | E76: 2011 | F76: 2014 | G76: 0 | H76: 12.4 | I76: 1 | J76: 12.4 | M76: 8 | N76: 156 | P76: 6000 | Q76: CNY | R76: 2013 | S76: 0.273 | T76: =P76*S76 -> 1638 | U76: =T76/H76 -> 132.09677 | V76: =IF(OR(A76 = "BG",A76 = "GR",A76 = "IT",A76 = "ES",A76 = "PT",A76 = "TR", A76 = "KR",A76 = "SE",A76 = "CH",A76 = "NO",A76 = "DK",A76 = "FI"), 1, 0) -> 0 | W76: =V76*H76 -> 0 | X76: =V76*J76 -> 0 | Y76: =IF(OR(A76 = "US",A76 = "CA",A76 = "UK",A76 = "NZ",A76 = "AU",A76 = "SG"), 1, 0) -> 0 | Z76: =VLOOKUP(R76,CPI!$A$2:$F$71,6,0) -> 1.3827208 | AA76: =T76*Z76 -> 2264.8967 | AB76: =U76*Z76 -> 182.65296 | AD76: http://politics.people.com.cn/n/2014/1105/c70731-25980932.html
A77: CN | B77: Beijing | C77: Line 8 | D77: Line 8 Phase 4 | E77: 2016 | F77: 2018 | G77: 0 | H77: 3.4 | I77: =J77/H77 -> 0.29076471 | J77: 0.9886 | K77: 2.414 | L77: 0 | M77: 2 | O77: Wiki | P77: 3420 | Q77: CNY | R77: 2015 | S77: 0.258 | T77: =P77*S77 -> 882.36 | U77: =T77/H77 -> 259.51765 | V77: =IF(OR(A77 = "BG",A77 = "GR",A77 = "IT",A77 = "ES",A77 = "PT",A77 = "TR", A77 = "KR",A77 = "SE",A77 = "CH",A77 = "NO",A77 = "DK",A77 = "FI"), 1, 0) -> 0 | W77: =V77*H77 -> 0 | X77: =V77*J77 -> 0 | Y77: =IF(OR(A77 = "US",A77 = "CA",A77 = "UK",A77 = "NZ",A77 = "AU",A77 = "SG"), 1, 0) -> 0 | Z77: =VLOOKUP(R77,CPI!$A$2:$F$71,6,0) -> 1.3590354 | AA77: =T77*Z77 -> 1199.1585 | AB77: =U77*Z77 -> 352.69368 | AC77: Media | AD77: https://zh.wikipedia.org/wiki/%E5%8C%97%E4%BA%AC%E5%9C%B0%E9%93%818%E5%8F%B7%E7%BA%BF#%E4%B8%89%E6%9C%9F%E5%8F%8A%E5%9B%9B%E6%9C%9F%E5%B7%A5%E7%A8%8B
A78: CN | B78: Beijing | C78: Daxing Airport Express | D78: Daxing Airport Express Phase 1 | E78: 2016 | F78: 2019 | G78: 0 | H78: 44 | K78: #N/A | L78: #N/A | M78: 3 | O78: Plan | P78: 27820 | Q78: CNY | R78: 2019 | S78: 0.238 | T78: =S78*P78 -> 6621.16 | U78: =T78/H78 -> 150.48091 | V78: =IF(OR(A78 = "BG",A78 = "GR",A78 = "IT",A78 = "ES",A78 = "PT",A78 = "TR", A78 = "KR",A78 = "SE",A78 = "CH",A78 = "NO",A78 = "DK",A78 = "FI"), 1, 0) -> 0 | W78: =V78*H78 -> 0 | X78: =V78*J78 -> 0 | Y78: =IF(OR(A78 = "US",A78 = "CA",A78 = "UK",A78 = "NZ",A78 = "AU",A78 = "SG"), 1, 0) -> 0 | Z78: =VLOOKUP(R78,CPI!$A$2:$F$71,6,0) -> 1.2599479 | AA78: =T78*Z78 -> 8342.3166 | AB78: =U78*Z78 -> 189.59811 | AC78: Plan | AD78: http://www.tzxm.gov.cn/flfg/law/201912/t20191220_12825.html
A79: CN | B79: Beijing | C79: Capital Airport Express | D79: Capital Airport Express west extenion | E79: 2016 | F79: 2020 | G79: 0 | H79: 1.83 | I79: 1 | J79: 1.83 | M79: 1 | N79: 68 | P79: 1800 | Q79: CNY | R79: 2018 | S79: 0.237 | T79: =P79*S79 -> 426.6 | U79: =T79/H79 -> 233.11475 | V79: =IF(OR(A79 = "BG",A79 = "GR",A79 = "IT",A79 = "ES",A79 = "PT",A79 = "TR", A79 = "KR",A79 = "SE",A79 = "CH",A79 = "NO",A79 = "DK",A79 = "FI"), 1, 0) -> 0 | W79: =V79*H79 -> 0 | X79: =V79*J79 -> 0 | Y79: =IF(OR(A79 = "US",A79 = "CA",A79 = "UK",A79 = "NZ",A79 = "AU",A79 = "SG"), 1, 0) -> 0 | Z79: =VLOOKUP(R79,CPI!$A$2:$F$71,6,0) -> 1.2827779 | AA79: =T79*Z79 -> 547.23303 | AB79: =U79*Z79 -> 299.03445 | AC79: Media | AD79: https://new.qq.com/omn/20210301/20210301A0E4JW00.html
A80: CN | B80: Beijing | C80: Line 7 | D80: Line 7 Phase 2 (Eastern Extension) | E80: 2016 | F80: 2020 | G80: 0 | H80: 17.2 | I80: 0.87209302 | J80: 15 | K80: 0 | L80: 0 | M80: 9 | O80: Plan | P80: 15330 | Q80: CNY | R80: 2016 | S80: 0.251 | T80: =P80*S80 -> 3847.83 | U80: =T80/H80 -> 223.71105 | V80: =IF(OR(A80 = "BG",A80 = "GR",A80 = "IT",A80 = "ES",A80 = "PT",A80 = "TR", A80 = "KR",A80 = "SE",A80 = "CH",A80 = "NO",A80 = "DK",A80 = "FI"), 1, 0) -> 0 | W80: =V80*H80 -> 0 | X80: =V80*J80 -> 0 | Y80: =IF(OR(A80 = "US",A80 = "CA",A80 = "UK",A80 = "NZ",A80 = "AU",A80 = "SG"), 1, 0) -> 0 | Z80: =VLOOKUP(R80,CPI!$A$2:$F$71,6,0) -> 1.3421046 | AA80: =T80*Z80 -> 5164.1904 | AB80: =U80*Z80 -> 300.24363 | AC80: Media | AD80: https://zh.wikisource.org/zh-hans/%E5%8C%97%E4%BA%AC%E5%B8%82%E5%9F%8E%E5%B8%82%E8%BD%A8%E9%81%93%E4%BA%A4%E9%80%9A%E7%AC%AC%E4%BA%8C%E6%9C%9F%E5%BB%BA%E8%AE%BE%E8%A7%84%E5%88%92%EF%BC%882015%EF%BD%9E2021%E5%B9%B4%EF%BC%89
A81: CN | B81: Beijing | C81: Line 25 | D81: Line 25 Phase 2 (Fangshan Northern Extension) | E81: 2017 | F81: 2020 | G81: 0 | H81: 5 | K81: #N/A | L81: #N/A | M81: 4 | O81: Plan | P81: 4860 | Q81: CNY | R81: 2015 | S81: 0.258 | T81: =P81*S81 -> 1253.88 | U81: =T81/H81 -> 250.776 | V81: =IF(OR(A81 = "BG",A81 = "GR",A81 = "IT",A81 = "ES",A81 = "PT",A81 = "TR", A81 = "KR",A81 = "SE",A81 = "CH",A81 = "NO",A81 = "DK",A81 = "FI"), 1, 0) -> 0 | W81: =V81*H81 -> 0 | X81: =V81*J81 -> 0 | Y81: =IF(OR(A81 = "US",A81 = "CA",A81 = "UK",A81 = "NZ",A81 = "AU",A81 = "SG"), 1, 0) -> 0 | Z81: =VLOOKUP(R81,CPI!$A$2:$F$71,6,0) -> 1.3590354 | AA81: =T81*Z81 -> 1704.0673 | AB81: =U81*Z81 -> 340.81347 | AC81: Media | AD81: https://zh.wikisource.org/zh-hans/%E5%8C%97%E4%BA%AC%E5%B8%82%E5%9F%8E%E5%B8%82%E8%BD%A8%E9%81%93%E4%BA%A4%E9%80%9A%E7%AC%AC%E4%BA%8C%E6%9C%9F%E5%BB%BA%E8%AE%BE%E8%A7%84%E5%88%92%EF%BC%882015%EF%BD%9E2021%E5%B9%B4%EF%BC%89
A82: CN | B82: Beijing | C82: Line 16 | D82: Line 16 | E82: 2013 | F82: 2021 | G82: 0 | H82: 49.8 | I82: 1 | J82: 49.8 | K82: 0 | L82: 0 | M82: 29 | O82: Media | P82: 49500 | Q82: CNY | R82: 2013 | S82: 0.273 | T82: =P82*S82 -> 13513.5 | U82: =T82/H82 -> 271.35542 | V82: =IF(OR(A82 = "BG",A82 = "GR",A82 = "IT",A82 = "ES",A82 = "PT",A82 = "TR", A82 = "KR",A82 = "SE",A82 = "CH",A82 = "NO",A82 = "DK",A82 = "FI"), 1, 0) -> 0 | W82: =V82*H82 -> 0 | X82: =V82*J82 -> 0 | Y82: =IF(OR(A82 = "US",A82 = "CA",A82 = "UK",A82 = "NZ",A82 = "AU",A82 = "SG"), 1, 0) -> 0 | Z82: =VLOOKUP(R82,CPI!$A$2:$F$71,6,0) -> 1.3827208 | AA82: =T82*Z82 -> 18685.398 | AB82: =U82*Z82 -> 375.2088 | AC82: Media | AD82: http://www.bjnews.com.cn/news/2016/11/25/424943.html; https://baijiahao.baidu.com/s?id=1633332748114018963&wfr=spider&for=pc
A83: CN | B83: Beijing | C83: Line 3 | D83: Line 3 Phase 1+2 | E83: 2016 | F83: 2021 | G83: 0 | H83: 37.4 | I83: 0.55614973 | J83: 20.8 | K83: 0 | L83: 0 | M83: 27 | O83: Plan | P83: 41500 | Q83: CNY | R83: 2015 | S83: 0.258 | T83: =P83*S83 -> 10707 | U83: =T83/H83 -> 286.28342 | V83: =IF(OR(A83 = "BG",A83 = "GR",A83 = "IT",A83 = "ES",A83 = "PT",A83 = "TR", A83 = "KR",A83 = "SE",A83 = "CH",A83 = "NO",A83 = "DK",A83 = "FI"), 1, 0) -> 0 | W83: =V83*H83 -> 0 | X83: =V83*J83 -> 0 | Y83: =IF(OR(A83 = "US",A83 = "CA",A83 = "UK",A83 = "NZ",A83 = "AU",A83 = "SG"), 1, 0) -> 0 | Z83: =VLOOKUP(R83,CPI!$A$2:$F$71,6,0) -> 1.3590354 | AA83: =T83*Z83 -> 14551.192 | AB83: =U83*Z83 -> 389.06931 | AC83: Plan | AD83: http://www.gov.cn/xinwen/2018-02/18/content_5267552.htm; https://zh.m.wikisource.org/zh-hans/%E5%8C%97%E4%BA%AC%E5%B8%82%E5%9F%8E%E5%B8%82%E8%BD%A8%E9%81%93%E4%BA%A4%E9%80%9A%E7%AC%AC%E4%BA%8C%E6%9C%9F%E5%BB%BA%E8%AE%BE%E8%A7%84%E5%88%92%EF%BC%882015%EF%BD%9E2021%E5%B9%B4%EF%BC%89
A84: CN | B84: Beijing | C84: Line 12 | D84: Line 12 | E84: 2017 | F84: 2021 | G84: 0 | H84: 29.2 | I84: 1 | J84: 29.2 | K84: 0 | L84: 0 | M84: 21 | O84: Plan | P84: 32400 | Q84: CNY | R84: 2015 | S84: 0.258 | T84: =P84*S84 -> 8359.2 | U84: =T84/H84 -> 286.27397 | V84: =IF(OR(A84 = "BG",A84 = "GR",A84 = "IT",A84 = "ES",A84 = "PT",A84 = "TR", A84 = "KR",A84 = "SE",A84 = "CH",A84 = "NO",A84 = "DK",A84 = "FI"), 1, 0) -> 0 | W84: =V84*H84 -> 0 | X84: =V84*J84 -> 0 | Y84: =IF(OR(A84 = "US",A84 = "CA",A84 = "UK",A84 = "NZ",A84 = "AU",A84 = "SG"), 1, 0) -> 0 | Z84: =VLOOKUP(R84,CPI!$A$2:$F$71,6,0) -> 1.3590354 | AA84: =T84*Z84 -> 11360.449 | AB84: =U84*Z84 -> 389.05647 | AC84: Media | AD84: https://zh.wikisource.org/zh-hans/%E5%8C%97%E4%BA%AC%E5%B8%82%E5%9F%8E%E5%B8%82%E8%BD%A8%E9%81%93%E4%BA%A4%E9%80%9A%E7%AC%AC%E4%BA%8C%E6%9C%9F%E5%BB%BA%E8%AE%BE%E8%A7%84%E5%88%92%EF%BC%882015%EF%BD%9E2021%E5%B9%B4%EF%BC%89
A85: CN | B85: Beijing | C85: Line 19 | D85: Line 19 Phase 1 | E85: 2017 | F85: 2021 | G85: 0 | H85: 22.4 | I85: 1 | J85: 22.4 | K85: 0 | L85: 0 | M85: 10 | O85: Plan | P85: 22180 | Q85: CNY | R85: 2015 | S85: 0.258 | T85: =P85*S85 -> 5722.44 | U85: =T85/H85 -> 255.46607 | V85: =IF(OR(A85 = "BG",A85 = "GR",A85 = "IT",A85 = "ES",A85 = "PT",A85 = "TR", A85 = "KR",A85 = "SE",A85 = "CH",A85 = "NO",A85 = "DK",A85 = "FI"), 1, 0) -> 0 | W85: =V85*H85 -> 0 | X85: =V85*J85 -> 0 | Y85: =IF(OR(A85 = "US",A85 = "CA",A85 = "UK",A85 = "NZ",A85 = "AU",A85 = "SG"), 1, 0) -> 0 | Z85: =VLOOKUP(R85,CPI!$A$2:$F$71,6,0) -> 1.3590354 | AA85: =T85*Z85 -> 7776.9987 | AB85: =U85*Z85 -> 347.18744 | AC85: Media | AD85: https://zh.wikisource.org/zh-hans/%E5%8C%97%E4%BA%AC%E5%B8%82%E5%9F%8E%E5%B8%82%E8%BD%A8%E9%81%93%E4%BA%A4%E9%80%9A%E7%AC%AC%E4%BA%8C%E6%9C%9F%E5%BB%BA%E8%AE%BE%E8%A7%84%E5%88%92%EF%BC%882015%EF%BD%9E2021%E5%B9%B4%EF%BC%89
A86: CN | B86: Beijing | C86: Line 28 | D86: Line 28 | E86: 2017 | F86: 2021 | G86: 0 | H86: 8.777 | I86: 1 | J86: 8.777 | K86: 0 | L86: 0 | M86: 9 | O86: Media | P86: =12.75*1000 -> 12750 | Q86: CNY | R86: 2019 | S86: 0.238 | T86: =P86*S86 -> 3034.5 | U86: =T86/H86 -> 345.73317 | V86: =IF(OR(A86 = "BG",A86 = "GR",A86 = "IT",A86 = "ES",A86 = "PT",A86 = "TR", A86 = "KR",A86 = "SE",A86 = "CH",A86 = "NO",A86 = "DK",A86 = "FI"), 1, 0) -> 0 | W86: =V86*H86 -> 0 | X86: =V86*J86 -> 0 | Y86: =IF(OR(A86 = "US",A86 = "CA",A86 = "UK",A86 = "NZ",A86 = "AU",A86 = "SG"), 1, 0) -> 0 | Z86: =VLOOKUP(R86,CPI!$A$2:$F$71,6,0) -> 1.2599479 | AA86: =T86*Z86 -> 3823.3119 | AB86: =U86*Z86 -> 435.60578 | AC86: Media | AD86: http://www.tzxm.gov.cn/flfg/law/201912/t20191220_12825.html; https://new.qq.com/rain/a/20200812A0UGAJ00
A87: CN | B87: Beijing | C87: Line 11 | D87: Line 11 West | E87: 2019 | F87: 2021 | G87: 0 | H87: 4.2 | I87: 1 | J87: 4.2 | M87: 4 | N87: 138 | P87: 5715 | Q87: CNY | R87: 2020 | S87: 0.239 | T87: =P87*S87 -> 1365.885 | U87: =T87/H87 -> 325.21071 | V87: =IF(OR(A87 = "BG",A87 = "GR",A87 = "IT",A87 = "ES",A87 = "PT",A87 = "TR", A87 = "KR",A87 = "SE",A87 = "CH",A87 = "NO",A87 = "DK",A87 = "FI"), 1, 0) -> 0 | W87: =V87*H87 -> 0 | X87: =V87*J87 -> 0 | Y87: =IF(OR(A87 = "US",A87 = "CA",A87 = "UK",A87 = "NZ",A87 = "AU",A87 = "SG"), 1, 0) -> 0 | Z87: =VLOOKUP(R87,CPI!$A$2:$F$71,6,0) -> 1.2445935 | AA87: =T87*Z87 -> 1699.9717 | AB87: =U87*Z87 -> 404.75516 | AC87: Trade | AD87: http://www.rail-transit.com/project/show.php?itemid=360
A88: CN | B88: Beijing | C88: Line 27 | D88: Line 27 Phase 2 (Changping Southern Extension) | E88: 2019 | F88: 2021 | G88: 0 | H88: 16.6 | K88: #N/A | L88: #N/A | M88: 8 | O88: Plan | P88: 14230 | Q88: CNY | R88: 2015 | S88: 0.258 | T88: =P88*S88 -> 3671.34 | U88: =T88/H88 -> 221.16506 | V88: =IF(OR(A88 = "BG",A88 = "GR",A88 = "IT",A88 = "ES",A88 = "PT",A88 = "TR", A88 = "KR",A88 = "SE",A88 = "CH",A88 = "NO",A88 = "DK",A88 = "FI"), 1, 0) -> 0 | W88: =V88*H88 -> 0 | X88: =V88*J88 -> 0 | Y88: =IF(OR(A88 = "US",A88 = "CA",A88 = "UK",A88 = "NZ",A88 = "AU",A88 = "SG"), 1, 0) -> 0 | Z88: =VLOOKUP(R88,CPI!$A$2:$F$71,6,0) -> 1.3590354 | AA88: =T88*Z88 -> 4989.4811 | AB88: =U88*Z88 -> 300.57115 | AC88: Media | AD88: https://zh.wikisource.org/zh-hans/%E5%8C%97%E4%BA%AC%E5%B8%82%E5%9F%8E%E5%B8%82%E8%BD%A8%E9%81%93%E4%BA%A4%E9%80%9A%E7%AC%AC%E4%BA%8C%E6%9C%9F%E5%BB%BA%E8%AE%BE%E8%A7%84%E5%88%92%EF%BC%882015%EF%BD%9E2021%E5%B9%B4%EF%BC%89
A89: CN | B89: Beijing | C89: Line 17 | D89: Line 17 | E89: 2015 | F89: 2022 | G89: 0 | H89: 49.7 | I89: 1 | J89: 49.7 | M89: 20 | N89: 184 | P89: 51085 | Q89: CNY | R89: 2019 | S89: 0.238 | T89: =P89*S89 -> 12158.23 | U89: =T89/H89 -> 244.63239 | V89: =IF(OR(A89 = "BG",A89 = "GR",A89 = "IT",A89 = "ES",A89 = "PT",A89 = "TR", A89 = "KR",A89 = "SE",A89 = "CH",A89 = "NO",A89 = "DK",A89 = "FI"), 1, 0) -> 0 | W89: =V89*H89 -> 0 | X89: =V89*J89 -> 0 | Y89: =IF(OR(A89 = "US",A89 = "CA",A89 = "UK",A89 = "NZ",A89 = "AU",A89 = "SG"), 1, 0) -> 0 | Z89: =VLOOKUP(R89,CPI!$A$2:$F$71,6,0) -> 1.2599479 | AA89: =T89*Z89 -> 15318.736 | AB89: =U89*Z89 -> 308.22407 | AC89: Trade | AD89: http://www.rail-transit.com/project/show.php?itemid=92
A90: CN | B90: Beijing | C90: Line 13 | D90: Line 13A | E90: 2019 | F90: 2022 | G90: 0 | H90: 30.2 | I90: =J90/H90 -> 0.60264901 | J90: 18.2 | K90: 12.08 | L90: 0 | M90: 18 | O90: Plan | P90: 23960 | Q90: CNY | R90: 2019 | S90: 0.238 | T90: =P90*S90 -> 5702.48 | U90: =T90/H90 -> 188.82384 | V90: =IF(OR(A90 = "BG",A90 = "GR",A90 = "IT",A90 = "ES",A90 = "PT",A90 = "TR", A90 = "KR",A90 = "SE",A90 = "CH",A90 = "NO",A90 = "DK",A90 = "FI"), 1, 0) -> 0 | W90: =V90*H90 -> 0 | X90: =V90*J90 -> 0 | Y90: =IF(OR(A90 = "US",A90 = "CA",A90 = "UK",A90 = "NZ",A90 = "AU",A90 = "SG"), 1, 0) -> 0 | Z90: =VLOOKUP(R90,CPI!$A$2:$F$71,6,0) -> 1.2599479 | AA90: =T90*Z90 -> 7184.8277 | AB90: =U90*Z90 -> 237.9082 | AC90: Plan | AD90: http://www.tzxm.gov.cn/flfg/law/201912/t20191220_12825.html; https://baijiahao.baidu.com/s?id=1636643464335769195&wfr=spider&for=pc
A91: CN | B91: Beijing | C91: Line 13 | D91: Line 13B | E91: 2019 | F91: 2022 | G91: 0 | H91: 32.2 | I91: =J91/H91 -> 0.31987578 | J91: 10.3 | K91: 12.11 | L91: 10.108 | M91: 15 | O91: Plan | P91: 12640 | Q91: CNY | R91: 2019 | S91: 0.238 | T91: =S91*P91 -> 3008.32 | U91: =T91/H91 -> 93.426087 | V91: =IF(OR(A91 = "BG",A91 = "GR",A91 = "IT",A91 = "ES",A91 = "PT",A91 = "TR", A91 = "KR",A91 = "SE",A91 = "CH",A91 = "NO",A91 = "DK",A91 = "FI"), 1, 0) -> 0 | W91: =V91*H91 -> 0 | X91: =V91*J91 -> 0 | Y91: =IF(OR(A91 = "US",A91 = "CA",A91 = "UK",A91 = "NZ",A91 = "AU",A91 = "SG"), 1, 0) -> 0 | Z91: =VLOOKUP(R91,CPI!$A$2:$F$71,6,0) -> 1.2599479 | AA91: =T91*Z91 -> 3790.3265 | AB91: =U91*Z91 -> 117.712 | AC91: Plan | AD91: http://www.tzxm.gov.cn/flfg/law/201912/t20191220_12825.html
A92: CN | B92: Beijing | C92: Line 22 | D92: Line 22 | E92: 2019 | F92: 2022 | G92: 0 | H92: 78.6 | I92: 0.62 | J92: 48.5 | K92: 0 | L92: 0 | M92: 20 | O92: Plan | P92: 63930 | Q92: CNY | R92: 2019 | S92: 0.238 | T92: =P92*S92 -> 15215.34 | U92: =T92/H92 -> 193.57939 | V92: =IF(OR(A92 = "BG",A92 = "GR",A92 = "IT",A92 = "ES",A92 = "PT",A92 = "TR", A92 = "KR",A92 = "SE",A92 = "CH",A92 = "NO",A92 = "DK",A92 = "FI"), 1, 0) -> 0 | W92: =V92*H92 -> 0 | X92: =V92*J92 -> 0 | Y92: =IF(OR(A92 = "US",A92 = "CA",A92 = "UK",A92 = "NZ",A92 = "AU",A92 = "SG"), 1, 0) -> 0 | Z92: =VLOOKUP(R92,CPI!$A$2:$F$71,6,0) -> 1.2599479 | AA92: =T92*Z92 -> 19170.536 | AB92: =U92*Z92 -> 243.89994 | AC92: Plan | AD92: http://www.tzxm.gov.cn/flfg/law/201912/t20191220_12825.html
A93: CN | B93: Beijing | C93: Line M101 | D93: Line M101 | E93: 2022 | F93: 2027 | G93: 0 | H93: 19 | I93: 1 | J93: 19 | M93: 14 | N93: 138 | P93: 18753.93 | Q93: CNY | R93: 2021 | S93: 0.239 | T93: =P93*S93 -> 4482.1893 | U93: =T93/H93 -> 235.9047 | V93: =IF(OR(A93 = "BG",A93 = "GR",A93 = "IT",A93 = "ES",A93 = "PT",A93 = "TR", A93 = "KR",A93 = "SE",A93 = "CH",A93 = "NO",A93 = "DK",A93 = "FI"), 1, 0) -> 0 | W93: =V93*H93 -> 0 | X93: =V93*J93 -> 0 | Y93: =IF(OR(A93 = "US",A93 = "CA",A93 = "UK",A93 = "NZ",A93 = "AU",A93 = "SG"), 1, 0) -> 0 | Z93: =VLOOKUP(R93,CPI!$A$2:$F$71,6,0) -> 1.188746 | AA93: =T93*Z93 -> 5328.1845 | AB93: =U93*Z93 -> 280.43076 | AD93: https://web.archive.org/web/20220515142603/https://www.rails.cn/download/2022/20220418_%E9%99%84%E4%BB%B61%EF%BC%9A%E5%8C%97%E4%BA%AC%E8%BD%A8%E9%81%93%E4%BA%A4%E9%80%9AM101%E7%BA%BF%E4%B8%80%E6%9C%9F%E5%B7%A5%E7%A8%8B%E7%8E%AF%E5%A2%83%E5%BD%B1%E5%93%8D%E6%8A%A5%E5%91%8A%E4%B9%A6%EF%BC%88%E5%BE%81%E6%B1%82%E6%84%8F%E8%A7%81%E7%A8%BF%EF%BC%89.pdf
A94: CN | B94: Beijing | C94: Daxing Airport Express | D94: Daxing Airport Express Phase 2 | E94: 2019 | G94: 0 | H94: 3.5 | K94: #N/A | L94: #N/A | M94: 2 | O94: Plan | P94: 4040 | Q94: CNY | R94: 2019 | S94: 0.238 | T94: =S94*P94 -> 961.52 | U94: =T94/H94 -> 274.72 | V94: =IF(OR(A94 = "BG",A94 = "GR",A94 = "IT",A94 = "ES",A94 = "PT",A94 = "TR", A94 = "KR",A94 = "SE",A94 = "CH",A94 = "NO",A94 = "DK",A94 = "FI"), 1, 0) -> 0 | W94: =V94*H94 -> 0 | X94: =V94*J94 -> 0 | Y94: =IF(OR(A94 = "US",A94 = "CA",A94 = "UK",A94 = "NZ",A94 = "AU",A94 = "SG"), 1, 0) -> 0 | Z94: =VLOOKUP(R94,CPI!$A$2:$F$71,6,0) -> 1.2599479 | AA94: =T94*Z94 -> 1211.4651 | AB94: =U94*Z94 -> 346.13289 | AC94: Plan | AD94: http://www.tzxm.gov.cn/flfg/law/201912/t20191220_12825.html
A95: CN | B95: Beijing | C95: Yanfang Branch | D95: Yanfang Branch | E95: 2020 | G95: 0 | H95: 6.015 | I95: 0 | J95: 0 | M95: 3 | N95: 117 | P95: 4500 | Q95: CNY | R95: 2020 | S95: 0.239 | T95: =P95*S95 -> 1075.5 | U95: =T95/H95 -> 178.80299 | V95: =IF(OR(A95 = "BG",A95 = "GR",A95 = "IT",A95 = "ES",A95 = "PT",A95 = "TR", A95 = "KR",A95 = "SE",A95 = "CH",A95 = "NO",A95 = "DK",A95 = "FI"), 1, 0) -> 0 | W95: =V95*H95 -> 0 | X95: =V95*J95 -> 0 | Y95: =IF(OR(A95 = "US",A95 = "CA",A95 = "UK",A95 = "NZ",A95 = "AU",A95 = "SG"), 1, 0) -> 0 | Z95: =VLOOKUP(R95,CPI!$A$2:$F$71,6,0) -> 1.2445935 | AA95: =T95*Z95 -> 1338.5604 | AB95: =U95*Z95 -> 222.53705 | AD95: http://www.rail-transit.com/project/show.php?itemid=525
A96: CN | B96: Changchun | C96: Line 1 | D96: Line 1 South Extension | E96: 2010 | F96: 2019 | G96: 0 | H96: 8 | I96: 1 | J96: 8 | M96: 6 | N96: 117 | P96: 5520 | Q96: CNY | R96: 2015 | S96: 0.258 | T96: =P96*S96 -> 1424.16 | U96: =T96/H96 -> 178.02 | V96: =IF(OR(A96 = "BG",A96 = "GR",A96 = "IT",A96 = "ES",A96 = "PT",A96 = "TR", A96 = "KR",A96 = "SE",A96 = "CH",A96 = "NO",A96 = "DK",A96 = "FI"), 1, 0) -> 0 | W96: =V96*H96 -> 0 | X96: =V96*J96 -> 0 | Y96: =IF(OR(A96 = "US",A96 = "CA",A96 = "UK",A96 = "NZ",A96 = "AU",A96 = "SG"), 1, 0) -> 0 | Z96: =VLOOKUP(R96,CPI!$A$2:$F$71,6,0) -> 1.3590354 | AA96: =T96*Z96 -> 1935.4839 | AB96: =U96*Z96 -> 241.93549 | AD96: https://zfxxgk.ndrc.gov.cn/web/iteminfo.jsp?id=320
A97: CN | B97: Changchun | C97: New Beihu Line | D97: New Beihu Line | E97: 2010 | F97: 2019 | G97: 0 | H97: 13.4 | I97: 0 | J97: 0 | M97: 13 | N97: 55 | P97: 4210 | Q97: CNY | R97: 2015 | S97: 0.258 | T97: =P97*S97 -> 1086.18 | U97: =T97/H97 -> 81.058209 | V97: =IF(OR(A97 = "BG",A97 = "GR",A97 = "IT",A97 = "ES",A97 = "PT",A97 = "TR", A97 = "KR",A97 = "SE",A97 = "CH",A97 = "NO",A97 = "DK",A97 = "FI"), 1, 0) -> 0 | W97: =V97*H97 -> 0 | X97: =V97*J97 -> 0 | Y97: =IF(OR(A97 = "US",A97 = "CA",A97 = "UK",A97 = "NZ",A97 = "AU",A97 = "SG"), 1, 0) -> 0 | Z97: =VLOOKUP(R97,CPI!$A$2:$F$71,6,0) -> 1.3590354 | AA97: =T97*Z97 -> 1476.1571 | AB97: =U97*Z97 -> 110.16098 | AD97: https://zfxxgk.ndrc.gov.cn/web/iteminfo.jsp?id=320
A98: CN | B98: Changchun | C98: Line 2 | D98: Line 2 Western Extension | E98: 2015 | F98: 2019 | G98: 0 | H98: 5.3 | I98: 1 | J98: 5.3 | M98: 3 | N98: 117 | P98: 3350 | Q98: CNY | R98: 2017 | S98: 0.239 | T98: =P98*S98 -> 800.65 | U98: =T98/H98 -> 151.06604 | V98: =IF(OR(A98 = "BG",A98 = "GR",A98 = "IT",A98 = "ES",A98 = "PT",A98 = "TR", A98 = "KR",A98 = "SE",A98 = "CH",A98 = "NO",A98 = "DK",A98 = "FI"), 1, 0) -> 0 | W98: =V98*H98 -> 0 | X98: =V98*J98 -> 0 | Y98: =IF(OR(A98 = "US",A98 = "CA",A98 = "UK",A98 = "NZ",A98 = "AU",A98 = "SG"), 1, 0) -> 0 | Z98: =VLOOKUP(R98,CPI!$A$2:$F$71,6,0) -> 1.3141094 | AA98: =T98*Z98 -> 1052.1417 | AB98: =U98*Z98 -> 198.5173 | AD98: https://zfxxgk.ndrc.gov.cn/web/iteminfo.jsp?id=320
A99: CN | B99: Changchun | C99: Line 2 | D99: Line 2 | F99: 2020 | G99: 0 | H99: 22.8 | I99: 1 | J99: 22.8 | M99: 19 | N99: 117 | P99: 15400 | Q99: CNY | R99: 2020 | S99: 0.239 | T99: =P99*S99 -> 3680.6 | U99: =T99/H99 -> 161.42982 | V99: =IF(OR(A99 = "BG",A99 = "GR",A99 = "IT",A99 = "ES",A99 = "PT",A99 = "TR", A99 = "KR",A99 = "SE",A99 = "CH",A99 = "NO",A99 = "DK",A99 = "FI"), 1, 0) -> 0 | W99: =V99*H99 -> 0 | X99: =V99*J99 -> 0 | Y99: =IF(OR(A99 = "US",A99 = "CA",A99 = "UK",A99 = "NZ",A99 = "AU",A99 = "SG"), 1, 0) -> 0 | Z99: =VLOOKUP(R99,CPI!$A$2:$F$71,6,0) -> 1.2445935 | AA99: =T99*Z99 -> 4580.851 | AB99: =U99*Z99 -> 200.91452 | AD99: http://www.rail-transit.com/project/show.php?itemid=231
A100: CN | B100: Changchun | C100: Line 2 | D100: Line 2 Eastern Extension | E100: 2019 | F100: 2025 | G100: 0 | H100: 9.1 | I100: 1 | J100: 9.1 | K100: 0 | L100: 0 | M100: 5 | O100: Plan | P100: 5131 | Q100: CNY | R100: 2018 | S100: 0.237 | T100: =S100*P100 -> 1216.047 | U100: =T100/H100 -> 133.63154 | V100: =IF(OR(A100 = "BG",A100 = "GR",A100 = "IT",A100 = "ES",A100 = "PT",A100 = "TR", A100 = "KR",A100 = "SE",A100 = "CH",A100 = "NO",A100 = "DK",A100 = "FI"), 1, 0) -> 0 | W100: =V100*H100 -> 0 | X100: =V100*J100 -> 0 | Y100: =IF(OR(A100 = "US",A100 = "CA",A100 = "UK",A100 = "NZ",A100 = "AU",A100 = "SG"), 1, 0) -> 0 | Z100: =VLOOKUP(R100,CPI!$A$2:$F$71,6,0) -> 1.2827779 | AA100: =T100*Z100 -> 1559.9182 | AB100: =U100*Z100 -> 171.41958 | AC100: Plan | AD100: https://www.ndrc.gov.cn/xxgk/zcfb/tz/201812/W020190905514226164270.pdf
A101: CN | B101: Changchun | C101: Line 9 | D101: Line 9 (Konggang) | E101: 2019 | F101: 2025 | G101: 0 | H101: 28.2 | I101: 0.4929078 | J101: 13.9 | K101: 0 | L101: 0 | M101: 8 | O101: Plan | P101: 12640 | Q101: CNY | R101: 2018 | S101: 0.237 | T101: =S101*P101 -> 2995.68 | U101: =T101/H101 -> 106.22979 | V101: =IF(OR(A101 = "BG",A101 = "GR",A101 = "IT",A101 = "ES",A101 = "PT",A101 = "TR", A101 = "KR",A101 = "SE",A101 = "CH",A101 = "NO",A101 = "DK",A101 = "FI"), 1, 0) -> 0 | W101: =V101*H101 -> 0 | X101: =V101*J101 -> 0 | Y101: =IF(OR(A101 = "US",A101 = "CA",A101 = "UK",A101 = "NZ",A101 = "AU",A101 = "SG"), 1, 0) -> 0 | Z101: =VLOOKUP(R101,CPI!$A$2:$F$71,6,0) -> 1.2827779 | AA101: =T101*Z101 -> 3842.792 | AB101: =U101*Z101 -> 136.26922 | AC101: Plan | AD101: https://www.ndrc.gov.cn/xxgk/zcfb/tz/201812/W020190905514226164270.pdf
A102: CN | B102: Changchun | C102: Line 7 | D102: Line 7 Phase 1 | E102: 2020 | F102: 2025 | G102: 0 | H102: 22.5 | I102: 1 | J102: 22.5 | K102: 0 | L102: 0 | M102: 19 | O102: Plan | P102: 15583 | Q102: CNY | R102: 2018 | S102: 0.237 | T102: =P102*S102 -> 3693.171 | U102: =T102/H102 -> 164.14093 | V102: =IF(OR(A102 = "BG",A102 = "GR",A102 = "IT",A102 = "ES",A102 = "PT",A102 = "TR", A102 = "KR",A102 = "SE",A102 = "CH",A102 = "NO",A102 = "DK",A102 = "FI"), 1, 0) -> 0 | W102: =V102*H102 -> 0 | X102: =V102*J102 -> 0 | Y102: =IF(OR(A102 = "US",A102 = "CA",A102 = "UK",A102 = "NZ",A102 = "AU",A102 = "SG"), 1, 0) -> 0 | Z102: =VLOOKUP(R102,CPI!$A$2:$F$71,6,0) -> 1.2827779 | AA102: =T102*Z102 -> 4737.518 | AB102: =U102*Z102 -> 210.55636 | AC102: Plan | AD102: https://www.ndrc.gov.cn/xxgk/zcfb/tz/201812/W020190905514226164270.pdf; https://baike.baidu.com/item/%E9%95%BF%E6%98%A5%E8%BD%A8%E9%81%93%E4%BA%A4%E9%80%9A7%E5%8F%B7%E7%BA%BF/17545289
A103: CN | B103: Changchun | C103: Line 5 | D103: Line 5 Phase 1 | E103: 2021 | G103: 0 | H103: 19.567 | I103: 1 | J103: 19.567 | M103: 18 | N103: 117 | P103: 20000 | Q103: CNY | R103: 2019 | S103: 0.238 | T103: =P103*S103 -> 4760 | U103: =T103/H103 -> 243.26672 | V103: =IF(OR(A103 = "BG",A103 = "GR",A103 = "IT",A103 = "ES",A103 = "PT",A103 = "TR", A103 = "KR",A103 = "SE",A103 = "CH",A103 = "NO",A103 = "DK",A103 = "FI"), 1, 0) -> 0 | W103: =V103*H103 -> 0 | X103: =V103*J103 -> 0 | Y103: =IF(OR(A103 = "US",A103 = "CA",A103 = "UK",A103 = "NZ",A103 = "AU",A103 = "SG"), 1, 0) -> 0 | Z103: =VLOOKUP(R103,CPI!$A$2:$F$71,6,0) -> 1.2599479 | AA103: =T103*Z103 -> 5997.352 | AB103: =U103*Z103 -> 306.5034 | AC103: Plan | AD103: http://www.rail-transit.com/project/show.php?itemid=531
A104: CN | B104: Changchun | C104: Line 3 | D104: Line 3 Southern Extension | G104: 0 | H104: 3 | I104: 0.26666667 | J104: 0.8 | K104: 0 | L104: 0 | M104: 2 | O104: Plan | P104: 839 | Q104: CNY | R104: 2018 | S104: 0.237 | T104: =S104*P104 -> 198.843 | U104: =T104/H104 -> 66.281 | V104: =IF(OR(A104 = "BG",A104 = "GR",A104 = "IT",A104 = "ES",A104 = "PT",A104 = "TR", A104 = "KR",A104 = "SE",A104 = "CH",A104 = "NO",A104 = "DK",A104 = "FI"), 1, 0) -> 0 | W104: =V104*H104 -> 0 | X104: =V104*J104 -> 0 | Y104: =IF(OR(A104 = "US",A104 = "CA",A104 = "UK",A104 = "NZ",A104 = "AU",A104 = "SG"), 1, 0) -> 0 | Z104: =VLOOKUP(R104,CPI!$A$2:$F$71,6,0) -> 1.2827779 | AA104: =T104*Z104 -> 255.0714 | AB104: =U104*Z104 -> 85.023799 | AC104: Plan | AD104: https://www.ndrc.gov.cn/xxgk/zcfb/tz/201812/W020190905514226164270.pdf
A105: CN | B105: Changchun | C105: Line 4 | D105: Line 4 Southern Extension | G105: 0 | H105: 4 | I105: 0 | J105: 0 | K105: 0 | L105: 0 | M105: 6 | O105: Plan | P105: 2013 | Q105: CNY | R105: 2018 | S105: 0.237 | T105: =S105*P105 -> 477.081 | U105: =T105/H105 -> 119.27025 | V105: =IF(OR(A105 = "BG",A105 = "GR",A105 = "IT",A105 = "ES",A105 = "PT",A105 = "TR", A105 = "KR",A105 = "SE",A105 = "CH",A105 = "NO",A105 = "DK",A105 = "FI"), 1, 0) -> 0 | W105: =V105*H105 -> 0 | X105: =V105*J105 -> 0 | Y105: =IF(OR(A105 = "US",A105 = "CA",A105 = "UK",A105 = "NZ",A105 = "AU",A105 = "SG"), 1, 0) -> 0 | Z105: =VLOOKUP(R105,CPI!$A$2:$F$71,6,0) -> 1.2827779 | AA105: =T105*Z105 -> 611.98894 | AB105: =U105*Z105 -> 152.99724 | AC105: Plan | AD105: https://www.ndrc.gov.cn/xxgk/zcfb/tz/201812/W020190905514226164270.pdf
...

Sheet 1_16_2026
A1: d | B1: Country | C1: City | D1: Line | E1: Phase | F1: Start year | G1: End year | H1: RR? | I1: Length | J1: TunnelPer | K1: Tunnel | L1: Elevated | M1: Atgrade | N1: Stations | O1: Platform Length (Meters) | P1: Source1 | Q1: Cost | R1: Currency | S1: Year | T1: PPP rate | U1: Real cost | V1: Cost/km (Millions) | W1: Cheap? | X1: Clength | Y1: Ctunnel | Z1: Anglo? | AA1: Inflation Index | AB1: Real cost (2023 dollars) | AC1: Cost/km (2023 dollars)
A2: 8200 | B2: AE | C2: Dubai | D2: Phase 1 | E2: Phase 1 - Red Line | F2: 2005 | G2: 2010 | H2: 0 | I2: 35 | J2: =K2/I2 -> 0.13428571 | K2: 4.7 | L2: 0 | M2: 0 | N2: 29 | P2: Trade | Q2: 4200 | R2: USD | S2: 2005 | T2: 1.8 | U2: =Q2*T2 -> 7560 | V2: =U2/I2 -> 216 | W2: =IF(OR(B2 = "BG",B2 = "GR",B2 = "IT",B2 = "ES",B2 = "PT",B2 = "TR", B2 = "KR",B2 = "SE",B2 = "CH",B2 = "NO",B2 = "DK",B2 = "FI"), 1, 0) -> 0 | X2: =W2*I2 -> 0 | Y2: =W2*K2 -> 0 | Z2: =IF(OR(B2 = "US",B2 = "CA",B2 = "UK",B2 = "NZ",B2 = "AU",B2 = "SG"), 1, 0) -> 0 | AA2: =VLOOKUP(S2,CPI!$A$2:$E$67,5,0) -> 1.5601741 | AB2: =U2*AA2 -> 11794.916 | AC2: =V2*AA2 -> 336.9976
A3: 8201 | B3: AE | C3: Dubai | D3: Phase 2 | E3: Phase 2 - Green Line | F3: 2006 | G3: 2010 | H3: 0 | I3: 22.5 | J3: =K3/I3 -> 0.35111111 | K3: 7.9 | L3: 0 | M3: 0 | N3: 20 | Q3: 3600 | R3: USD | S3: 2006 | T3: 1.9 | U3: =Q3*T3 -> 6840 | V3: =U3/I3 -> 304 | W3: =IF(OR(B3 = "BG",B3 = "GR",B3 = "IT",B3 = "ES",B3 = "PT",B3 = "TR", B3 = "KR",B3 = "SE",B3 = "CH",B3 = "NO",B3 = "DK",B3 = "FI"), 1, 0) -> 0 | X3: =W3*I3 -> 0 | Y3: =W3*K3 -> 0 | Z3: =IF(OR(B3 = "US",B3 = "CA",B3 = "UK",B3 = "NZ",B3 = "AU",B3 = "SG"), 1, 0) -> 0 | AA3: =VLOOKUP(S3,CPI!$A$2:$E$67,5,0) -> 1.5114187 | AB3: =U3*AA3 -> 10338.104 | AC3: =V3*AA3 -> 459.47127
A4: 8202 | B4: AE | C4: Dubai | D4: Red Line | E4: Phase 3 (Red Line Extension/Route 2020) | F4: 2016 | G4: 2020 | H4: 0 | I4: 15 | J4: =K4/I4 -> 0.21333333 | K4: 3.2 | L4: 0 | M4: 0 | N4: 7 | P4: Trade | Q4: 2900 | R4: USD | S4: 2016 | T4: 1.9 | U4: =Q4*T4 -> 5510 | V4: =U4/I4 -> 367.33333 | W4: =IF(OR(B4 = "BG",B4 = "GR",B4 = "IT",B4 = "ES",B4 = "PT",B4 = "TR", B4 = "KR",B4 = "SE",B4 = "CH",B4 = "NO",B4 = "DK",B4 = "FI"), 1, 0) -> 0 | X4: =W4*I4 -> 0 | Y4: =W4*K4 -> 0 | Z4: =IF(OR(B4 = "US",B4 = "CA",B4 = "UK",B4 = "NZ",B4 = "AU",B4 = "SG"), 1, 0) -> 0 | AA4: =VLOOKUP(S4,CPI!$A$2:$E$67,5,0) -> 1.2695546 | AB4: =U4*AA4 -> 6995.2461 | AC4: =V4*AA4 -> 466.34974
A5: 7593 | B5: AR | C5: Buenos Aires | D5: RER | E5: RER | F5: 2020 | G5: 2026 | H5: 1 | I5: 20 | J5: 1 | K5: 20 | L5: 0 | M5: 0 | N5: 4 | P5: Media | Q5: 2300 | R5: USD | S5: 2023 | T5: 2.02 | U5: =Q5*T5 -> 4646 | V5: =U5/I5 -> 232.3 | W5: =IF(OR(B5 = "BG",B5 = "GR",B5 = "IT",B5 = "ES",B5 = "PT",B5 = "TR", B5 = "KR",B5 = "SE",B5 = "CH",B5 = "NO",B5 = "DK",B5 = "FI"), 1, 0) -> 0 | X5: =W5*I5 -> 0 | Y5: =W5*K5 -> 0 | Z5: =IF(OR(B5 = "US",B5 = "CA",B5 = "UK",B5 = "NZ",B5 = "AU",B5 = "SG"), 1, 0) -> 0 | AA5: =VLOOKUP(S5,CPI!$A$2:$E$67,5,0) -> 1 | AB5: =U5*AA5 -> 4646 | AC5: =V5*AA5 -> 232.3
A6: 9753 | B6: AT | C6: Vienna | D6: va | E6: Lainz Tunnel | F6: 1999 | G6: 2012 | H6: 1 | I6: 12.8 | J6: 1 | K6: 12.8 | L6: 0 | M6: 0 | N6: 0 | P6: Media | Q6: 1300 | R6: EUR | S6: 2005 | T6: 1.25 | U6: =Q6*T6 -> 1625 | V6: =U6/I6 -> 126.95312 | W6: =IF(OR(B6 = "BG",B6 = "GR",B6 = "IT",B6 = "ES",B6 = "PT",B6 = "TR", B6 = "KR",B6 = "SE",B6 = "CH",B6 = "NO",B6 = "DK",B6 = "FI"), 1, 0) -> 0 | X6: =W6*I6 -> 0 | Y6: =W6*K6 -> 0 | Z6: =IF(OR(B6 = "US",B6 = "CA",B6 = "UK",B6 = "NZ",B6 = "AU",B6 = "SG"), 1, 0) -> 0 | AA6: =VLOOKUP(S6,CPI!$A$2:$E$67,5,0) -> 1.5601741 | AB6: =U6*AA6 -> 2535.2829 | AC6: =V6*AA6 -> 198.06898
A7: 7360 | B7: AT | C7: Vienna | D7: Line 2 | E7: Line 2 extension | F7: 2010 | G7: 2013 | H7: 0 | I7: 4.2 | J7: 0 | K7: 0 | L7: 2.63 | M7: 1.57 | N7: 3 | P7: Media | Q7: 320 | R7: EUR | S7: 2012 | T7: 1.3 | U7: =Q7*T7 -> 416 | V7: =U7/I7 -> 99.047619 | W7: =IF(OR(B7 = "BG",B7 = "GR",B7 = "IT",B7 = "ES",B7 = "PT",B7 = "TR", B7 = "KR",B7 = "SE",B7 = "CH",B7 = "NO",B7 = "DK",B7 = "FI"), 1, 0) -> 0 | X7: =W7*I7 -> 0 | Y7: =W7*K7 -> 0 | Z7: =IF(OR(B7 = "US",B7 = "CA",B7 = "UK",B7 = "NZ",B7 = "AU",B7 = "SG"), 1, 0) -> 0 | AA7: =VLOOKUP(S7,CPI!$A$2:$E$67,5,0) -> 1.327134 | AB7: =U7*AA7 -> 552.08774 | AC7: =V7*AA7 -> 131.44946
A8: 7361 | B8: AT | C8: Vienna | D8: Line 1 | E8: Line 1 extension | F8: 2012 | G8: 2017 | H8: 0 | I8: 4.7 | J8: 0.57 | K8: 2.7 | L8: 0.06 | M8: 2.008 | N8: 5 | P8: Measured | Q8: 600 | R8: EUR | S8: 2015 | T8: 1.3 | U8: =Q8*T8 -> 780 | V8: =U8/I8 -> 165.95745 | W8: =IF(OR(B8 = "BG",B8 = "GR",B8 = "IT",B8 = "ES",B8 = "PT",B8 = "TR", B8 = "KR",B8 = "SE",B8 = "CH",B8 = "NO",B8 = "DK",B8 = "FI"), 1, 0) -> 0 | X8: =W8*I8 -> 0 | Y8: =W8*K8 -> 0 | Z8: =IF(OR(B8 = "US",B8 = "CA",B8 = "UK",B8 = "NZ",B8 = "AU",B8 = "SG"), 1, 0) -> 0 | AA8: =VLOOKUP(S8,CPI!$A$2:$E$67,5,0) -> 1.2855702 | AB8: =U8*AA8 -> 1002.7448 | AC8: =V8*AA8 -> 213.34995
A9: 7362 | B9: AT | C9: Vienna | D9: U2/U5 cross | E9: U2/U5 cross | F9: 2019 | G9: 2029 | H9: 0 | I9: 9 | J9: 1 | K9: 9 | L9: 0 | M9: 0 | N9: 11 | P9: Plan | Q9: 2200 | R9: EUR | S9: 2023 | T9: 1.3 | U9: =Q9*T9 -> 2860 | V9: =U9/I9 -> 317.77778 | W9: =IF(OR(B9 = "BG",B9 = "GR",B9 = "IT",B9 = "ES",B9 = "PT",B9 = "TR", B9 = "KR",B9 = "SE",B9 = "CH",B9 = "NO",B9 = "DK",B9 = "FI"), 1, 0) -> 0 | X9: =W9*I9 -> 0 | Y9: =W9*K9 -> 0 | Z9: =IF(OR(B9 = "US",B9 = "CA",B9 = "UK",B9 = "NZ",B9 = "AU",B9 = "SG"), 1, 0) -> 0 | AA9: =VLOOKUP(S9,CPI!$A$2:$E$67,5,0) -> 1 | AB9: =U9*AA9 -> 2860 | AC9: =V9*AA9 -> 317.77778
A10: 7280 | B10: AU | C10: Melbourne | D10: Metro Tunnel | E10: Metro Tunnel | F10: 2018 | G10: 2025 | H10: 0 | I10: 9 | J10: 1 | K10: 9 | L10: 0 | M10: 0 | N10: 5 | P10: Plan | Q10: 12584.4 | R10: AUD | S10: 2021 | T10: 0.69 | U10: =Q10*T10 -> 8683.236 | V10: =U10/I10 -> 964.804 | W10: =IF(OR(B10 = "BG",B10 = "GR",B10 = "IT",B10 = "ES",B10 = "PT",B10 = "TR", B10 = "KR",B10 = "SE",B10 = "CH",B10 = "NO",B10 = "DK",B10 = "FI"), 1, 0) -> 0 | X10: =W10*I10 -> 0 | Y10: =W10*K10 -> 0 | Z10: =IF(OR(B10 = "US",B10 = "CA",B10 = "UK",B10 = "NZ",B10 = "AU",B10 = "SG"), 1, 0) -> 1 | AA10: =VLOOKUP(S10,CPI!$A$2:$E$67,5,0) -> 1.1244861 | AB10: =U10*AA10 -> 9764.1782 | AC10: =V10*AA10 -> 1084.9087
A11: 7587 | B11: AU | C11: Perth | D11: Forrestfield-Airport Link | E11: Forrestfield-Airport Link | F11: 2016 | G11: 2021 | H11: 1 | I11: 8.5 | J11: 1 | K11: 8.5 | L11: 0 | M11: 0 | N11: 3 | P11: Plan | Q11: 1860 | R11: AUD | S11: 2018 | T11: 0.69 | U11: =Q11*T11 -> 1283.4 | V11: =U11/I11 -> 150.98824 | W11: =IF(OR(B11 = "BG",B11 = "GR",B11 = "IT",B11 = "ES",B11 = "PT",B11 = "TR", B11 = "KR",B11 = "SE",B11 = "CH",B11 = "NO",B11 = "DK",B11 = "FI"), 1, 0) -> 0 | X11: =W11*I11 -> 0 | Y11: =W11*K11 -> 0 | Z11: =IF(OR(B11 = "US",B11 = "CA",B11 = "UK",B11 = "NZ",B11 = "AU",B11 = "SG"), 1, 0) -> 1 | AA11: =VLOOKUP(S11,CPI!$A$2:$E$67,5,0) -> 1.2134349 | AB11: =U11*AA11 -> 1557.3224 | AC11: =V11*AA11 -> 183.2144
A12: 7275 | B12: AU | C12: Sydney | D12: Metro NW | E12: Metro NW | F12: 2013 | G12: 2019 | H12: 0 | I12: 36 | J12: 0.42 | K12: 15.1 | L12: 0 | M12: 0 | N12: 13 | P12: Wiki | Q12: 7800 | R12: AUD | S12: 2016 | T12: 0.69 | U12: =Q12*T12 -> 5382 | V12: =U12/I12 -> 149.5 | W12: =IF(OR(B12 = "BG",B12 = "GR",B12 = "IT",B12 = "ES",B12 = "PT",B12 = "TR", B12 = "KR",B12 = "SE",B12 = "CH",B12 = "NO",B12 = "DK",B12 = "FI"), 1, 0) -> 0 | X12: =W12*I12 -> 0 | Y12: =W12*K12 -> 0 | Z12: =IF(OR(B12 = "US",B12 = "CA",B12 = "UK",B12 = "NZ",B12 = "AU",B12 = "SG"), 1, 0) -> 1 | AA12: =VLOOKUP(S12,CPI!$A$2:$E$67,5,0) -> 1.2695546 | AB12: =U12*AA12 -> 6832.7431 | AC12: =V12*AA12 -> 189.79842
A13: 7274 | B13: AU | C13: Sydney | D13: Metro City & SW | E13: Metro City & SW | F13: 2017 | G13: 2024 | H13: 0 | I13: 30 | J13: 0.51 | K13: 15.3 | L13: 0 | M13: 0 | N13: 7 | P13: Wiki | Q13: 15500 | R13: AUD | S13: 2021 | T13: 0.69 | U13: =Q13*T13 -> 10695 | V13: =U13/I13 -> 356.5 | W13: =IF(OR(B13 = "BG",B13 = "GR",B13 = "IT",B13 = "ES",B13 = "PT",B13 = "TR", B13 = "KR",B13 = "SE",B13 = "CH",B13 = "NO",B13 = "DK",B13 = "FI"), 1, 0) -> 0 | X13: =W13*I13 -> 0 | Y13: =W13*K13 -> 0 | Z13: =IF(OR(B13 = "US",B13 = "CA",B13 = "UK",B13 = "NZ",B13 = "AU",B13 = "SG"), 1, 0) -> 1 | AA13: =VLOOKUP(S13,CPI!$A$2:$E$67,5,0) -> 1.1244861 | AB13: =U13*AA13 -> 12026.379 | AC13: =V13*AA13 -> 400.8793
A14: 7464 | B14: BD | C14: Dhaka | D14: Line 6 | E14: Line 6 | F14: 2015 | G14: 2022 | H14: 0 | I14: 21.3 | J14: 0 | K14: 0 | L14: 0 | M14: 0 | N14: 16 | P14: Media | Q14: 334720 | R14: BDT | S14: 2019 | T14: 0.032 | U14: =Q14*T14 -> 10711.04 | V14: =U14/I14 -> 502.86573 | W14: =IF(OR(B14 = "BG",B14 = "GR",B14 = "IT",B14 = "ES",B14 = "PT",B14 = "TR", B14 = "KR",B14 = "SE",B14 = "CH",B14 = "NO",B14 = "DK",B14 = "FI"), 1, 0) -> 0 | X14: =W14*I14 -> 0 | Y14: =W14*K14 -> 0 | Z14: =IF(OR(B14 = "US",B14 = "CA",B14 = "UK",B14 = "NZ",B14 = "AU",B14 = "SG"), 1, 0) -> 0 | AA14: =VLOOKUP(S14,CPI!$A$2:$E$67,5,0) -> 1.1918391 | AB14: =U14*AA14 -> 12765.836 | AC14: =V14*AA14 -> 599.33502
A15: 7465 | B15: BD | C15: Dhaka | D15: Line 1 | E15: Line 1 | F15: 2020 | G15: 2026 | H15: 0 | I15: 31.2 | J15: 0.64 | K15: 19.9 | L15: 0 | M15: 0 | N15: 19 | P15: Media | Q15: 525610 | R15: BDT | S15: 2023 | T15: 0.032 | U15: =Q15*T15 -> 16819.52 | V15: =U15/I15 -> 539.08718 | W15: =IF(OR(B15 = "BG",B15 = "GR",B15 = "IT",B15 = "ES",B15 = "PT",B15 = "TR", B15 = "KR",B15 = "SE",B15 = "CH",B15 = "NO",B15 = "DK",B15 = "FI"), 1, 0) -> 0 | X15: =W15*I15 -> 0 | Y15: =W15*K15 -> 0 | Z15: =IF(OR(B15 = "US",B15 = "CA",B15 = "UK",B15 = "NZ",B15 = "AU",B15 = "SG"), 1, 0) -> 0 | AA15: =VLOOKUP(S15,CPI!$A$2:$E$67,5,0) -> 1 | AB15: =U15*AA15 -> 16819.52 | AC15: =V15*AA15 -> 539.08718
A16: 7466 | B16: BD | C16: Dhaka | D16: Line 5 | E16: Line 5 | F16: 2020 | G16: 2028 | H16: 0 | I16: 19.6 | J16: 0.7 | K16: 14 | L16: 0 | M16: 0 | N16: 14 | P16: Media | Q16: 412380 | R16: BDT | S16: 2024 | T16: 0.032 | U16: =Q16*T16 -> 13196.16 | V16: =U16/I16 -> 673.27347 | W16: =IF(OR(B16 = "BG",B16 = "GR",B16 = "IT",B16 = "ES",B16 = "PT",B16 = "TR", B16 = "KR",B16 = "SE",B16 = "CH",B16 = "NO",B16 = "DK",B16 = "FI"), 1, 0) -> 0 | X16: =W16*I16 -> 0 | Y16: =W16*K16 -> 0 | Z16: =IF(OR(B16 = "US",B16 = "CA",B16 = "UK",B16 = "NZ",B16 = "AU",B16 = "SG"), 1, 0) -> 0 | AA16: =VLOOKUP(S16,CPI!$A$2:$E$67,5,0) -> 1 | AB16: =U16*AA16 -> 13196.16 | AC16: =V16*AA16 -> 673.27347
... A22: 7177 | B22: BG | C22: Sofia | D22: Line 3 | E22: Line 3 extension (Third Stage) | F22: 2021 | G22: 2026 | H22: 0 | I22: 3.1 | J22: 1 | K22: 3.1 | L22: 0 | M22: 0 | N22: 4 | P22: Plan | Q22: 112.5 | R22: EUR | S22: 2021 | T22: 3.32 | U22: =Q22*T22 -> 373.5 | V22: =U22/I22 -> 120.48387 | W22: =IF(OR(B22 = "BG",B22 = "GR",B22 = "IT",B22 = "ES",B22 = "PT",B22 = "TR", B22 = "KR",B22 = "SE",B22 = "CH",B22 = "NO",B22 = "DK",B22 = "FI"), 1, 0) -> 1 | X22: =W22*I22 -> 3.1 | Y22: =W22*K22 -> 3.1 | Z22: =IF(OR(B22 = "US",B22 = "CA",B22 = "UK",B22 = "NZ",B22 = "AU",B22 = "SG"), 1, 0) -> 0 | AA22: =VLOOKUP(S22,CPI!$A$2:$E$67,5,0) -> 1.1244861 | AB22: =U22*AA22 -> 419.99556 | AC22: =V22*AA22 -> 135.48244
A23: 7168 | B23: BG | C23: Sofia | D23: Line 1 | E23: Line 1 northern | F23: 2009 | G23: cond | H23: 0 | I23: 5.1 | J23: 0.6 | K23: 3.1 | L23: 0 | M23: 0 | N23: 4 | P23: Measured | Q23: 407 | R23: BGN | S23: 2010 | T23: 1.69 | U23: =Q23*T23 -> 687.83 | V23: =U23/I23 -> 134.86863 | W23: =IF(OR(B23 = "BG",B23 = "GR",B23 = "IT",B23 = "ES",B23 = "PT",B23 = "TR", B23 = "KR",B23 = "SE",B23 = "CH",B23 = "NO",B23 = "DK",B23 = "FI"), 1, 0) -> 1 | X23: =W23*I23 -> 5.1 | Y23: =W23*K23 -> 3.1 | Z23: =IF(OR(B23 = "US",B23 = "CA",B23 = "UK",B23 = "NZ",B23 = "AU",B23 = "SG"), 1, 0) -> 0 | AA23: =VLOOKUP(S23,CPI!$A$2:$E$67,5,0) -> 1.3973566 | AB23: =U23*AA23 -> 961.14382 | AC23: =V23*AA23 -> 188.45957
A24: 8194 | B24: BH | C24: Bahrain | D24: Phase 1 | E24: Phase 1 (Red & Blue) | F24: 2018 | G24: 2023 | H24: 1 | I24: 28.6 | J24: =K24/I24 -> 0 | K24: 0 | L24: 0 | M24: 0 | N24: 20 | Q24: 453 | R24: BD | S24: 2019 | T24: =1/0.2 -> 5 | U24: =Q24*T24 -> 2265 | V24: =U24/I24 -> 79.195804 | W24: =IF(OR(B24 = "BG",B24 = "GR",B24 = "IT",B24 = "ES",B24 = "PT",B24 = "TR", B24 = "KR",B24 = "SE",B24 = "CH",B24 = "NO",B24 = "DK",B24 = "FI"), 1, 0) -> 0 | X24: =W24*I24 -> 0 | Y24: =W24*K24 -> 0 | Z24: =IF(OR(B24 = "US",B24 = "CA",B24 = "UK",B24 = "NZ",B24 = "AU",B24 = "SG"), 1, 0) -> 0 | AA24: =VLOOKUP(S24,CPI!$A$2:$E$67,5,0) -> 1.1918391 | AB24: =U24*AA24 -> 2699.5155 | AC24: =V24*AA24 -> 94.388653
A25: 8195 | B25: BH | C25: Bahrain | D25: Phase 2 | E25: Phase 2 | F25: 2020 | G25: X | H25: 1 | I25: 72.7 | J25: =K25/I25 -> 0 | K25: 0 | L25: 0 | M25: 0 | Q25: 1500 | R25: BD | S25: 2010 | T25: =1/0.2 -> 5 | U25: =Q25*T25 -> 7500 | V25: =U25/I25 -> 103.16369 | W25: =IF(OR(B25 = "BG",B25 = "GR",B25 = "IT",B25 = "ES",B25 = "PT",B25 = "TR", B25 = "KR",B25 = "SE",B25 = "CH",B25 = "NO",B25 = "DK",B25 = "FI"), 1, 0) -> 0 | X25: =W25*I25 -> 0 | Y25: =W25*K25 -> 0 | Z25: =IF(OR(B25 = "US",B25 = "CA",B25 = "UK",B25 = "NZ",B25 = "AU",B25 = "SG"), 1, 0) -> 0 | AA25: =VLOOKUP(S25,CPI!$A$2:$E$67,5,0) -> 1.3973566 | AB25: =U25*AA25 -> 10480.175 | AC25: =V25*AA25 -> 144.15646
A26: 9754 | B26: BR | C26: Rio de Janeiro | D26: Line 4 | E26: Line 4 | F26: 2010 | G26: 2016 | H26: 0 | I26: 16 | J26: 0.96 | K26: 15.4 | L26: 0 | M26: 0 | N26: 7 | P26: Measured | Q26: 10300 | R26: BRL | S26: 2013 | T26: 0.59 | U26: =Q26*T26 -> 6077 | V26: =U26/I26 -> 379.8125 | W26: =IF(OR(B26 = "BG",B26 = "GR",B26 = "IT",B26 = "ES",B26 = "PT",B26 = "TR", B26 = "KR",B26 = "SE",B26 = "CH",B26 = "NO",B26 = "DK",B26 = "FI"), 1, 0) -> 0 | X26: =W26*I26 -> 0 | Y26: =W26*K26 -> 0 | Z26: =IF(OR(B26 = "US",B26 = "CA",B26 = "UK",B26 = "NZ",B26 = "AU",B26 = "SG"), 1, 0) -> 0 | AA26: =VLOOKUP(S26,CPI!$A$2:$E$67,5,0) -> 1.3079753 | AB26: =U26*AA26 -> 7948.5658 | AC26: =V26*AA26 -> 496.78537
A27: 7344 | B27: BR | C27: Salvador | D27: Lines 1-2 | E27: Lines 1-2 | F27: 2000 | G27: 2017 | H27: 0 | I27: 33 | J27: 0.04 | K27: 1.4 | L27: 10.935 | M27: 20.745 | N27: 20 | P27: Wiki | Q27: 4800 | R27: BRL | S27: 2012 | T27: 0.62 | U27: =Q27*T27 -> 2976 | V27: =U27/I27 -> 90.181818 | W27: =IF(OR(B27 = "BG",B27 = "GR",B27 = "IT",B27 = "ES",B27 = "PT",B27 = "TR", B27 = "KR",B27 = "SE",B27 = "CH",B27 = "NO",B27 = "DK",B27 = "FI"), 1, 0) -> 0 | X27: =W27*I27 -> 0 | Y27: =W27*K27 -> 0 | Z27: =IF(OR(B27 = "US",B27 = "CA",B27 = "UK",B27 = "NZ",B27 = "AU",B27 = "SG"), 1, 0) -> 0 | AA27: =VLOOKUP(S27,CPI!$A$2:$E$67,5,0) -> 1.327134 | AB27: =U27*AA27 -> 3949.5507 | AC27: =V27*AA27 -> 119.68336
A28: 9755 | B28: BR | C28: Salvador | D28: SkyRail Bahia | E28: SkyRail Bahia | F28: 2020 | G28: 2022 | H28: 0 | I28: 23.3 | J28: 0 | K28: 0 | L28: 0 | M28: 0 | N28: 26 | P28: Trade | Q28: 689 | R28: USD | S28: 2021 | T28: 2.3 | U28: =Q28*T28 -> 1584.7 | V28: =U28/I28 -> 68.012876 | W28: =IF(OR(B28 = "BG",B28 = "GR",B28 = "IT",B28 = "ES",B28 = "PT",B28 = "TR", B28 = "KR",B28 = "SE",B28 = "CH",B28 = "NO",B28 = "DK",B28 = "FI"), 1, 0) -> 0 | X28: =W28*I28 -> 0 | Y28: =W28*K28 -> 0 | Z28: =IF(OR(B28 = "US",B28 = "CA",B28 = "UK",B28 = "NZ",B28 = "AU",B28 = "SG"), 1, 0) -> 0 | AA28: =VLOOKUP(S28,CPI!$A$2:$E$67,5,0) -> 1.1244861 | AB28: =U28*AA28 -> 1781.9731 | AC28: =V28*AA28 -> 76.479534
A29: 7339 | B29: BR | C29: Sao Paulo | D29: Line 5 | E29: Line 5 extension | F29: 2010 | G29: 2019 | H29: 0 | I29: 12 | J29: 1 | K29: 12 | L29: 0 | M29: 0 | N29: 11 | P29: Wiki | Q29: 6900 | R29: BRL | S29: 2014 | T29: 0.55 | U29: =Q29*T29 -> 3795 | V29: =U29/I29 -> 316.25 | W29: =IF(OR(B29 = "BG",B29 = "GR",B29 = "IT",B29 = "ES",B29 = "PT",B29 = "TR", B29 = "KR",B29 = "SE",B29 = "CH",B29 = "NO",B29 = "DK",B29 = "FI"), 1, 0) -> 0 | X29: =W29*I29 -> 0 | Y29: =W29*K29 -> 0 | Z29: =IF(OR(B29 = "US",B29 = "CA",B29 = "UK",B29 = "NZ",B29 = "AU",B29 = "SG"), 1, 0) -> 0 | AA29: =VLOOKUP(S29,CPI!$A$2:$E$67,5,0) -> 1.2870962 | AB29: =U29*AA29 -> 4884.53 | AC29: =V29*AA29 -> 407.04417
A30: 9756 | B30: BR | C30: Sao Paulo | D30: Line 17 | E30: Line 17 | F30: 2012 | G30: 2021 | H30: 0 | I30: 7.7 | J30: 0 | K30: 0 | L30: 0 | M30: 0 | N30: 8 | P30: Trade | Q30: 1300 | R30: USD | S30: 2016 | T30: 2.3 | U30: =Q30*T30 -> 2990 | V30: =U30/I30 -> 388.31169 | W30: =IF(OR(B30 = "BG",B30 = "GR",B30 = "IT",B30 = "ES",B30 = "PT",B30 = "TR", B30 = "KR",B30 = "SE",B30 = "CH",B30 = "NO",B30 = "DK",B30 = "FI"), 1, 0) -> 0 | X30: =W30*I30 -> 0 | Y30: =W30*K30 -> 0 | Z30: =IF(OR(B30 = "US",B30 = "CA",B30 = "UK",B30 = "NZ",B30 = "AU",B30 = "SG"), 1, 0) -> 0 | AA30: =VLOOKUP(S30,CPI!$A$2:$E$67,5,0) -> 1.2695546 | AB30: =U30*AA30 -> 3795.9684 | AC30: =V30*AA30 -> 492.9829
A31: 7528 | B31: BR | C31: Sao Paulo | D31: Line 6 | E31: Line 6 phase 1 | F31: 2015 | G31: 2023 | H31: 0 | I31: 15.9 | J31: 0.84 | K31: 13.4 | L31: 0 | M31: 0 | N31: 15 | P31: Trade | Q31: 9600 | R31: BRL | S31: 2020 | T31: 0.44 | U31: =Q31*T31 -> 4224 | V31: =U31/I31 -> 265.66038 | W31: =IF(OR(B31 = "BG",B31 = "GR",B31 = "IT",B31 = "ES",B31 = "PT",B31 = "TR", B31 = "KR",B31 = "SE",B31 = "CH",B31 = "NO",B31 = "DK",B31 = "FI"), 1, 0) -> 0 | X31: =W31*I31 -> 0 | Y31: =W31*K31 -> 0 | Z31: =IF(OR(B31 = "US",B31 = "CA",B31 = "UK",B31 = "NZ",B31 = "AU",B31 = "SG"), 1, 0) -> 0 | AA31: =VLOOKUP(S31,CPI!$A$2:$E$67,5,0) -> 1.1773147 | AB31: =U31*AA31 -> 4972.9774 | AC31: =V31*AA31 -> 312.76587
A32: 9761 | B32: CA | C32: Calgary | D32: Green Line | E32: Green Line stage 1 | F32: 2021 | G32: 2027 | H32: 0 | I32: 20 | J32: 0.2 | K32: 4 | L32: 0 | M32: 0 | N32: 15 | P32: Wiki | Q32: 5500 | R32: CAD | S32: 2024 | T32: 0.84 | U32: =Q32*T32 -> 4620 | V32: =U32/I32 -> 231 | W32: =IF(OR(B32 = "BG",B32 = "GR",B32 = "IT",B32 = "ES",B32 = "PT",B32 = "TR", B32 = "KR",B32 = "SE",B32 = "CH",B32 = "NO",B32 = "DK",B32 = "FI"), 1, 0) -> 0 | X32: =W32*I32 -> 0 | Y32: =W32*K32 -> 0 | Z32: =IF(OR(B32 = "US",B32 = "CA",B32 = "UK",B32 = "NZ",B32 = "AU",B32 = "SG"), 1, 0) -> 1 | AA32: =VLOOKUP(S32,CPI!$A$2:$E$67,5,0) -> 1 | AB32: =U32*AA32 -> 4620 | AC32: =V32*AA32 -> 231
B33: CA | C33: Edmonton | D33: Valley Line Southeast | E33: Southeast | F33: 2016 | G33: 2023 | H33: 0 | I33: 13.1 | J33: 0.03 | K33: 0.4 | N33: 12 | O33: 125 | P33: Wiki | Q33: 1800 | R33: CAD | S33: 2019 | T33: 0.802 | U33: =Q33*T33 -> 1443.6 | V33: =U33/I33 -> 110.19847 | W33: =IF(OR(B33 = "BG",B33 = "GR",B33 = "IT",B33 = "ES",B33 = "PT",B33 = "TR", B33 = "KR",B33 = "SE",B33 = "CH",B33 = "NO",B33 = "DK",B33 = "FI"), 1, 0) -> 0 | X33: =W33*I33 -> 0 | Y33: =W33*K33 -> 0 | Z33: =IF(OR(B33 = "US",B33 = "CA",B33 = "UK",B33 = "NZ",B33 = "AU",B33 = "SG"), 1, 0) -> 1 | AA33: =VLOOKUP(S33,CPI!$A$2:$E$67,5,0) -> 1.1918391 | AB33: =U33*AA33 -> 1720.5389 | AC33: =V33*AA33 -> 131.33885
A34: 7104 | B34: CA | C34: Edmonton | D34: Metro Line Extension | E34: Northwest Phase 1 | F34: 2020 | G34: 2024 | H34: 0 | I34: 1.6 | J34: 0 | K34: 0 | L34: 0 | M34: 1.6 | N34: 2 | O34: 125 | P34: Plan | Q34: 291 | R34: CAD | S34: 2020 | T34: 0.81 | U34: =Q34*T34 -> 235.71 | V34: =U34/I34 -> 147.31875 | Z34: 1 | AA34: =VLOOKUP(S34,CPI!$A$2:$E$67,5,0) -> 1.1773147 | AB34: =U34*AA34 -> 277.50485 | AC34: =V34*AA34 -> 173.44053
A35: 7103 | B35: CA | C35: Edmonton | D35: Valley Line Extension | E35: West | F35: 2022 | G35: 2028 | H35: 0 | I35: 14 | J35: 0 | K35: 0 | L35: 2.1 | M35: =14-2.1 -> 11.9 | N35: 14 | O35: 125 | P35: Plan | Q35: 2700 | R35: CAD | S35: 2022 | T35: 0.88 | U35: =Q35*T35 -> 2376 | V35: =U35/I35 -> 169.71429 | W35: 0 | Z35: 1 | AA35: =VLOOKUP(S35,CPI!$A$2:$E$67,5,0) -> 1.0411645 | AB35: =U35*AA35 -> 2473.8069 | AC35: =V35*AA35 -> 176.70049
A36: 7116 | B36: CA | C36: Hamilton | D36: Hamilton LRT | E36: Phase 1 | F36: 2025 | G36: 2029 | H36: 0 | I36: 14 | J36: 0 | K36: 0 | L36: 0 | M36: 14 | N36: 17 | O36: 50 | P36: Plan | Q36: 3400 | R36: CAD | S36: 2025 | T36: 1 | U36: =Q36*T36 -> 3400 | V36: =U36/I36 -> 242.85714 | AA36: =VLOOKUP(S36,CPI!$A$2:$E$67,5,0) -> 1 | AB36: =U36*AA36 -> 3400 | AC36: =V36*AA36 -> 242.85714
A37: 7114 | B37: CA | C37: Mississauga | D37: Hazel McCallion LRT | E37: Phase 1 | F37: 2020 | G37: 2027 | H37: 0 | I37: 18 | J37: =(1/19)% -> 0.00052631579 | K37: 1 | M37: 18 | N37: 19 | O37: 50 | P37: Plan | Q37: 4700 | R37: CAD | S37: 2020 | T37: 0.84 | U37: =Q37*T37 -> 3948 | V37: =U37/I37 -> 219.33333 | AA37: =VLOOKUP(S37,CPI!$A$2:$E$67,5,0) -> 1.1773147 | AB37: =U37*AA37 -> 4648.0385 | AC37: =V37*AA37 -> 258.22436
A38: 7401 | B38: CA | C38: Montreal | D38: Laval extension | E38: Laval extension | F38: 2001 | G38: 2007 | H38: 0 | I38: 5.2 | J38: 1 | K38: 5.2 | L38: 0 | M38: 0 | N38: 3 | P38: Wiki | Q38: 745 | R38: CAD | S38: 2004 | T38: 0.81 | U38: =Q38*T38 -> 603.45 | V38: =U38/I38 -> 116.04808 | W38: =IF(OR(B38 = "BG",B38 = "GR",B38 = "IT",B38 = "ES",B38 = "PT",B38 = "TR", B38 = "KR",B38 = "SE",B38 = "CH",B38 = "NO",B38 = "DK",B38 = "FI"), 1, 0) -> 0 | X38: =W38*I38 -> 0 | Y38: =W38*K38 -> 0 | Z38: =IF(OR(B38 = "US",B38 = "CA",B38 = "UK",B38 = "NZ",B38 = "AU",B38 = "SG"), 1, 0) -> 1 | AA38: =VLOOKUP(S38,CPI!$A$2:$E$67,5,0) -> 1.6130334 | AB38: =U38*AA38 -> 973.38498 | AC38: =V38*AA38 -> 187.18942
A39: 7146 | B39: CA | C39: Montreal | D39: Blue Line | E39: Blue Line | F39: 2020 | G39: 2026 | H39: 0 | I39: 5.8 | J39: 1 | K39: 5.8 | L39: 0 | M39: 0 | N39: 5 | P39: Media | Q39: 7600 | R39: CAD | S39: 2018 | T39: 0.84 | U39: =Q39*T39 -> 6384 | V39: =U39/I39 -> 1100.6897 | W39: =IF(OR(B39 = "BG",B39 = "GR",B39 = "IT",B39 = "ES",B39 = "PT",B39 = "TR", B39 = "KR",B39 = "SE",B39 = "CH",B39 = "NO",B39 = "DK",B39 = "FI"), 1, 0) -> 0 | X39: =W39*I39 -> 0 | Y39: =W39*K39 -> 0 | Z39: =IF(OR(B39 = "US",B39 = "CA",B39 = "UK",B39 = "NZ",B39 = "AU",B39 = "SG"), 1, 0) -> 1 | AA39: =VLOOKUP(S39,CPI!$A$2:$E$67,5,0) -> 1.2134349 | AB39: =U39*AA39 -> 7746.5685 | AC39: =V39*AA39 -> 1335.6153
A40: 7130 | B40: CA | C40: Montreal | D40: PSE | E40: Phase 1 | F40: 2025 | G40: 2033 | H40: 0 | I40: 31 | J40: 0 | K40: 0 | L40: 0 | M40: 31 | N40: 36/22 | P40: Plan | Q40: 19000 | R40: CAD | S40: 2025 | T40: 1 | U40: 19000 | V40: =U40/I40 -> 612.90323 | Z40: 0 | AA40: 1 | AB40: =U40*AA40 -> 19000 | AC40: =V40*AA40 -> 612.90323
A41: 7125 | B41: CA | C41: Montreal | D41: REM | E41: Current Project Scope | F41: 2018 | G41: 2027 | H41: 0 | I41: 67 | J41: =10.5/67 -> 0.15671642 | K41: 10.5 | L41: 16.3 | M41: 36.7 | N41: 24 | O41: 26 | P41: Plan | Q41: 9400 | R41: CAD | S41: 2018 | T41: 0.84 | U41: =Q41*T41 -> 7896 | V41: =U41/I41 -> 117.85075 | W41: 0 | X41: =W41*I41 -> 0 | Y41: =X41*J41 -> 0 | Z41: 1 | AA41: =VLOOKUP(S41,CPI!$A$2:$E$67,5,0) -> 1.2134349 | AB41: =U41*AA41 -> 9581.2821 | AC41: =V41*AA41 -> 143.00421
A42: 7117 | B42: CA | C42: Ottawa | D42: Confederation | E42: Confederation | F42: 2013 | G42: 2019 | H42: 0 | I42: 12.5 | J42: 0.2 | K42: 2.5 | L42: 0.84 | M42: 9.16 | N42: 13 | O42: 90/120 | P42: Trade | Q42: 2100 | R42: CAD | S42: 2016 | T42: 0.83 | U42: =Q42*T42 -> 1743 | V42: =U42/I42 -> 139.44 | W42: =IF(OR(B42 = "BG",B42 = "GR",B42 = "IT",B42 = "ES",B42 = "PT",B42 = "TR", B42 = "KR",B42 = "SE",B42 = "CH",B42 = "NO",B42 = "DK",B42 = "FI"), 1, 0) -> 0 | X42: =W42*I42 -> 0 | Y42: =W42*K42 -> 0 | Z42: =IF(OR(B42 = "US",B42 = "CA",B42 = "UK",B42 = "NZ",B42 = "AU",B42 = "SG"), 1, 0) -> 1 | AA42: =VLOOKUP(S42,CPI!$A$2:$E$67,5,0) -> 1.2695546 | AB42: =U42*AA42 -> 2212.8337 | AC42: =V42*AA42 -> 177.0267
A43: 7118 | B43: CA | C43: Ottawa | D43: Confederation | E43: East West Extensions | F43: 2019 | G43: 2025 | H43: 0 | I43: 28 | J43: =(3.4/28) -> 0.12142857 | K43: 3.4 | L43: 0 | M43: 12 | N43: 17 | O43: 90/120 | P43: Plan | Q43: 2600 | R43: CAD | S43: 2019 | T43: 0.802 | U43: =Q43*T43 -> 2085.2 | V43: =U43/I43 -> 74.471429 | Z43: 1 | AA43: =VLOOKUP(S43,CPI!$A$2:$E$67,5,0) -> 1.1918391 | AB43: =U43*AA43 -> 2485.2228 | AC43: =V43*AA43 -> 88.757958
A44: 7121 | B44: CA | C44: Ottawa | D44: Line 2/Line 4 | E44: South Extension+Airport Link | F44: 2020 | G44: 2025 | H44: 0 | I44: 20 | J44: 0 | K44: 0 | L44: 0.5 | M44: 15.5 | N44: 13 | O44: 90/120 | P44: Plan | Q44: 1660 | R44: CAD | S44: 2019 | T44: 0.802 | U44: =Q44*T44 -> 1331.32 | V44: =U44/I44 -> 66.566 | AA44: =VLOOKUP(S44,CPI!$A$2:$E$67,5,0) -> 1.1918391 | AB44: =U44*AA44 -> 1586.7192 | AC44: =V44*AA44 -> 79.335959
A45: 7400 | B45: CA | C45: Toronto | D45: Sheppard | E45: Sheppard | F45: 1994 | G45: 2002 | H45: 0 | I45: 5.5 | J45: 1 | K45: 5.5 | L45: 0 | M45: 0 | N45: 5 | P45: Media | Q45: 1000 | R45: CAD | S45: 1998 | T45: 0.81 | U45: =Q45*T45 -> 810 | V45: =U45/I45 -> 147.27273 | W45: =IF(OR(B45 = "BG",B45 = "GR",B45 = "IT",B45 = "ES",B45 = "PT",B45 = "TR", B45 = "KR",B45 = "SE",B45 = "CH",B45 = "NO",B45 = "DK",B45 = "FI"), 1, 0) -> 0 | X45: =W45*I45 -> 0 | Y45: =W45*K45 -> 0 | Z45: =IF(OR(B45 = "US",B45 = "CA",B45 = "UK",B45 = "NZ",B45 = "AU",B45 = "SG"), 1, 0) -> 1 | AA45: =VLOOKUP(S45,CPI!$A$2:$E$67,5,0) -> 1.8693374 | AB45: =U45*AA45 -> 1514.1633 | AC45: =V45*AA45 -> 275.30242
A46: 7108 | B46: CA | C46: Toronto | D46: YUS | E46: Vaughan | F46: 2009 | G46: 2017 | H46: 0 | I46: 8.6 | J46: 1 | K46: 8.6 | L46: 0 | M46: 0 | N46: 6 | P46: Media | Q46: 3200 | R46: CAD | S46: 2013 | T46: 0.81 | U46: =Q46*T46 -> 2592 | V46: =U46/I46 -> 301.39535 | W46: =IF(OR(B46 = "BG",B46 = "GR",B46 = "IT",B46 = "ES",B46 = "PT",B46 = "TR", B46 = "KR",B46 = "SE",B46 = "CH",B46 = "NO",B46 = "DK",B46 = "FI"), 1, 0) -> 0 | X46: =W46*I46 -> 0 | Y46: =W46*K46 -> 0 | Z46: 1 | AA46: =VLOOKUP(S46,CPI!$A$2:$E$67,5,0) -> 1.3079753 | AB46: =U46*AA46 -> 3390.272 | AC46: =V46*AA46 -> 394.21767
A47: 7283 | B47: CA | C47: Toronto | D47: Eglinton Crosstown | E47: Eglinton Crosstown | F47: 2011 | G47: 2025 | H47: 0 | I47: 19 | J47: 0.53 | K47: 10 | L47: 0.62 | M47: 8.31 | N47: 25 | P47: Plan | Q47: 12800 | R47: CAD | S47: 2016 | T47: 0.83 | U47: =Q47*T47 -> 10624 | V47: =U47/I47 -> 559.15789 | W47: =IF(OR(B47 = "BG",B47 = "GR",B47 = "IT",B47 = "ES",B47 = "PT",B47 = "TR", B47 = "KR",B47 = "SE",B47 = "CH",B47 = "NO",B47 = "DK",B47 = "FI"), 1, 0) -> 0 | X47: =W47*I47 -> 0 | Y47: =W47*K47 -> 0 | Z47: =IF(OR(B47 = "US",B47 = "CA",B47 = "UK",B47 = "NZ",B47 = "AU",B47 = "SG"), 1, 0) -> 1 | AA47: =VLOOKUP(S47,CPI!$A$2:$E$67,5,0) -> 1.2695546 | AB47: =U47*AA47 -> 13487.748 | AC47: =V47*AA47 -> 709.8815
A48: 7115 | B48: CA | C48: Toronto | D48: Finch West LRT | E48: Phase 1 | F48: 2019 | G48: 2025 | H48: 0 | I48: 10.3 | J48: =(1/19)% -> 0.00052631579 | K48: 1 | M48: 17 | N48: 18 | O48: 50 | P48: Plan | Q48: 2500 | R48: CAD | S48: 2019 | T48: 0.84 | U48: =Q48*T48 -> 2100 | V48: =U48/I48 -> 203.8835 | AA48: =VLOOKUP(S48,CPI!$A$2:$E$67,5,0) -> 1.1918391 | AB48: =U48*AA48 -> 2502.862 | AC48: =V48*AA48 -> 242.99631
A49: 7109 | B49: CA | C49: Toronto | D49: Bloor/SSE | E49: Scarborough | F49: 2020 | G49: 2030 | H49: 0 | I49: 7.8 | J49: 1 | K49: 7.8 | L49: 0 | M49: 0 | N49: 3 | P49: Wiki | Q49: 5500 | R49: CAD | S49: 2018 | T49: 0.84 | U49: =Q49*T49 -> 4620 | V49: =U49/I49 -> 592.30769 | W49: =IF(OR(B49 = "BG",B49 = "GR",B49 = "IT",B49 = "ES",B49 = "PT",B49 = "TR", B49 = "KR",B49 = "SE",B49 = "CH",B49 = "NO",B49 = "DK",B49 = "FI"), 1, 0) -> 0 | X49: =W49*I49 -> 0 | Y49: =W49*K49 -> 0 | Z49: =IF(OR(B49 = "US",B49 = "CA",B49 = "UK",B49 = "NZ",B49 = "AU",B49 = "SG"), 1, 0) -> 1 | AA49: =VLOOKUP(S49,CPI!$A$2:$E$67,5,0) -> 1.2134349 | AB49: =U49*AA49 -> 5606.0693 | AC49: =V49*AA49 -> 718.72683
A50: 7111 | B50: CA | C50: Toronto | D50: YUS/YNSE | E50: Yonge to Richmond Hill | F50: 2020 | G50: 2030 | H50: 0 | I50: 7.4 | J50: 1 | K50: 7.4 | L50: 0 | M50: 0 | N50: 6 | P50: Plan | Q50: 5600 | R50: CAD | S50: 2020 | T50: 0.84 | U50: =Q50*T50 -> 4704 | V50: =U50/I50 -> 635.67568 | W50: =IF(OR(B50 = "BG",B50 = "GR",B50 = "IT",B50 = "ES",B50 = "PT",B50 = "TR", B50 = "KR",B50 = "SE",B50 = "CH",B50 = "NO",B50 = "DK",B50 = "FI"), 1, 0) -> 0 | X50: =W50*I50 -> 0 | Y50: =W50*K50 -> 0 | Z50: =IF(OR(B50 = "US",B50 = "CA",B50 = "UK",B50 = "NZ",B50 = "AU",B50 = "SG"), 1, 0) -> 1 | AA50: =VLOOKUP(S50,CPI!$A$2:$E$67,5,0) -> 1.1773147 | AB50: =U50*AA50 -> 5538.0884 | AC50: =V50*AA50 -> 748.39033
A51: 7113 | B51: CA | C51: Toronto | D51: Eglinton Crosstown | E51: Phase 1 West | F51: 2022 | G51: 2031 | H51: 0 | I51: 9.2 | J51: =6.8/9.2 -> 0.73913043 | K51: 6.8 | L51: 1.5 | M51: 0.9 | N51: 7 | O51: 50 | P51: Plan | Q51: 2500 | R51: CAD | S51: 2022 | T51: 0.84 | U51: =Q51*T51 -> 2100 | V51: =U51/I51 -> 228.26087 | AA51: =VLOOKUP(S51,CPI!$A$2:$E$67,5,0) -> 1.0411645 | AB51: =U51*AA51 -> 2186.4455 | AC51: =V51*AA51 -> 237.65712
A52: 7110 | B52: CA | C52: Toronto | D52: Ontario Line | E52: Ontario | F52: 2022 | G52: 2031 | H52: 0 | I52: 15.5 | J52: 0.57 | K52: 8.8 | L52: 5.76 | M52: 1.06 | N52: 15 | P52: Plan | Q52: 27200 | R52: CAD | S52: 2023 | T52: 0.84 | U52: =Q52*T52 -> 22848 | V52: =U52/I52 -> 1474.0645 | W52: =IF(OR(B52 = "BG",B52 = "GR",B52 = "IT",B52 = "ES",B52 = "PT",B52 = "TR", B52 = "KR",B52 = "SE",B52 = "CH",B52 = "NO",B52 = "DK",B52 = "FI"), 1, 0) -> 0 | X52: =W52*I52 -> 0 | Y52: =W52*K52 -> 0 | Z52: =IF(OR(B52 = "US",B52 = "CA",B52 = "UK",B52 = "NZ",B52 = "AU",B52 = "SG"), 1, 0) -> 1 | AA52: =VLOOKUP(S52,CPI!$A$2:$E$67,5,0) -> 1 | AB52: =U52*AA52 -> 22848 | AC52: =V52*AA52 -> 1474.0645
A53: 9762 | B53: CA | C53: Vancouver | D53: Millennium Line | E53: Millennium Line Phase 1 | F53: 1998 | G53: 2002 | H53: 0 | I53: 19.9 | J53: 0 | K53: 0 | L53: 0 | M53: 0 | N53: 13 | P53: Wiki | Q53: 1200 | R53: CAD | S53: 2000 | T53: 0.81 | U53: =Q53*T53 -> 972 | V53: =U53/I53 -> 48.844221 | W53: =IF(OR(B53 = "BG",B53 = "GR",B53 = "IT",B53 = "ES",B53 = "PT",B53 = "TR", B53 = "KR",B53 = "SE",B53 = "CH",B53 = "NO",B53 = "DK",B53 = "FI"), 1, 0) -> 0 | X53: =W53*I53 -> 0 | Y53: =W53*K53 -> 0 | Z53: =IF(OR(B53 = "US",B53 = "CA",B53 = "UK",B53 = "NZ",B53 = "AU",B53 = "SG"), 1, 0) -> 1 | AA53: =VLOOKUP(S53,CPI!$A$2:$E$67,5,0) -> 1.7694657 | AB53: =U53*AA53 -> 1719.9207 | AC53: =V53*AA53 -> 86.428176
A54: 9763 | B54: CA | C54: Vancouver | D54: Canada Line | E54: Canada Line | F54: 2005 | G54: 2009 | H54: 0 | I54: 18.4 | J54: 0.49 | K54: 9.1 | L54: 0 | M54: 0 | N54: 16 | P54: Wiki | Q54: 2050 | R54: CAD | S54: 2007 | T54: 0.82 | U54: =Q54*T54 -> 1681 | V54: =U54/I54 -> 91.358696 | W54: =IF(OR(B54 = "BG",B54 = "GR",B54 = "IT",B54 = "ES",B54 = "PT",B54 = "TR", B54 = "KR",B54 = "SE",B54 = "CH",B54 = "NO",B54 = "DK",B54 = "FI"), 1, 0) -> 0 | X54: =W54*I54 -> 0 | Y54: =W54*K54 -> 0 | Z54: =IF(OR(B54 = "US",B54 = "CA",B54 = "UK",B54 = "NZ",B54 = "AU",B54 = "SG"), 1, 0) -> 1 | AA54: =VLOOKUP(S54,CPI!$A$2:$E$67,5,0) -> 1.4695624 | AB54: =U54*AA54 -> 2470.3343 | AC54: =V54*AA54 -> 134.2573
A55: 9764 | B55: CA | C55: Vancouver | D55: Evergreen Line | E55: Evergreen Line | F55: 2012 | G55: 2016 | H55: 0 | I55: 10.9 | J55: 0.18 | K55: 2 | L55: 0 | M55: 0 | N55: 6 | P55: Wiki | Q55: 1430 | R55: CAD | S55: 2014 | T55: 0.81 | U55: =Q55*T55 -> 1158.3 | V55: =U55/I55 -> 106.26605 | W55: =IF(OR(B55 = "BG",B55 = "GR",B55 = "IT",B55 = "ES",B55 = "PT",B55 = "TR", B55 = "KR",B55 = "SE",B55 = "CH",B55 = "NO",B55 = "DK",B55 = "FI"), 1, 0) -> 0 | X55: =W55*I55 -> 0 | Y55: =W55*K55 -> 0 | Z55: =IF(OR(B55 = "US",B55 = "CA",B55 = "UK",B55 = "NZ",B55 = "AU",B55 = "SG"), 1, 0) -> 1 | AA55: =VLOOKUP(S55,CPI!$A$2:$E$67,5,0) -> 1.2870962 | AB55: =U55*AA55 -> 1490.8435 | AC55: =V55*AA55 -> 136.77463
A56: 7136 | B56: CA | C56: Vancouver | D56: Millennium | E56: Broadway | F56: 2020 | G56: 2027 | H56: 0 | I56: 5.7 | J56: =5/5.7 -> 0.87719298 | K56: 5 | L56: 0.295 | M56: 0.446 | N56: 6 | P56: Plan | Q56: 2954 | R56: CAD | S56: 2018 | T56: 0.84 | U56: =Q56*T56 -> 2481.36 | V56: =U56/I56 -> 435.32632 | W56: =IF(OR(B56 = "BG",B56 = "GR",B56 = "IT",B56 = "ES",B56 = "PT",B56 = "TR", B56 = "KR",B56 = "SE",B56 = "CH",B56 = "NO",B56 = "DK",B56 = "FI"), 1, 0) -> 0 | X56: =W56*I56 -> 0 | Y56: =W56*K56 -> 0 | Z56: =IF(OR(B56 = "US",B56 = "CA",B56 = "UK",B56 = "NZ",B56 = "AU",B56 = "SG"), 1, 0) -> 1 | AA56: =VLOOKUP(S56,CPI!$A$2:$E$67,5,0) -> 1.2134349 | AB56: =U56*AA56 -> 3010.9688 | AC56: =V56*AA56 -> 528.24015
A57: 7102 | B57: CA | C57: Vancouver | D57: Surrey Langley SkyTrain | E57: Planning | F57: 2024 | G57: 2029 | H57: 0 | I57: 16 | J57: 0 | K57: 0 | L57: 1 | M57: 0 | N57: 8 | O57: 80 | P57: Plan | Q57: 5996 | R57: CAD | S57: 2024 | T57: 1 | U57: =Q57*T57 -> 5996 | V57: =U57/I57 -> 374.75 | W57: 0 | Z57: 1 | AA57: =VLOOKUP(S57,CPI!$A$2:$E$67,5,0) -> 1 | AB57: =U57*AA57 -> 5996 | AC57: =V57*AA57 -> 374.75
B58: CA | C58: Vancouver | D58: Expo Line | E58: Expo Line Surrey-Langley extension | F58: 2022 | H58: 0 | I58: 16 | J58: 0 | K58: 0 | N58: 8 | Q58: 3940 | R58: CAD | S58: 2021 | T58: 0.798 | U58: =Q58*T58 -> 3144.12 | V58: =U58/I58 -> 196.5075 | W58: =IF(OR(B58 = "BG",B58 = "GR",B58 = "IT",B58 = "ES",B58 = "PT",B58 = "TR", B58 = "KR",B58 = "SE",B58 = "CH",B58 = "NO",B58 = "DK",B58 = "FI"), 1, 0) -> 0 | X58: =W58*I58 -> 0 | Y58: =W58*K58 -> 0 | Z58: =IF(OR(B58 = "US",B58 = "CA",B58 = "UK",B58 = "NZ",B58 = "AU",B58 = "SG"), 1, 0) -> 1 | AA58: =VLOOKUP(S58,CPI!$A$2:$E$67,5,0) -> 1.1244861 | AB58: =U58*AA58 -> 3535.5193 | AC58: =V58*AA58 -> 220.96995
A59: 7560 | B59: CH | C59: Geneva | D59: CEVA | E59: CEVA | F59: 2013 | G59: 2019 | H59: 1 | I59: 8.8 | J59: 0.96 | K59: 8.4 | L59: 0.14 | M59: 0.212 | N59: 4 | P59: Measured | Q59: 1567 | R59: CHF | S59: 2016 | T59: 0.68 | U59: =Q59*T59 -> 1065.56 | V59: =U59/I59 -> 121.08636 | W59: =IF(OR(B59 = "BG",B59 = "GR",B59 = "IT",B59 = "ES",B59 = "PT",B59 = "TR", B59 = "KR",B59 = "SE",B59 = "CH",B59 = "NO",B59 = "DK",B59 = "FI"), 1, 0) -> 1 | X59: =W59*I59 -> 8.8 | Y59: =W59*K59 -> 8.4 | Z59: =IF(OR(B59 = "US",B59 = "CA",B59 = "UK",B59 = "NZ",B59 = "AU",B59 = "SG"), 1, 0) -> 0 | AA59: =VLOOKUP(S59,CPI!$A$2:$E$67,5,0) -> 1.2695546 | AB59: =U59*AA59 -> 1352.7866 | AC59: =V59*AA59 -> 153.72575
B60: CH | C60: Lausanne | D60: Line 2 | E60: Line 2 | F60: 2002 | G60: 2008 | H60: 0 | I60: 6 | K60: 4.5 | L60: 1.5 | M60: 0 | N60: 14 | O60: 30 | P60: Wiki | Q60: 410 | R60: CHF | S60: 2000 | T60: 0.65 | U60: =Q60*T60 -> 266.5 | V60: =U60/I60 -> 44.416667 | W60: =IF(OR(B60 = "BG",B60 = "GR",B60 = "IT",B60 = "ES",B60 = "PT",B60 = "TR", B60 = "KR",B60 = "SE",B60 = "CH",B60 = "NO",B60 = "DK",B60 = "FI"), 1, 0) -> 1 | X60: =W60*I60 -> 6 | Y60: =W60*K60 -> 4.5 | Z60: =IF(OR(B60 = "US",B60 = "CA",B60 = "UK",B60 = "NZ",B60 = "AU",B60 = "SG"), 1, 0) -> 0 | AA60: =VLOOKUP(S60,CPI!$A$2:$E$67,5,0) -> 1.7694657 | AB60: =U60*AA60 -> 471.56262 | AC60: =V60*AA60 -> 78.59377
A61: 7529 | B61: CH | C61: Lucerne | D61: Zentralbahn | E61: Zentralbahn | F61: 2008 | G61: 2013 | H61: 1 | I61: 1.5 | J61: 0.9 | K61: 1.4 | L61: 0 | M61: 0 | N61: 1 | P61: Plan | Q61: 220.2 | R61: CHF | S61: 2010 | T61: 0.68 | U61: =Q61*T61 -> 149.736 | V61: =U61/I61 -> 99.824 | W61: =IF(OR(B61 = "BG",B61 = "GR",B61 = "IT",B61 = "ES",B61 = "PT",B61 = "TR", B61 = "KR",B61 = "SE",B61 = "CH",B61 = "NO",B61 = "DK",B61 = "FI"), 1, 0) -> 1 | X61: =W61*I61 -> 1.5 | Y61: =W61*K61 -> 1.4 | Z61: =IF(OR(B61 = "US",B61 = "CA",B61 = "UK",B61 = "NZ",B61 = "AU",B61 = "SG"), 1, 0) -> 0 | AA61: =VLOOKUP(S61,CPI!$A$2:$E$67,5,0) -> 1.3973566 | AB61: =U61*AA61 -> 209.23459 | AC61: =V61*AA61 -> 139.48973
A62: 7530 | B62: CH | C62: Zurich | D62: Durchmesserlinie | E62: Durchmesserlinie | F62: 2007 | G62: 2014 | H62: 1 | I62: 9.6 | J62: 0.5 | K62: 4.8 | L62: 0.2 | M62: 4.6 | N62: 1 | P62: Trade | Q62: 2030 | R62: CHF | S62: 2010 | T62: 0.68 | U62: =Q62*T62 -> 1380.4 | V62: =U62/I62 -> 143.79167 | W62: =IF(OR(B62 = "BG",B62 = "GR",B62 = "IT",B62 = "ES",B62 = "PT",B62 = "TR", B62 = "KR",B62 = "SE",B62 = "CH",B62 = "NO",B62 = "DK",B62 = "FI"), 1, 0) -> 1 | X62: =W62*I62 -> 9.6 | Y62: =W62*K62 -> 4.8 | Z62: =IF(OR(B62 = "US",B62 = "CA",B62 = "UK",B62 = "NZ",B62 = "AU",B62 = "SG"), 1, 0) -> 0 | AA62: =VLOOKUP(S62,CPI!$A$2:$E$67,5,0) -> 1.3973566 | AB62: =U62*AA62 -> 1928.9111 | AC62: =V62*AA62 -> 200.92824
A63: 7338 | B63: CL | C63: Santiago | D63: Project 63 | E63: Project 63 | F63: 2013 | G63: 2019 | H63: 0 | I63: 37 | J63: 1 | K63: 37 | L63: 0 | M63: 0 | N63: 28 | P63: Plan | Q63: 3000 | R63: USD | S63: 2016 | T63: 1.7 | U63: =Q63*T63 -> 5100 | V63: =U63/I63 -> 137.83784 | W63: =IF(OR(B63 = "BG",B63 = "GR",B63 = "IT",B63 = "ES",B63 = "PT",B63 = "TR", B63 = "KR",B63 = "SE",B63 = "CH",B63 = "NO",B63 = "DK",B63 = "FI"), 1, 0) -> 0 | X63: =W63*I63 -> 0 | Y63: =W63*K63 -> 0 | Z63: =IF(OR(B63 = "US",B63 = "CA",B63 = "UK",B63 = "NZ",B63 = "AU",B63 = "SG"), 1, 0) -> 0 | AA63: =VLOOKUP(S63,CPI!$A$2:$E$67,5,0) -> 1.2695546 | AB63: =U63*AA63 -> 6474.7287 | AC63: =V63*AA63 -> 174.99267
A64: 7337 | B64: CL | C64: Santiago | D64: Line 7 | E64: Line 7 | F64: 2021 | G64: 2026 | H64: 0 | I64: 24.8 | J64: 1 | K64: 24.8 | L64: 0 | M64: 0 | N64: 21 | P64: Plan | Q64: 2900 | R64: USD | S64: 2022 | T64: 1.7 | U64: =Q64*T64 -> 4930 | V64: =U64/I64 -> 198.79032 | W64: =IF(OR(B64 = "BG",B64 = "GR",B64 = "IT",B64 = "ES",B64 = "PT",B64 = "TR", B64 = "KR",B64 = "SE",B64 = "CH",B64 = "NO",B64 = "DK",B64 = "FI"), 1, 0) -> 0 | X64: =W64*I64 -> 0 | Y64: =W64*K64 -> 0 | Z64: =IF(OR(B64 = "US",B64 = "CA",B64 = "UK",B64 = "NZ",B64 = "AU",B64 = "SG"), 1, 0) -> 0 | AA64: =VLOOKUP(S64,CPI!$A$2:$E$67,5,0) -> 1.0411645 | AB64: =U64*AA64 -> 5132.941 | AC64: =V64*AA64 -> 206.97343
A65: 7649 | B65: CN | C65: Beijing | D65: Line 13 | E65: Line 13 | F65: 1999 | G65: 2003 | H65: 0 | I65: 40.85 | J65: 0 | K65: 0 | L65: 13.855 | M65: 26.995 | N65: 17 | O65: 117 | P65: Wiki | Q65: =6.57*10^3 -> 6570 | R65: CNY | S65: 1999 | T65: 0.367 | U65: =Q65*T65 -> 2411.19 | V65: =U65/I65 -> 59.025459 | W65: =IF(OR(B65 = "BG",B65 = "GR",B65 = "IT",B65 = "ES",B65 = "PT",B65 = "TR", B65 = "KR",B65 = "SE",B65 = "CH",B65 = "NO",B65 = "DK",B65 = "FI"), 1, 0) -> 0 | X65: =W65*I65 -> 0 | Y65: =W65*K65 -> 0 | Z65: =IF(OR(B65 = "US",B65 = "CA",B65 = "UK",B65 = "NZ",B65 = "AU",B65 = "SG"), 1, 0) -> 0 | AA65: =VLOOKUP(S65,CPI!$A$2:$E$67,5,0) -> 1.8289436 | AB65: =U65*AA65 -> 4409.9305 | AC65: =V65*AA65 -> 107.95423
A66: 8065 | B66: CN | C66: Beijing | D66: Line 5 | E66: Line 5 | F66: 2002 | G66: 2007 | H66: 0 | I66: 27.6 | L66: #N/A | M66: #N/A | N66: 23 | P66: Media | Q66: 12000 | R66: CNY | S66: 2004 | T66: 0.355 | U66: =T66*Q66 -> 4260 | V66: =U66/I66 -> 154.34783 | W66: =IF(OR(B66 = "BG",B66 = "GR",B66 = "IT",B66 = "ES",B66 = "PT",B66 = "TR", B66 = "KR",B66 = "SE",B66 = "CH",B66 = "NO",B66 = "DK",B66 = "FI"), 1, 0) -> 0 | X66: =W66*I66 -> 0 | Y66: =W66*K66 -> 0 | Z66: =IF(OR(B66 = "US",B66 = "CA",B66 = "UK",B66 = "NZ",B66 = "AU",B66 = "SG"), 1, 0) -> 0 | AA66: =VLOOKUP(S66,CPI!$A$2:$E$67,5,0) -> 1.6130334 | AB66: =U66*AA66 -> 6871.5221 | AC66: =V66*AA66 -> 248.96819
A67: 7960 | B67: CN | C67: Beijing | D67: Line 10 | E67: Line 10 North and East | F67: 2003 | G67: 2008 | H67: 0 | I67: 24.64 | J67: 1 | K67: 24.64 | L67: 0 | M67: 0 | N67: 22 | P67: Media | Q67: 13700 | R67: CNY | S67: 2005 | T67: 0.3519 | U67: =Q67*T67 -> 4821.03 | V67: =U67/I67 -> 195.65869 | W67: =IF(OR(B67 = "BG",B67 = "GR",B67 = "IT",B67 = "ES",B67 = "PT",B67 = "TR", B67 = "KR",B67 = "SE",B67 = "CH",B67 = "NO",B67 = "DK",B67 = "FI"), 1, 0) -> 0 | X67: =W67*I67 -> 0 | Y67: =W67*K67 -> 0 | Z67: =IF(OR(B67 = "US",B67 = "CA",B67 = "UK",B67 = "NZ",B67 = "AU",B67 = "SG"), 1, 0) -> 0 | AA67: =VLOOKUP(S67,CPI!$A$2:$E$67,5,0) -> 1.5601741 | AB67: =U67*AA67 -> 7521.6461 | AC67: =V67*AA67 -> 305.26161
A68: 8139 | B68: CN | C68: Beijing | D68: Capital Airport Express | E68: Capital Airport Express | F68: 2005 | G68: 2008 | H68: 0 | I68: 28.1 | J68: 0 | K68: 0 | L68: 17.315 | M68: 10.785 | N68: 4 | P68: Measured | Q68: 622.3 | R68: CNY | S68: 2005 | T68: 0.3519 | U68: =T68*Q68 -> 218.98737 | V68: =U68/I68 -> 7.7931448 | W68: =IF(OR(B68 = "BG",B68 = "GR",B68 = "IT",B68 = "ES",B68 = "PT",B68 = "TR", B68 = "KR",B68 = "SE",B68 = "CH",B68 = "NO",B68 = "DK",B68 = "FI"), 1, 0) -> 0 | X68: =W68*I68 -> 0 | Y68: =W68*K68 -> 0 | Z68: =IF(OR(B68 = "US",B68 = "CA",B68 = "UK",B68 = "NZ",B68 = "AU",B68 = "SG"), 1, 0) -> 0 | AA68: =VLOOKUP(S68,CPI!$A$2:$E$67,5,0) -> 1.5601741 | AB68: =U68*AA68 -> 341.65842 | AC68: =V68*AA68 -> 12.158663
A69: 7987 | B69: CN | C69: Beijing | D69: Line 8 | E69: Line 8 Phase 1 for Olympics | F69: 2005 | G69: 2008 | H69: 0 | I69: 4.528 | J69: 1 | K69: 4.528 | L69: 0 | M69: 0 | N69: 4 | P69: Media | Q69: 2420 | R69: CNY | S69: 2005 | T69: 0.3519 | U69: =T69*Q69 -> 851.598 | V69: =U69/I69 -> 188.07376 | W69: =IF(OR(B69 = "BG",B69 = "GR",B69 = "IT",B69 = "ES",B69 = "PT",B69 = "TR", B69 = "KR",B69 = "SE",B69 = "CH",B69 = "NO",B69 = "DK",B69 = "FI"), 1, 0) -> 0 | X69: =W69*I69 -> 0 | Y69: =W69*K69 -> 0 | Z69: =IF(OR(B69 = "US",B69 = "CA",B69 = "UK",B69 = "NZ",B69 = "AU",B69 = "SG"), 1, 0) -> 0 | AA69: =VLOOKUP(S69,CPI!$A$2:$E$67,5,0) -> 1.5601741 | AB69: =U69*AA69 -> 1328.6411 | AC69: =V69*AA69 -> 293.42781
A70: 7640 | B70: CN | C70: Beijing | D70: Line 4 | E70: Line 4 | F70: 2004 | G70: 2009 | H70: 0 | I70: 28.2 | J70: =K70/I70 -> 0.95166667 | K70: 26.837 | L70: 0 | M70: 0 | N70: 24 | O70: 117 | P70: Media | Q70: 15380 | R70: CNY | S70: 2005 | T70: 0.3519 | U70: =Q70*T70 -> 5412.222 | V70: =U70/I70 -> 191.92277 | W70: =IF(OR(B70 = "BG",B70 = "GR",B70 = "IT",B70 = "ES",B70 = "PT",B70 = "TR", B70 = "KR",B70 = "SE",B70 = "CH",B70 = "NO",B70 = "DK",B70 = "FI"), 1, 0) -> 0 | X70: =W70*I70 -> 0 | Y70: =W70*K70 -> 0 | Z70: =IF(OR(B70 = "US",B70 = "CA",B70 = "UK",B70 = "NZ",B70 = "AU",B70 = "SG"), 1, 0) -> 0 | AA70: =VLOOKUP(S70,CPI!$A$2:$E$67,5,0) -> 1.5601741 | AB70: =U70*AA70 -> 8444.0085 | AC70: =V70*AA70 -> 299.43293
A71: 8041 | B71: CN | C71: Beijing | D71: Daxing Line | E71: Daxing Line | F71: 2007 | G71: 2010 | H71: 0 | I71: 21.8 | J71: 0.80275229 | K71: 17.5 | L71: 4.36 | M71: 0 | N71: 11 | P71: Media | Q71: 10930 | R71: CNY | S71: 2007 | T71: 0.333 | U71: =T71*Q71 -> 3639.69 | V71: =U71/I71 -> 166.95826 | W71: =IF(OR(B71 = "BG",B71 = "GR",B71 = "IT",B71 = "ES",B71 = "PT",B71 = "TR", B71 = "KR",B71 = "SE",B71 = "CH",B71 = "NO",B71 = "DK",B71 = "FI"), 1, 0) -> 0 | X71: =W71*I71 -> 0 | Y71: =W71*K71 -> 0 | Z71: =IF(OR(B71 = "US",B71 = "CA",B71 = "UK",B71 = "NZ",B71 = "AU",B71 = "SG"), 1, 0) -> 0 | AA71: =VLOOKUP(S71,CPI!$A$2:$E$67,5,0) -> 1.4695624 | AB71: =U71*AA71 -> 5348.7514 | AC71: =V71*AA71 -> 245.35557
B72: CN | C72: Beijing | D72: Line 9 | E72: Line 9 | F72: 2007 | G72: 2012 | H72: 0 | I72: 16.5 | J72: 1 | K72: 16.5 | N72: 13 | O72: 117 | Q72: 12900 | R72: CNY | S72: 2010 | T72: 0.3 | U72: =Q72*T72 -> 3870 | V72: =U72/I72 -> 234.54545 | W72: =IF(OR(B72 = "BG",B72 = "GR",B72 = "IT",B72 = "ES",B72 = "PT",B72 = "TR", B72 = "KR",B72 = "SE",B72 = "CH",B72 = "NO",B72 = "DK",B72 = "FI"), 1, 0) -> 0 | X72: =W72*I72 -> 0 | Y72: =W72*K72 -> 0 | Z72: =IF(OR(B72 = "US",B72 = "CA",B72 = "UK",B72 = "NZ",B72 = "AU",B72 = "SG"), 1, 0) -> 0 | AA72: =VLOOKUP(S72,CPI!$A$2:$E$67,5,0) -> 1.3973566 | AB72: =U72*AA72 -> 5407.7702 | AC72: =V72*AA72 -> 327.74365
A73: 7832 | B73: CN | C73: Beijing | D73: Line 6 | E73: Line 6 Phase 1 | F73: 2008 | G73: 2012 | H73: 0 | I73: 30.4 | J73: 1 | K73: 30.4 | N73: 20 | O73: 156 | P73: Wiki | Q73: 28000 | R73: CNY | S73: 2010 | T73: 0.3 | U73: =Q73*T73 -> 8400 | V73: =U73/I73 -> 276.31579 | W73: =IF(OR(B73 = "BG",B73 = "GR",B73 = "IT",B73 = "ES",B73 = "PT",B73 = "TR", B73 = "KR",B73 = "SE",B73 = "CH",B73 = "NO",B73 = "DK",B73 = "FI"), 1, 0) -> 0 | X73: =W73*I73 -> 0 | Y73: =W73*K73 -> 0 | Z73: =IF(OR(B73 = "US",B73 = "CA",B73 = "UK",B73 = "NZ",B73 = "AU",B73 = "SG"), 1, 0) -> 0 | AA73: =VLOOKUP(S73,CPI!$A$2:$E$67,5,0) -> 1.3973566 | AB73: =U73*AA73 -> 11737.796 | AC73: =V73*AA73 -> 386.1117
A74: 8131 | B74: CN | C74: Beijing | D74: Line 8 | E74: Line 8 Northern Extension | F74: 2011 | G74: 2013 | H74: 0 | I74: 6.328 | J74: 0.73451327 | K74: 4.648 | L74: 1.7091 | M74: 0 | N74: 3 | P74: Measured | Q74: 3212.2 | R74: CNY | S74: 2011 | T74: 0.284 | U74: =T74*Q74 -> 912.2648 | V74: =U74/I74 -> 144.16321 | W74: =IF(OR(B74 = "BG",B74 = "GR",B74 = "IT",B74 = "ES",B74 = "PT",B74 = "TR", B74 = "KR",B74 = "SE",B74 = "CH",B74 = "NO",B74 = "DK",B74 = "FI"), 1, 0) -> 0 | X74: =W74*I74 -> 0 | Y74: =W74*K74 -> 0 | Z74: =IF(OR(B74 = "US",B74 = "CA",B74 = "UK",B74 = "NZ",B74 = "AU",B74 = "SG"), 1, 0) -> 0 | AA74: =VLOOKUP(S74,CPI!$A$2:$E$67,5,0) -> 1.3545984 | AB74: =U74*AA74 -> 1235.7524 | AC74: =V74*AA74 -> 195.28325
A75: 8112 | B75: CN | C75: Beijing | D75: Line 15 | E75: Line 15 Phase 1 | F75: 2009 | G75: 2014 | H75: 0 | I75: 41.4 | J75: 0.66908213 | K75: 27.7 | L75: 13.605 | M75: 0.471 | N75: 18 | O75: 117 | P75: Media | Q75: 18100 | R75: CNY | S75: 2010 | T75: 0.3 | U75: =T75*Q75 -> 5430 | V75: =U75/I75 -> 131.15942 | W75: =IF(OR(B75 = "BG",B75 = "GR",B75 = "IT",B75 = "ES",B75 = "PT",B75 = "TR", B75 = "KR",B75 = "SE",B75 = "CH",B75 = "NO",B75 = "DK",B75 = "FI"), 1, 0) -> 0 | X75: =W75*I75 -> 0 | Y75: =W75*K75 -> 0 | Z75: =IF(OR(B75 = "US",B75 = "CA",B75 = "UK",B75 = "NZ",B75 = "AU",B75 = "SG"), 1, 0) -> 0 | AA75: =VLOOKUP(S75,CPI!$A$2:$E$67,5,0) -> 1.3973566 | AB75: =U75*AA75 -> 7587.6466 | AC75: =V75*AA75 -> 183.27649
